Workbook
Name DepartmentFilterList: Employee_Lookups!$O$4:$O$10
Name ReportingYearList: Employee_Lookups!$P$4:$P$10

Sheet Dashboard
B1: NEXACORE TECHNOLOGIES — EXECUTIVE HR & WORKFORCE ANALYTICS DASHBOARD
B2: Observation Window: FY 2019 – FY 2025 | Reporting Cutoff: 2025-12-31 | Synthetic Portfolio Dataset (n = 1,450 Unique Employees)
B4: Select Department Filter: | C4: All Departments | E4: Select Reporting Year: | F4: 2025 | H4: Department filter updates workforce KPIs; year filter updates hires and exits. Attrition KPI is fixed to FY2025.
B6: ACTIVE HEADCOUNT (AS OF CUTOFF) | D6: NEW HIRES (SELECTED YEAR) | F6: TOTAL EXITS (SELECTED YEAR) | H6: FY2025 ATTRITION RATE | J6: AVG TENURE (ACTIVE STAFF) | L6: ACTIVE OVERTIME PARTICIPATION
B7: =IF($C$4="All Departments",KPI_Calculations!D12,INDEX(KPI_Calculations!D6:D11,MATCH($C$4,KPI_Calculations!A6:A11,0))) -> 1042 | D7: =IF($C$4="All Departments",COUNTIF(Cleaned_Data!$AB$2:$AB$1451,$F$4),COUNTIFS(Cleaned_Data!$D$2:$D$1451,$C$4,Cleaned_Data!$AB$2:$AB$1451,$F$4)) -> 221 | F7: =IF($C$4="All Departments",COUNTIF(Cleaned_Data!$AC$2:$AC$1451,$F$4),COUNTIFS(Cleaned_Data!$D$2:$D$1451,$C$4,Cleaned_Data!$AC$2:$AC$1451,$F$4)) -> 102 | H7: =IF($C$4="All Departments",KPI_Calculations!N12,INDEX(KPI_Calculations!N6:N11,MATCH($C$4,KPI_Calculations!A6:A11,0))) -> 0.10381679 | J7: =IF($C$4="All Departments",KPI_Calculations!O12,INDEX(KPI_Calculations!O6:O11,MATCH($C$4,KPI_Calculations!A6:A11,0))) -> 2.6975048 | L7: =IF($C$4="All Departments",KPI_Calculations!R12,INDEX(KPI_Calculations!R6:R11,MATCH($C$4,KPI_Calculations!A6:A11,0))) -> 0.3646833
B8: ="Target: "&TEXT(IF($C$4="All Departments",KPI_Calculations!C12,INDEX(KPI_Calculations!C6:C11,MATCH($C$4,KPI_Calculations!A6:A11,0))),"#,##0")&" | Variance: "&TEXT(IF($C$4="All Departments",KPI_Calculations!E12,INDEX(KPI_Calculations!E6:E11,MATCH($C$4,KPI_Calculations!A6:A11,0))),"+0;-0;0") -> Target: 1,095 | Variance: -53 | D8: ="Total Cohort Hired (19-25): "&TEXT(IF($C$4="All Departments",KPI_Calculations!F12,INDEX(KPI_Calculations!F6:F11,MATCH($C$4,KPI_Calculations!A6:A11,0))),"#,##0") -> Total Cohort Hired (19-25): 1,450 | F8: ="Cumulative Exits (19-25): "&TEXT(IF($C$4="All Departments",KPI_Calculations!G12,INDEX(KPI_Calculations!G6:G11,MATCH($C$4,KPI_Calculations!A6:A11,0))),"#,##0") -> Cumulative Exits (19-25): 408 | H8: ="Cohort Attrition: "&TEXT(IF($C$4="All Departments",KPI_Calculations!I12,INDEX(KPI_Calculations!I6:I11,MATCH($C$4,KPI_Calculations!A6:A11,0))),"0.0%") -> Cohort Attrition: 28.1% | J8: ="Avg Perf Rating: "&TEXT(IF($C$4="All Departments",KPI_Calculations!Q12,INDEX(KPI_Calculations!Q6:Q11,MATCH($C$4,KPI_Calculations!A6:A11,0))),"0.00")&" / 5.0" -> Avg Perf Rating: 3.19 / 5.0 | L8: ="High Retention Risk Active: "&TEXT(IF($C$4="All Departments",Pivot_Analysis!B33,INDEX(Pivot_Analysis!B27:B32,MATCH($C$4,Pivot_Analysis!A27:A32,0))),"#,##0") -> High Retention Risk Active: 203
B10: Department Workforce, Attrition & Risk Scorecard (With Exception Highlighting) | J10: Executive Insights & Recommended Management Actions
B11: Department | C11: Active HC | D11: HC Variance | E11: FY25 Attrition % | F11: Cohort Attrition % | G11: Overtime % | H11: High Risk Staff | J11: 1. Overtime & Turnover Hotspot (Sales & Ops):
B12: =KPI_Calculations!A6 -> Engineering & Product | C12: =KPI_Calculations!D6 -> 366 | D12: =KPI_Calculations!E6 -> -14 | E12: =KPI_Calculations!N6 -> 0.083333333 | F12: =KPI_Calculations!I6 -> 0.21290323 | G12: =KPI_Calculations!R6 -> 0.2704918 | H12: =Pivot_Analysis!B27 -> 54 | J12: Enterprise Sales (52.2% OT, 15.1% FY25 attrition) and Customer Ops (51.2% OT, 37.1% cohort attrition) lead turnover. Action: Audit workload & fill -26 open roles.
B13: =KPI_Calculations!A7 -> Enterprise Sales | C13: =KPI_Calculations!D7 -> 201 | D13: =KPI_Calculations!E7 -> -14 | E13: =KPI_Calculations!N7 -> 0.15143603 | F13: =KPI_Calculations!I7 -> 0.33222591 | G13: =KPI_Calculations!R7 -> 0.52238806 | H13: =Pivot_Analysis!B28 -> 53 | J13: 2. External Agency ROI Deficit:
B14: =KPI_Calculations!A8 -> Customer Operations | C14: =KPI_Calculations!D8 -> 168 | D14: =KPI_Calculations!E8 -> -12 | E14: =KPI_Calculations!N8 -> 0.11538462 | F14: =KPI_Calculations!I8 -> 0.37078652 | G14: =KPI_Calculations!R8 -> 0.51190476 | H14: =Pivot_Analysis!B29 -> 44 | J14: External Agencies cost ₹145k/hire (2.4x weighted avg) yet show 40.4% cohort attrition & 21.7% first-year attrition vs. Employee Referrals (20.0% cohort attrition at ₹42k). Action: Shift budget to Referrals.
B15: =KPI_Calculations!A9 -> Growth Marketing | C15: =KPI_Calculations!D9 -> 119 | D15: =KPI_Calculations!E9 -> -6 | E15: =KPI_Calculations!N9 -> 0.14414414 | F15: =KPI_Calculations!I9 -> 0.31609195 | G15: =KPI_Calculations!R9 -> 0.31092437 | H15: =Pivot_Analysis!B30 -> 20 | J15: 3. Entry-Level (L1) Onboarding Risk:
B16: =KPI_Calculations!A10 -> Finance & Strategy | C16: =KPI_Calculations!D10 -> 96 | D16: =KPI_Calculations!E10 -> -4 | E16: =KPI_Calculations!N10 -> 0.055248619 | F16: =KPI_Calculations!I10 -> 0.24409449 | G16: =KPI_Calculations!R10 -> 0.29166667 | H16: =Pivot_Analysis!B31 -> 17 | J16: L1 Associates represent 50.2% of all historical exits (34.9% attrition), and 64.0% of all exits occur in Year 1. Action: Launch 30-60-90 day L1 structured check-ins.
B17: =KPI_Calculations!A11 -> People & Talent | C17: =KPI_Calculations!D11 -> 92 | D17: =KPI_Calculations!E11 -> -3 | E17: =KPI_Calculations!N11 -> 0.058479532 | F17: =KPI_Calculations!I11 -> 0.20689655 | G17: =KPI_Calculations!R11 -> 0.27173913 | H17: =Pivot_Analysis!B32 -> 15 | J17: 4. Hybrid Hub vs. Remote Retention:
B18: Organization Total / Avg | C18: =KPI_Calculations!D12 -> 1042 | D18: =KPI_Calculations!E12 -> -53 | E18: =KPI_Calculations!N12 -> 0.10381679 | F18: =KPI_Calculations!I12 -> 0.28137931 | G18: =KPI_Calculations!R12 -> 0.3646833 | H18: =Pivot_Analysis!B33 -> 203 | J18: Remote-India cohort attrition is 14.3% vs. Pune (31.5%) and Bengaluru (29.4%). Action: Review commute/flexibility policies in Pune & Bengaluru delivery centers.

Sheet KPI_Calculations
A1: WORKFORCE ANALYTICS FORMULA ENGINE (SUMIF/S, COUNTIF/S, AVERAGEIF/S, VLOOKUP, INDEX/MATCH, XLOOKUP, SUMPRODUCT)
A2: All summary tables dynamically calculate from 'Cleaned_Data' ($A$2:$AF$1451) and 'Employee_Lookups' and feed the Executive Dashboard.
A4: 1. Department-Wise Headcount, Attrition, Tenure, Overtime & Budget Variance
A5: Department | B5: Dept_Code | C5: Approved_HC_Target | D5: Active_Headcount | E5: HC_Target_Variance | F5: Total_Historical_Hires | G5: Total_Historical_Exits | H5: Voluntary_Exits | I5: Cumulative_Cohort_Attrition_% | J5: FY2025_Starting_HC | K5: FY2025_Hires | L5: FY2025_Exits | M5: FY2025_Avg_HC | N5: FY2025_Annual_Attrition_% | O5: Avg_Tenure_Active_Yrs | P5: Avg_Active_Salary_INR | Q5: Avg_Perf_Rating | R5: Active_Overtime_%
A6: Engineering & Product | B6: DEP-ENG | C6: =VLOOKUP(B6,Employee_Lookups!$A$4:$G$9,5,FALSE()) -> 380 | D6: =COUNTIFS(Cleaned_Data!$D$2:$D$1451,A6,Cleaned_Data!$K$2:$K$1451,"Active") -> 366 | E6: =D6-C6 -> -14 | F6: =COUNTIF(Cleaned_Data!$D$2:$D$1451,A6) -> 465 | G6: =COUNTIFS(Cleaned_Data!$D$2:$D$1451,A6,Cleaned_Data!$K$2:$K$1451,"<>Active") -> 99 | H6: =COUNTIFS(Cleaned_Data!$D$2:$D$1451,A6,Cleaned_Data!$K$2:$K$1451,"Voluntary Exit") -> 63 | I6: =IFERROR(G6/F6,0) -> 0.21290323 | J6: =COUNTIFS(Cleaned_Data!$D$2:$D$1451,A6,Cleaned_Data!$AB$2:$AB$1451,"<=2024")-COUNTIFS(Cleaned_Data!$D$2:$D$1451,A6,Cleaned_Data!$AB$2:$AB$1451,"<=2024",Cleaned_Data!$AC$2:$AC$1451,"<=2024",Cleaned_Data!$AC$2:$AC$1451,">0") -> 330 | K6: =COUNTIFS(Cleaned_Data!$D$2:$D$1451,A6,Cleaned_Data!$AB$2:$AB$1451,2025) -> 65 | L6: =COUNTIFS(Cleaned_Data!$D$2:$D$1451,A6,Cleaned_Data!$AC$2:$AC$1451,2025) -> 29 | M6: =(J6+D6)/2 -> 348 | N6: =IFERROR(L6/M6,0) -> 0.083333333 | O6: =AVERAGEIFS(Cleaned_Data!$AD$2:$AD$1451,Cleaned_Data!$D$2:$D$1451,A6,Cleaned_Data!$K$2:$K$1451,"Active") -> 2.7999454 | P6: =AVERAGEIFS(Cleaned_Data!$O$2:$O$1451,Cleaned_Data!$D$2:$D$1451,A6,Cleaned_Data!$K$2:$K$1451,"Active") -> 1297612 | Q6: =AVERAGEIFS(Cleaned_Data!$P$2:$P$1451,Cleaned_Data!$D$2:$D$1451,A6,Cleaned_Data!$P$2:$P$1451,">0") -> 3.2171053 | R6: =IFERROR(COUNTIFS(Cleaned_Data!$D$2:$D$1451,A6,Cleaned_Data!$K$2:$K$1451,"Active",Cleaned_Data!$Q$2:$Q$1451,"Yes")/D6,0) -> 0.2704918
A7: Enterprise Sales | B7: DEP-SAL | C7: =VLOOKUP(B7,Employee_Lookups!$A$4:$G$9,5,FALSE()) -> 215 | D7: =COUNTIFS(Cleaned_Data!$D$2:$D$1451,A7,Cleaned_Data!$K$2:$K$1451,"Active") -> 201 | E7: =D7-C7 -> -14 | F7: =COUNTIF(Cleaned_Data!$D$2:$D$1451,A7) -> 301 | G7: =COUNTIFS(Cleaned_Data!$D$2:$D$1451,A7,Cleaned_Data!$K$2:$K$1451,"<>Active") -> 100 | H7: =COUNTIFS(Cleaned_Data!$D$2:$D$1451,A7,Cleaned_Data!$K$2:$K$1451,"Voluntary Exit") -> 67 | I7: =IFERROR(G7/F7,0) -> 0.33222591 | J7: =COUNTIFS(Cleaned_Data!$D$2:$D$1451,A7,Cleaned_Data!$AB$2:$AB$1451,"<=2024")-COUNTIFS(Cleaned_Data!$D$2:$D$1451,A7,Cleaned_Data!$AB$2:$AB$1451,"<=2024",Cleaned_Data!$AC$2:$AC$1451,"<=2024",Cleaned_Data!$AC$2:$AC$1451,">0") -> 182 | K7: =COUNTIFS(Cleaned_Data!$D$2:$D$1451,A7,Cleaned_Data!$AB$2:$AB$1451,2025) -> 48 | L7: =COUNTIFS(Cleaned_Data!$D$2:$D$1451,A7,Cleaned_Data!$AC$2:$AC$1451,2025) -> 29 | M7: =(J7+D7)/2 -> 191.5 | N7: =IFERROR(L7/M7,0) -> 0.15143603 | O7: =AVERAGEIFS(Cleaned_Data!$AD$2:$AD$1451,Cleaned_Data!$D$2:$D$1451,A7,Cleaned_Data!$K$2:$K$1451,"Active") -> 2.4998507 | P7: =AVERAGEIFS(Cleaned_Data!$O$2:$O$1451,Cleaned_Data!$D$2:$D$1451,A7,Cleaned_Data!$K$2:$K$1451,"Active") -> 1294432.8 | Q7: =AVERAGEIFS(Cleaned_Data!$P$2:$P$1451,Cleaned_Data!$D$2:$D$1451,A7,Cleaned_Data!$P$2:$P$1451,">0") -> 3.1190476 | R7: =IFERROR(COUNTIFS(Cleaned_Data!$D$2:$D$1451,A7,Cleaned_Data!$K$2:$K$1451,"Active",Cleaned_Data!$Q$2:$Q$1451,"Yes")/D7,0) -> 0.52238806
A8: Customer Operations | B8: DEP-OPS | C8: =VLOOKUP(B8,Employee_Lookups!$A$4:$G$9,5,FALSE()) -> 180 | D8: =COUNTIFS(Cleaned_Data!$D$2:$D$1451,A8,Cleaned_Data!$K$2:$K$1451,"Active") -> 168 | E8: =D8-C8 -> -12 | F8: =COUNTIF(Cleaned_Data!$D$2:$D$1451,A8) -> 267 | G8: =COUNTIFS(Cleaned_Data!$D$2:$D$1451,A8,Cleaned_Data!$K$2:$K$1451,"<>Active") -> 99 | H8: =COUNTIFS(Cleaned_Data!$D$2:$D$1451,A8,Cleaned_Data!$K$2:$K$1451,"Voluntary Exit") -> 61 | I8: =IFERROR(G8/F8,0) -> 0.37078652 | J8: =COUNTIFS(Cleaned_Data!$D$2:$D$1451,A8,Cleaned_Data!$AB$2:$AB$1451,"<=2024")-COUNTIFS(Cleaned_Data!$D$2:$D$1451,A8,Cleaned_Data!$AB$2:$AB$1451,"<=2024",Cleaned_Data!$AC$2:$AC$1451,"<=2024",Cleaned_Data!$AC$2:$AC$1451,">0") -> 144 | K8: =COUNTIFS(Cleaned_Data!$D$2:$D$1451,A8,Cleaned_Data!$AB$2:$AB$1451,2025) -> 42 | L8: =COUNTIFS(Cleaned_Data!$D$2:$D$1451,A8,Cleaned_Data!$AC$2:$AC$1451,2025) -> 18 | M8: =(J8+D8)/2 -> 156 | N8: =IFERROR(L8/M8,0) -> 0.11538462 | O8: =AVERAGEIFS(Cleaned_Data!$AD$2:$AD$1451,Cleaned_Data!$D$2:$D$1451,A8,Cleaned_Data!$K$2:$K$1451,"Active") -> 2.5744643 | P8: =AVERAGEIFS(Cleaned_Data!$O$2:$O$1451,Cleaned_Data!$D$2:$D$1451,A8,Cleaned_Data!$K$2:$K$1451,"Active") -> 1383113.1 | Q8: =AVERAGEIFS(Cleaned_Data!$P$2:$P$1451,Cleaned_Data!$D$2:$D$1451,A8,Cleaned_Data!$P$2:$P$1451,">0") -> 3.1030534 | R8: =IFERROR(COUNTIFS(Cleaned_Data!$D$2:$D$1451,A8,Cleaned_Data!$K$2:$K$1451,"Active",Cleaned_Data!$Q$2:$Q$1451,"Yes")/D8,0) -> 0.51190476
A9: Growth Marketing | B9: DEP-MKT | C9: =VLOOKUP(B9,Employee_Lookups!$A$4:$G$9,5,FALSE()) -> 125 | D9: =COUNTIFS(Cleaned_Data!$D$2:$D$1451,A9,Cleaned_Data!$K$2:$K$1451,"Active") -> 119 | E9: =D9-C9 -> -6 | F9: =COUNTIF(Cleaned_Data!$D$2:$D$1451,A9) -> 174 | G9: =COUNTIFS(Cleaned_Data!$D$2:$D$1451,A9,Cleaned_Data!$K$2:$K$1451,"<>Active") -> 55 | H9: =COUNTIFS(Cleaned_Data!$D$2:$D$1451,A9,Cleaned_Data!$K$2:$K$1451,"Voluntary Exit") -> 37 | I9: =IFERROR(G9/F9,0) -> 0.31609195 | J9: =COUNTIFS(Cleaned_Data!$D$2:$D$1451,A9,Cleaned_Data!$AB$2:$AB$1451,"<=2024")-COUNTIFS(Cleaned_Data!$D$2:$D$1451,A9,Cleaned_Data!$AB$2:$AB$1451,"<=2024",Cleaned_Data!$AC$2:$AC$1451,"<=2024",Cleaned_Data!$AC$2:$AC$1451,">0") -> 103 | K9: =COUNTIFS(Cleaned_Data!$D$2:$D$1451,A9,Cleaned_Data!$AB$2:$AB$1451,2025) -> 32 | L9: =COUNTIFS(Cleaned_Data!$D$2:$D$1451,A9,Cleaned_Data!$AC$2:$AC$1451,2025) -> 16 | M9: =(J9+D9)/2 -> 111 | N9: =IFERROR(L9/M9,0) -> 0.14414414 | O9: =AVERAGEIFS(Cleaned_Data!$AD$2:$AD$1451,Cleaned_Data!$D$2:$D$1451,A9,Cleaned_Data!$K$2:$K$1451,"Active") -> 2.3438655 | P9: =AVERAGEIFS(Cleaned_Data!$O$2:$O$1451,Cleaned_Data!$D$2:$D$1451,A9,Cleaned_Data!$K$2:$K$1451,"Active") -> 1261159.7 | Q9: =AVERAGEIFS(Cleaned_Data!$P$2:$P$1451,Cleaned_Data!$D$2:$D$1451,A9,Cleaned_Data!$P$2:$P$1451,">0") -> 3.2559524 | R9: =IFERROR(COUNTIFS(Cleaned_Data!$D$2:$D$1451,A9,Cleaned_Data!$K$2:$K$1451,"Active",Cleaned_Data!$Q$2:$Q$1451,"Yes")/D9,0) -> 0.31092437
A10: Finance & Strategy | B10: DEP-FIN | C10: =VLOOKUP(B10,Employee_Lookups!$A$4:$G$9,5,FALSE()) -> 100 | D10: =COUNTIFS(Cleaned_Data!$D$2:$D$1451,A10,Cleaned_Data!$K$2:$K$1451,"Active") -> 96 | E10: =D10-C10 -> -4 | F10: =COUNTIF(Cleaned_Data!$D$2:$D$1451,A10) -> 127 | G10: =COUNTIFS(Cleaned_Data!$D$2:$D$1451,A10,Cleaned_Data!$K$2:$K$1451,"<>Active") -> 31 | H10: =COUNTIFS(Cleaned_Data!$D$2:$D$1451,A10,Cleaned_Data!$K$2:$K$1451,"Voluntary Exit") -> 21 | I10: =IFERROR(G10/F10,0) -> 0.24409449 | J10: =COUNTIFS(Cleaned_Data!$D$2:$D$1451,A10,Cleaned_Data!$AB$2:$AB$1451,"<=2024")-COUNTIFS(Cleaned_Data!$D$2:$D$1451,A10,Cleaned_Data!$AB$2:$AB$1451,"<=2024",Cleaned_Data!$AC$2:$AC$1451,"<=2024",Cleaned_Data!$AC$2:$AC$1451,">0") -> 85 | K10: =COUNTIFS(Cleaned_Data!$D$2:$D$1451,A10,Cleaned_Data!$AB$2:$AB$1451,2025) -> 16 | L10: =COUNTIFS(Cleaned_Data!$D$2:$D$1451,A10,Cleaned_Data!$AC$2:$AC$1451,2025) -> 5 | M10: =(J10+D10)/2 -> 90.5 | N10: =IFERROR(L10/M10,0) -> 0.055248619 | O10: =AVERAGEIFS(Cleaned_Data!$AD$2:$AD$1451,Cleaned_Data!$D$2:$D$1451,A10,Cleaned_Data!$K$2:$K$1451,"Active") -> 3.2403125 | P10: =AVERAGEIFS(Cleaned_Data!$O$2:$O$1451,Cleaned_Data!$D$2:$D$1451,A10,Cleaned_Data!$K$2:$K$1451,"Active") -> 1176114.6 | Q10: =AVERAGEIFS(Cleaned_Data!$P$2:$P$1451,Cleaned_Data!$D$2:$D$1451,A10,Cleaned_Data!$P$2:$P$1451,">0") -> 3.2777778 | R10: =IFERROR(COUNTIFS(Cleaned_Data!$D$2:$D$1451,A10,Cleaned_Data!$K$2:$K$1451,"Active",Cleaned_Data!$Q$2:$Q$1451,"Yes")/D10,0) -> 0.29166667
A11: People & Talent | B11: DEP-HR | C11: =VLOOKUP(B11,Employee_Lookups!$A$4:$G$9,5,FALSE()) -> 95 | D11: =COUNTIFS(Cleaned_Data!$D$2:$D$1451,A11,Cleaned_Data!$K$2:$K$1451,"Active") -> 92 | E11: =D11-C11 -> -3 | F11: =COUNTIF(Cleaned_Data!$D$2:$D$1451,A11) -> 116 | G11: =COUNTIFS(Cleaned_Data!$D$2:$D$1451,A11,Cleaned_Data!$K$2:$K$1451,"<>Active") -> 24 | H11: =COUNTIFS(Cleaned_Data!$D$2:$D$1451,A11,Cleaned_Data!$K$2:$K$1451,"Voluntary Exit") -> 16 | I11: =IFERROR(G11/F11,0) -> 0.20689655 | J11: =COUNTIFS(Cleaned_Data!$D$2:$D$1451,A11,Cleaned_Data!$AB$2:$AB$1451,"<=2024")-COUNTIFS(Cleaned_Data!$D$2:$D$1451,A11,Cleaned_Data!$AB$2:$AB$1451,"<=2024",Cleaned_Data!$AC$2:$AC$1451,"<=2024",Cleaned_Data!$AC$2:$AC$1451,">0") -> 79 | K11: =COUNTIFS(Cleaned_Data!$D$2:$D$1451,A11,Cleaned_Data!$AB$2:$AB$1451,2025) -> 18 | L11: =COUNTIFS(Cleaned_Data!$D$2:$D$1451,A11,Cleaned_Data!$AC$2:$AC$1451,2025) -> 5 | M11: =(J11+D11)/2 -> 85.5 | N11: =IFERROR(L11/M11,0) -> 0.058479532 | O11: =AVERAGEIFS(Cleaned_Data!$AD$2:$AD$1451,Cleaned_Data!$D$2:$D$1451,A11,Cleaned_Data!$K$2:$K$1451,"Active") -> 2.8375 | P11: =AVERAGEIFS(Cleaned_Data!$O$2:$O$1451,Cleaned_Data!$D$2:$D$1451,A11,Cleaned_Data!$K$2:$K$1451,"Active") -> 1453184.8 | Q11: =AVERAGEIFS(Cleaned_Data!$P$2:$P$1451,Cleaned_Data!$D$2:$D$1451,A11,Cleaned_Data!$P$2:$P$1451,">0") -> 3.2280702 | R11: =IFERROR(COUNTIFS(Cleaned_Data!$D$2:$D$1451,A11,Cleaned_Data!$K$2:$K$1451,"Active",Cleaned_Data!$Q$2:$Q$1451,"Yes")/D11,0) -> 0.27173913
A12: Total / Organization Benchmark | B12: ALL-ORG | C12: =SUM(C6:C11) -> 1095 | D12: =SUM(D6:D11) -> 1042 | E12: =D12-C12 -> -53 | F12: =SUM(F6:F11) -> 1450 | G12: =SUM(G6:G11) -> 408 | H12: =SUM(H6:H11) -> 265 | I12: =IFERROR(G12/F12,0) -> 0.28137931 | J12: =SUM(J6:J11) -> 923 | K12: =SUM(K6:K11) -> 221 | L12: =SUM(L6:L11) -> 102 | M12: =(J12+D12)/2 -> 982.5 | N12: =IFERROR(L12/M12,0) -> 0.10381679 | O12: =SUMPRODUCT(D6:D11,O6:O11)/D12 -> 2.6975048 | P12: =SUMPRODUCT(D6:D11,P6:P11)/D12 -> 1309163.1 | Q12: =AVERAGEIF(Cleaned_Data!$P$2:$P$1451,">0") -> 3.1866197 | R12: =SUMPRODUCT(D6:D11,R6:R11)/D12 -> 0.3646833
A15: 2. Historical Workforce Growth, Hiring Velocity & Annualized Attrition Trend (2019–2025)
A16: Calendar_Year | B16: Starting_Headcount | C16: New_Hires | D16: Total_Exits | E16: Net_Headcount_Change | F16: Ending_Headcount | G16: Average_Headcount | H16: Annual_Attrition_Rate_%
A17: 2019 | B17: 0 | C17: =COUNTIF(Cleaned_Data!$AB$2:$AB$1451,A17) -> 87 | D17: =COUNTIF(Cleaned_Data!$AC$2:$AC$1451,A17) -> 9 | E17: =C17-D17 -> 78 | F17: =B17+E17 -> 78 | G17: =(B17+F17)/2 -> 39 | H17: =IFERROR(D17/G17,0) -> 0.23076923
A18: 2020 | B18: =F17 -> 78 | C18: =COUNTIF(Cleaned_Data!$AB$2:$AB$1451,A18) -> 116 | D18: =COUNTIF(Cleaned_Data!$AC$2:$AC$1451,A18) -> 22 | E18: =C18-D18 -> 94 | F18: =B18+E18 -> 172 | G18: =(B18+F18)/2 -> 125 | H18: =IFERROR(D18/G18,0) -> 0.176
A19: 2021 | B19: =F18 -> 172 | C19: =COUNTIF(Cleaned_Data!$AB$2:$AB$1451,A19) -> 197 | D19: =COUNTIF(Cleaned_Data!$AC$2:$AC$1451,A19) -> 37 | E19: =C19-D19 -> 160 | F19: =B19+E19 -> 332 | G19: =(B19+F19)/2 -> 252 | H19: =IFERROR(D19/G19,0) -> 0.1468254
A20: 2022 | B20: =F19 -> 332 | C20: =COUNTIF(Cleaned_Data!$AB$2:$AB$1451,A20) -> 299 | D20: =COUNTIF(Cleaned_Data!$AC$2:$AC$1451,A20) -> 72 | E20: =C20-D20 -> 227 | F20: =B20+E20 -> 559 | G20: =(B20+F20)/2 -> 445.5 | H20: =IFERROR(D20/G20,0) -> 0.16161616
A21: 2023 | B21: =F20 -> 559 | C21: =COUNTIF(Cleaned_Data!$AB$2:$AB$1451,A21) -> 268 | D21: =COUNTIF(Cleaned_Data!$AC$2:$AC$1451,A21) -> 82 | E21: =C21-D21 -> 186 | F21: =B21+E21 -> 745 | G21: =(B21+F21)/2 -> 652 | H21: =IFERROR(D21/G21,0) -> 0.12576687
A22: 2024 | B22: =F21 -> 745 | C22: =COUNTIF(Cleaned_Data!$AB$2:$AB$1451,A22) -> 262 | D22: =COUNTIF(Cleaned_Data!$AC$2:$AC$1451,A22) -> 84 | E22: =C22-D22 -> 178 | F22: =B22+E22 -> 923 | G22: =(B22+F22)/2 -> 834 | H22: =IFERROR(D22/G22,0) -> 0.10071942
A23: 2025 | B23: =F22 -> 923 | C23: =COUNTIF(Cleaned_Data!$AB$2:$AB$1451,A23) -> 221 | D23: =COUNTIF(Cleaned_Data!$AC$2:$AC$1451,A23) -> 102 | E23: =C23-D23 -> 119 | F23: =B23+E23 -> 1042 | G23: =(B23+F23)/2 -> 982.5 | H23: =IFERROR(D23/G23,0) -> 0.10381679
A26: 3. Job Level & Compensation Band Distribution, Attrition & Overtime Analysis
A27: Job_Level | B27: Level_Category | C27: Salary_Band | D27: Active_Headcount | E27: Historical_Exits | F27: Cohort_Attrition_% | G27: Avg_Active_Salary_INR | H27: Band_Midpoint_INR | I27: Avg_Compa_Ratio | J27: Active_Overtime_%
A28: L1 | B28: =INDEX(Employee_Lookups!$B$13:$B$17,MATCH(A28,Employee_Lookups!$A$13:$A$17,0)) -> Associate / Analyst | C28: =INDEX(Employee_Lookups!$C$13:$C$17,MATCH(A28,Employee_Lookups!$A$13:$A$17,0)) -> Band A (Entry) | D28: =COUNTIFS(Cleaned_Data!$F$2:$F$1451,A28,Cleaned_Data!$K$2:$K$1451,"Active") -> 382 | E28: =COUNTIFS(Cleaned_Data!$F$2:$F$1451,A28,Cleaned_Data!$K$2:$K$1451,"<>Active") -> 205 | F28: =IFERROR(E28/(D28+E28),0) -> 0.34923339 | G28: =AVERAGEIFS(Cleaned_Data!$O$2:$O$1451,Cleaned_Data!$F$2:$F$1451,A28,Cleaned_Data!$K$2:$K$1451,"Active") -> 701335.08 | H28: =VLOOKUP(A28,Employee_Lookups!$A$13:$G$17,5,FALSE()) -> 700000 | I28: =IFERROR(G28/H28,0) -> 1.0019073 | J28: =IFERROR(COUNTIFS(Cleaned_Data!$F$2:$F$1451,A28,Cleaned_Data!$K$2:$K$1451,"Active",Cleaned_Data!$Q$2:$Q$1451,"Yes")/D28,0) -> 0.36387435
A29: L2 | B29: =INDEX(Employee_Lookups!$B$13:$B$17,MATCH(A29,Employee_Lookups!$A$13:$A$17,0)) -> Specialist / Sr. Analyst | C29: =INDEX(Employee_Lookups!$C$13:$C$17,MATCH(A29,Employee_Lookups!$A$13:$A$17,0)) -> Band B (Mid) | D29: =COUNTIFS(Cleaned_Data!$F$2:$F$1451,A29,Cleaned_Data!$K$2:$K$1451,"Active") -> 378 | E29: =COUNTIFS(Cleaned_Data!$F$2:$F$1451,A29,Cleaned_Data!$K$2:$K$1451,"<>Active") -> 124 | F29: =IFERROR(E29/(D29+E29),0) -> 0.24701195 | G29: =AVERAGEIFS(Cleaned_Data!$O$2:$O$1451,Cleaned_Data!$F$2:$F$1451,A29,Cleaned_Data!$K$2:$K$1451,"Active") -> 1111518.5 | H29: =VLOOKUP(A29,Employee_Lookups!$A$13:$G$17,5,FALSE()) -> 1100000 | I29: =IFERROR(G29/H29,0) -> 1.0104714 | J29: =IFERROR(COUNTIFS(Cleaned_Data!$F$2:$F$1451,A29,Cleaned_Data!$K$2:$K$1451,"Active",Cleaned_Data!$Q$2:$Q$1451,"Yes")/D29,0) -> 0.38095238
A30: L3 | B30: =INDEX(Employee_Lookups!$B$13:$B$17,MATCH(A30,Employee_Lookups!$A$13:$A$17,0)) -> Lead / Manager | C30: =INDEX(Employee_Lookups!$C$13:$C$17,MATCH(A30,Employee_Lookups!$A$13:$A$17,0)) -> Band C (Senior) | D30: =COUNTIFS(Cleaned_Data!$F$2:$F$1451,A30,Cleaned_Data!$K$2:$K$1451,"Active") -> 155 | E30: =COUNTIFS(Cleaned_Data!$F$2:$F$1451,A30,Cleaned_Data!$K$2:$K$1451,"<>Active") -> 52 | F30: =IFERROR(E30/(D30+E30),0) -> 0.25120773 | G30: =AVERAGEIFS(Cleaned_Data!$O$2:$O$1451,Cleaned_Data!$F$2:$F$1451,A30,Cleaned_Data!$K$2:$K$1451,"Active") -> 1729412.9 | H30: =VLOOKUP(A30,Employee_Lookups!$A$13:$G$17,5,FALSE()) -> 1725000 | I30: =IFERROR(G30/H30,0) -> 1.0025582 | J30: =IFERROR(COUNTIFS(Cleaned_Data!$F$2:$F$1451,A30,Cleaned_Data!$K$2:$K$1451,"Active",Cleaned_Data!$Q$2:$Q$1451,"Yes")/D30,0) -> 0.39354839
A31: L4 | B31: =INDEX(Employee_Lookups!$B$13:$B$17,MATCH(A31,Employee_Lookups!$A$13:$A$17,0)) -> Director / Principal | C31: =INDEX(Employee_Lookups!$C$13:$C$17,MATCH(A31,Employee_Lookups!$A$13:$A$17,0)) -> Band D (Leadership) | D31: =COUNTIFS(Cleaned_Data!$F$2:$F$1451,A31,Cleaned_Data!$K$2:$K$1451,"Active") -> 90 | E31: =COUNTIFS(Cleaned_Data!$F$2:$F$1451,A31,Cleaned_Data!$K$2:$K$1451,"<>Active") -> 17 | F31: =IFERROR(E31/(D31+E31),0) -> 0.1588785 | G31: =AVERAGEIFS(Cleaned_Data!$O$2:$O$1451,Cleaned_Data!$F$2:$F$1451,A31,Cleaned_Data!$K$2:$K$1451,"Active") -> 2793100 | H31: =VLOOKUP(A31,Employee_Lookups!$A$13:$G$17,5,FALSE()) -> 2750000 | I31: =IFERROR(G31/H31,0) -> 1.0156727 | J31: =IFERROR(COUNTIFS(Cleaned_Data!$F$2:$F$1451,A31,Cleaned_Data!$K$2:$K$1451,"Active",Cleaned_Data!$Q$2:$Q$1451,"Yes")/D31,0) -> 0.28888889
A32: L5 | B32: =INDEX(Employee_Lookups!$B$13:$B$17,MATCH(A32,Employee_Lookups!$A$13:$A$17,0)) -> VP / Executive | C32: =INDEX(Employee_Lookups!$C$13:$C$17,MATCH(A32,Employee_Lookups!$A$13:$A$17,0)) -> Band E (Executive) | D32: =COUNTIFS(Cleaned_Data!$F$2:$F$1451,A32,Cleaned_Data!$K$2:$K$1451,"Active") -> 37 | E32: =COUNTIFS(Cleaned_Data!$F$2:$F$1451,A32,Cleaned_Data!$K$2:$K$1451,"<>Active") -> 10 | F32: =IFERROR(E32/(D32+E32),0) -> 0.21276596 | G32: =AVERAGEIFS(Cleaned_Data!$O$2:$O$1451,Cleaned_Data!$F$2:$F$1451,A32,Cleaned_Data!$K$2:$K$1451,"Active") -> 4233675.7 | H32: =VLOOKUP(A32,Employee_Lookups!$A$13:$G$17,5,FALSE()) -> 4300000 | I32: =IFERROR(G32/H32,0) -> 0.98457574 | J32: =IFERROR(COUNTIFS(Cleaned_Data!$F$2:$F$1451,A32,Cleaned_Data!$K$2:$K$1451,"Active",Cleaned_Data!$Q$2:$Q$1451,"Yes")/D32,0) -> 0.27027027
A35: 4. Recruitment Source ROI, First-Year Attrition & Weighted Cost-Per-Hire (SUMPRODUCT)
A36: Recruitment_Source | B36: Total_Hires | C36: Share_of_Hires_% | D36: Active_Retained | E36: Total_Exits | F36: First_Year_Exits (<1 Yr) | G36: Overall_Source_Attrition_% | H36: First_Year_Attrition_% | I36: Avg_Perf_Rating | J36: Std_Cost_Per_Hire_INR
A37: Campus Recruitment | B37: =COUNTIF(Cleaned_Data!$N$2:$N$1451,A37) -> 243 | C37: =B37/$B$42 -> 0.16758621 | D37: =COUNTIFS(Cleaned_Data!$N$2:$N$1451,A37,Cleaned_Data!$K$2:$K$1451,"Active") -> 181 | E37: =COUNTIFS(Cleaned_Data!$N$2:$N$1451,A37,Cleaned_Data!$K$2:$K$1451,"<>Active") -> 62 | F37: =COUNTIFS(Cleaned_Data!$N$2:$N$1451,A37,Cleaned_Data!$K$2:$K$1451,"<>Active",Cleaned_Data!$AD$2:$AD$1451,"<1") -> 32 | G37: =IFERROR(E37/B37,0) -> 0.25514403 | H37: =IFERROR(F37/B37,0) -> 0.13168724 | I37: =AVERAGEIFS(Cleaned_Data!$P$2:$P$1451,Cleaned_Data!$N$2:$N$1451,A37,Cleaned_Data!$P$2:$P$1451,">0") -> 3.1344538 | J37: =VLOOKUP(A37,Employee_Lookups!$A$21:$C$25,2,FALSE()) -> 35000
A38: Company Career Portal | B38: =COUNTIF(Cleaned_Data!$N$2:$N$1451,A38) -> 240 | C38: =B38/$B$42 -> 0.16551724 | D38: =COUNTIFS(Cleaned_Data!$N$2:$N$1451,A38,Cleaned_Data!$K$2:$K$1451,"Active") -> 177 | E38: =COUNTIFS(Cleaned_Data!$N$2:$N$1451,A38,Cleaned_Data!$K$2:$K$1451,"<>Active") -> 63 | F38: =COUNTIFS(Cleaned_Data!$N$2:$N$1451,A38,Cleaned_Data!$K$2:$K$1451,"<>Active",Cleaned_Data!$AD$2:$AD$1451,"<1") -> 45 | G38: =IFERROR(E38/B38,0) -> 0.2625 | H38: =IFERROR(F38/B38,0) -> 0.1875 | I38: =AVERAGEIFS(Cleaned_Data!$P$2:$P$1451,Cleaned_Data!$N$2:$N$1451,A38,Cleaned_Data!$P$2:$P$1451,">0") -> 3.2863248 | J38: =VLOOKUP(A38,Employee_Lookups!$A$21:$C$25,2,FALSE()) -> 22000
A39: Employee Referral | B39: =COUNTIF(Cleaned_Data!$N$2:$N$1451,A39) -> 310 | C39: =B39/$B$42 -> 0.2137931 | D39: =COUNTIFS(Cleaned_Data!$N$2:$N$1451,A39,Cleaned_Data!$K$2:$K$1451,"Active") -> 248 | E39: =COUNTIFS(Cleaned_Data!$N$2:$N$1451,A39,Cleaned_Data!$K$2:$K$1451,"<>Active") -> 62 | F39: =COUNTIFS(Cleaned_Data!$N$2:$N$1451,A39,Cleaned_Data!$K$2:$K$1451,"<>Active",Cleaned_Data!$AD$2:$AD$1451,"<1") -> 46 | G39: =IFERROR(E39/B39,0) -> 0.2 | H39: =IFERROR(F39/B39,0) -> 0.1483871 | I39: =AVERAGEIFS(Cleaned_Data!$P$2:$P$1451,Cleaned_Data!$N$2:$N$1451,A39,Cleaned_Data!$P$2:$P$1451,">0") -> 3.1901639 | J39: =VLOOKUP(A39,Employee_Lookups!$A$21:$C$25,2,FALSE()) -> 42000
A40: External Agency | B40: =COUNTIF(Cleaned_Data!$N$2:$N$1451,A40) -> 198 | C40: =B40/$B$42 -> 0.13655172 | D40: =COUNTIFS(Cleaned_Data!$N$2:$N$1451,A40,Cleaned_Data!$K$2:$K$1451,"Active") -> 118 | E40: =COUNTIFS(Cleaned_Data!$N$2:$N$1451,A40,Cleaned_Data!$K$2:$K$1451,"<>Active") -> 80 | F40: =COUNTIFS(Cleaned_Data!$N$2:$N$1451,A40,Cleaned_Data!$K$2:$K$1451,"<>Active",Cleaned_Data!$AD$2:$AD$1451,"<1") -> 43 | G40: =IFERROR(E40/B40,0) -> 0.4040404 | H40: =IFERROR(F40/B40,0) -> 0.21717172 | I40: =AVERAGEIFS(Cleaned_Data!$P$2:$P$1451,Cleaned_Data!$N$2:$N$1451,A40,Cleaned_Data!$P$2:$P$1451,">0") -> 3.1435897 | J40: =VLOOKUP(A40,Employee_Lookups!$A$21:$C$25,2,FALSE()) -> 145000
A41: LinkedIn Sourcing | B41: =COUNTIF(Cleaned_Data!$N$2:$N$1451,A41) -> 459 | C41: =B41/$B$42 -> 0.31655172 | D41: =COUNTIFS(Cleaned_Data!$N$2:$N$1451,A41,Cleaned_Data!$K$2:$K$1451,"Active") -> 318 | E41: =COUNTIFS(Cleaned_Data!$N$2:$N$1451,A41,Cleaned_Data!$K$2:$K$1451,"<>Active") -> 141 | F41: =COUNTIFS(Cleaned_Data!$N$2:$N$1451,A41,Cleaned_Data!$K$2:$K$1451,"<>Active",Cleaned_Data!$AD$2:$AD$1451,"<1") -> 95 | G41: =IFERROR(E41/B41,0) -> 0.30718954 | H41: =IFERROR(F41/B41,0) -> 0.20697168 | I41: =AVERAGEIFS(Cleaned_Data!$P$2:$P$1451,Cleaned_Data!$N$2:$N$1451,A41,Cleaned_Data!$P$2:$P$1451,">0") -> 3.1785714 | J41: =VLOOKUP(A41,Employee_Lookups!$A$21:$C$25,2,FALSE()) -> 68000
A42: Total / Weighted Portfolio | B42: =SUM(B37:B41) -> 1450 | C42: =SUM(C37:C41) -> 1 | D42: =SUM(D37:D41) -> 1042 | E42: =SUM(E37:E41) -> 408 | F42: =SUM(F37:F41) -> 261 | G42: =IFERROR(E42/B42,0) -> 0.28137931 | H42: =IFERROR(F42/B42,0) -> 0.18 | I42: =SUMPRODUCT(B37:B41,I37:I41)/B42 -> 3.1867145 | J42: =SUMPRODUCT(B37:B41,J37:J41)/B42 -> 59811.724
A45: 5. Location & Work Mode Headcount, Attrition & Payroll Distribution
A46: Location | B46: Work_Mode | C46: Active_Headcount | D46: Share_of_Active_HC_% | E46: Total_Exits | F46: Cohort_Attrition_% | G46: Active_Payroll_INR (SUMIFS)
A47: Bengaluru | B47: Hybrid | C47: =COUNTIFS(Cleaned_Data!$H$2:$H$1451,A47,Cleaned_Data!$K$2:$K$1451,"Active") -> 426 | D47: =C47/$C$52 -> 0.40882917 | E47: =COUNTIFS(Cleaned_Data!$H$2:$H$1451,A47,Cleaned_Data!$K$2:$K$1451,"<>Active") -> 177 | F47: =IFERROR(E47/(C47+E47),0) -> 0.29353234 | G47: =SUMIFS(Cleaned_Data!$O$2:$O$1451,Cleaned_Data!$H$2:$H$1451,A47,Cleaned_Data!$K$2:$K$1451,"Active") -> 565018000
A48: Pune | B48: Hybrid | C48: =COUNTIFS(Cleaned_Data!$H$2:$H$1451,A48,Cleaned_Data!$K$2:$K$1451,"Active") -> 261 | D48: =C48/$C$52 -> 0.25047985 | E48: =COUNTIFS(Cleaned_Data!$H$2:$H$1451,A48,Cleaned_Data!$K$2:$K$1451,"<>Active") -> 120 | F48: =IFERROR(E48/(C48+E48),0) -> 0.31496063 | G48: =SUMIFS(Cleaned_Data!$O$2:$O$1451,Cleaned_Data!$H$2:$H$1451,A48,Cleaned_Data!$K$2:$K$1451,"Active") -> 343335000
A49: Hyderabad | B49: On-Site | C49: =COUNTIFS(Cleaned_Data!$H$2:$H$1451,A49,Cleaned_Data!$K$2:$K$1451,"Active") -> 195 | D49: =C49/$C$52 -> 0.18714012 | E49: =COUNTIFS(Cleaned_Data!$H$2:$H$1451,A49,Cleaned_Data!$K$2:$K$1451,"<>Active") -> 68 | F49: =IFERROR(E49/(C49+E49),0) -> 0.25855513 | G49: =SUMIFS(Cleaned_Data!$O$2:$O$1451,Cleaned_Data!$H$2:$H$1451,A49,Cleaned_Data!$K$2:$K$1451,"Active") -> 257750000
A50: Mumbai | B50: On-Site | C50: =COUNTIFS(Cleaned_Data!$H$2:$H$1451,A50,Cleaned_Data!$K$2:$K$1451,"Active") -> 100 | D50: =C50/$C$52 -> 0.09596929 | E50: =COUNTIFS(Cleaned_Data!$H$2:$H$1451,A50,Cleaned_Data!$K$2:$K$1451,"<>Active") -> 33 | F50: =IFERROR(E50/(C50+E50),0) -> 0.2481203 | G50: =SUMIFS(Cleaned_Data!$O$2:$O$1451,Cleaned_Data!$H$2:$H$1451,A50,Cleaned_Data!$K$2:$K$1451,"Active") -> 120446000
A51: Remote-India | B51: Remote | C51: =COUNTIFS(Cleaned_Data!$H$2:$H$1451,A51,Cleaned_Data!$K$2:$K$1451,"Active") -> 60 | D51: =C51/$C$52 -> 0.057581574 | E51: =COUNTIFS(Cleaned_Data!$H$2:$H$1451,A51,Cleaned_Data!$K$2:$K$1451,"<>Active") -> 10 | F51: =IFERROR(E51/(C51+E51),0) -> 0.14285714 | G51: =SUMIFS(Cleaned_Data!$O$2:$O$1451,Cleaned_Data!$H$2:$H$1451,A51,Cleaned_Data!$K$2:$K$1451,"Active") -> 77599000
A52: Total Organization | B52: All Modes | C52: =SUM(C47:C51) -> 1042 | D52: =SUM(D47:D51) -> 1 | E52: =SUM(E47:E51) -> 408 | F52: =IFERROR(E52/(C52+E52),0) -> 0.28137931 | G52: =SUM(G47:G51) -> 1364148000

Sheet Pivot_Analysis
A1: MULTI-DIMENSIONAL CROSS-TAB ANALYSIS (Formula-Driven Pivot Matrices + Native PivotTable Staging)
A2: Note: Because Python XML builders cannot compile binary PivotCaches natively, these cross-tabs use live COUNTIFS/AVERAGEIFS formulas. Native PivotTables can be added in 30 seconds from 'tbl_Cleaned_HR'.
A4: Cross-Tab 1: Active Headcount by Department vs. Job Level (COUNTIFS Matrix)
A5: Department | B5: L1 | C5: L2 | D5: L3 | E5: L4 | F5: L5 | G5: Total Active HC
A6: Engineering & Product | B6: =COUNTIFS(Cleaned_Data!$D$2:$D$1451,$A6,Cleaned_Data!$F$2:$F$1451,B$5,Cleaned_Data!$K$2:$K$1451,"Active") -> 141 | C6: =COUNTIFS(Cleaned_Data!$D$2:$D$1451,$A6,Cleaned_Data!$F$2:$F$1451,C$5,Cleaned_Data!$K$2:$K$1451,"Active") -> 131 | D6: =COUNTIFS(Cleaned_Data!$D$2:$D$1451,$A6,Cleaned_Data!$F$2:$F$1451,D$5,Cleaned_Data!$K$2:$K$1451,"Active") -> 51 | E6: =COUNTIFS(Cleaned_Data!$D$2:$D$1451,$A6,Cleaned_Data!$F$2:$F$1451,E$5,Cleaned_Data!$K$2:$K$1451,"Active") -> 28 | F6: =COUNTIFS(Cleaned_Data!$D$2:$D$1451,$A6,Cleaned_Data!$F$2:$F$1451,F$5,Cleaned_Data!$K$2:$K$1451,"Active") -> 15 | G6: =SUM(B6:F6) -> 366
A7: Enterprise Sales | B7: =COUNTIFS(Cleaned_Data!$D$2:$D$1451,$A7,Cleaned_Data!$F$2:$F$1451,B$5,Cleaned_Data!$K$2:$K$1451,"Active") -> 75 | C7: =COUNTIFS(Cleaned_Data!$D$2:$D$1451,$A7,Cleaned_Data!$F$2:$F$1451,C$5,Cleaned_Data!$K$2:$K$1451,"Active") -> 72 | D7: =COUNTIFS(Cleaned_Data!$D$2:$D$1451,$A7,Cleaned_Data!$F$2:$F$1451,D$5,Cleaned_Data!$K$2:$K$1451,"Active") -> 31 | E7: =COUNTIFS(Cleaned_Data!$D$2:$D$1451,$A7,Cleaned_Data!$F$2:$F$1451,E$5,Cleaned_Data!$K$2:$K$1451,"Active") -> 16 | F7: =COUNTIFS(Cleaned_Data!$D$2:$D$1451,$A7,Cleaned_Data!$F$2:$F$1451,F$5,Cleaned_Data!$K$2:$K$1451,"Active") -> 7 | G7: =SUM(B7:F7) -> 201
A8: Customer Operations | B8: =COUNTIFS(Cleaned_Data!$D$2:$D$1451,$A8,Cleaned_Data!$F$2:$F$1451,B$5,Cleaned_Data!$K$2:$K$1451,"Active") -> 48 | C8: =COUNTIFS(Cleaned_Data!$D$2:$D$1451,$A8,Cleaned_Data!$F$2:$F$1451,C$5,Cleaned_Data!$K$2:$K$1451,"Active") -> 67 | D8: =COUNTIFS(Cleaned_Data!$D$2:$D$1451,$A8,Cleaned_Data!$F$2:$F$1451,D$5,Cleaned_Data!$K$2:$K$1451,"Active") -> 32 | E8: =COUNTIFS(Cleaned_Data!$D$2:$D$1451,$A8,Cleaned_Data!$F$2:$F$1451,E$5,Cleaned_Data!$K$2:$K$1451,"Active") -> 15 | F8: =COUNTIFS(Cleaned_Data!$D$2:$D$1451,$A8,Cleaned_Data!$F$2:$F$1451,F$5,Cleaned_Data!$K$2:$K$1451,"Active") -> 6 | G8: =SUM(B8:F8) -> 168
A9: Growth Marketing | B9: =COUNTIFS(Cleaned_Data!$D$2:$D$1451,$A9,Cleaned_Data!$F$2:$F$1451,B$5,Cleaned_Data!$K$2:$K$1451,"Active") -> 47 | C9: =COUNTIFS(Cleaned_Data!$D$2:$D$1451,$A9,Cleaned_Data!$F$2:$F$1451,C$5,Cleaned_Data!$K$2:$K$1451,"Active") -> 39 | D9: =COUNTIFS(Cleaned_Data!$D$2:$D$1451,$A9,Cleaned_Data!$F$2:$F$1451,D$5,Cleaned_Data!$K$2:$K$1451,"Active") -> 19 | E9: =COUNTIFS(Cleaned_Data!$D$2:$D$1451,$A9,Cleaned_Data!$F$2:$F$1451,E$5,Cleaned_Data!$K$2:$K$1451,"Active") -> 13 | F9: =COUNTIFS(Cleaned_Data!$D$2:$D$1451,$A9,Cleaned_Data!$F$2:$F$1451,F$5,Cleaned_Data!$K$2:$K$1451,"Active") -> 1 | G9: =SUM(B9:F9) -> 119
A10: Finance & Strategy | B10: =COUNTIFS(Cleaned_Data!$D$2:$D$1451,$A10,Cleaned_Data!$F$2:$F$1451,B$5,Cleaned_Data!$K$2:$K$1451,"Active") -> 41 | C10: =COUNTIFS(Cleaned_Data!$D$2:$D$1451,$A10,Cleaned_Data!$F$2:$F$1451,C$5,Cleaned_Data!$K$2:$K$1451,"Active") -> 33 | D10: =COUNTIFS(Cleaned_Data!$D$2:$D$1451,$A10,Cleaned_Data!$F$2:$F$1451,D$5,Cleaned_Data!$K$2:$K$1451,"Active") -> 14 | E10: =COUNTIFS(Cleaned_Data!$D$2:$D$1451,$A10,Cleaned_Data!$F$2:$F$1451,E$5,Cleaned_Data!$K$2:$K$1451,"Active") -> 6 | F10: =COUNTIFS(Cleaned_Data!$D$2:$D$1451,$A10,Cleaned_Data!$F$2:$F$1451,F$5,Cleaned_Data!$K$2:$K$1451,"Active") -> 2 | G10: =SUM(B10:F10) -> 96
A11: People & Talent | B11: =COUNTIFS(Cleaned_Data!$D$2:$D$1451,$A11,Cleaned_Data!$F$2:$F$1451,B$5,Cleaned_Data!$K$2:$K$1451,"Active") -> 30 | C11: =COUNTIFS(Cleaned_Data!$D$2:$D$1451,$A11,Cleaned_Data!$F$2:$F$1451,C$5,Cleaned_Data!$K$2:$K$1451,"Active") -> 36 | D11: =COUNTIFS(Cleaned_Data!$D$2:$D$1451,$A11,Cleaned_Data!$F$2:$F$1451,D$5,Cleaned_Data!$K$2:$K$1451,"Active") -> 8 | E11: =COUNTIFS(Cleaned_Data!$D$2:$D$1451,$A11,Cleaned_Data!$F$2:$F$1451,E$5,Cleaned_Data!$K$2:$K$1451,"Active") -> 12 | F11: =COUNTIFS(Cleaned_Data!$D$2:$D$1451,$A11,Cleaned_Data!$F$2:$F$1451,F$5,Cleaned_Data!$K$2:$K$1451,"Active") -> 6 | G11: =SUM(B11:F11) -> 92
A12: Total Active by Level | B12: =SUM(B6:B11) -> 382 | C12: =SUM(C6:C11) -> 378 | D12: =SUM(D6:D11) -> 155 | E12: =SUM(E6:E11) -> 90 | F12: =SUM(F6:F11) -> 37 | G12: =SUM(G6:G11) -> 1042
A15: Cross-Tab 2: Attrition Rate Comparison — Overtime vs. Non-Overtime Cohorts by Department
A16: Department | B16: Overtime = Yes (Exits) | C16: Overtime = Yes (Attrition %) | D16: Overtime = No (Exits) | E16: Overtime = No (Attrition %)
A17: Engineering & Product | B17: =COUNTIFS(Cleaned_Data!$D$2:$D$1451,$A17,Cleaned_Data!$Q$2:$Q$1451,"Yes",Cleaned_Data!$K$2:$K$1451,"<>Active") -> 48 | C17: =IFERROR(B17/COUNTIFS(Cleaned_Data!$D$2:$D$1451,$A17,Cleaned_Data!$Q$2:$Q$1451,"Yes"),0) -> 0.32653061 | D17: =COUNTIFS(Cleaned_Data!$D$2:$D$1451,$A17,Cleaned_Data!$Q$2:$Q$1451,"No",Cleaned_Data!$K$2:$K$1451,"<>Active") -> 51 | E17: =IFERROR(D17/COUNTIFS(Cleaned_Data!$D$2:$D$1451,$A17,Cleaned_Data!$Q$2:$Q$1451,"No"),0) -> 0.16037736
A18: Enterprise Sales | B18: =COUNTIFS(Cleaned_Data!$D$2:$D$1451,$A18,Cleaned_Data!$Q$2:$Q$1451,"Yes",Cleaned_Data!$K$2:$K$1451,"<>Active") -> 69 | C18: =IFERROR(B18/COUNTIFS(Cleaned_Data!$D$2:$D$1451,$A18,Cleaned_Data!$Q$2:$Q$1451,"Yes"),0) -> 0.39655172 | D18: =COUNTIFS(Cleaned_Data!$D$2:$D$1451,$A18,Cleaned_Data!$Q$2:$Q$1451,"No",Cleaned_Data!$K$2:$K$1451,"<>Active") -> 31 | E18: =IFERROR(D18/COUNTIFS(Cleaned_Data!$D$2:$D$1451,$A18,Cleaned_Data!$Q$2:$Q$1451,"No"),0) -> 0.24409449
A19: Customer Operations | B19: =COUNTIFS(Cleaned_Data!$D$2:$D$1451,$A19,Cleaned_Data!$Q$2:$Q$1451,"Yes",Cleaned_Data!$K$2:$K$1451,"<>Active") -> 60 | C19: =IFERROR(B19/COUNTIFS(Cleaned_Data!$D$2:$D$1451,$A19,Cleaned_Data!$Q$2:$Q$1451,"Yes"),0) -> 0.4109589 | D19: =COUNTIFS(Cleaned_Data!$D$2:$D$1451,$A19,Cleaned_Data!$Q$2:$Q$1451,"No",Cleaned_Data!$K$2:$K$1451,"<>Active") -> 39 | E19: =IFERROR(D19/COUNTIFS(Cleaned_Data!$D$2:$D$1451,$A19,Cleaned_Data!$Q$2:$Q$1451,"No"),0) -> 0.32231405
A20: Growth Marketing | B20: =COUNTIFS(Cleaned_Data!$D$2:$D$1451,$A20,Cleaned_Data!$Q$2:$Q$1451,"Yes",Cleaned_Data!$K$2:$K$1451,"<>Active") -> 24 | C20: =IFERROR(B20/COUNTIFS(Cleaned_Data!$D$2:$D$1451,$A20,Cleaned_Data!$Q$2:$Q$1451,"Yes"),0) -> 0.39344262 | D20: =COUNTIFS(Cleaned_Data!$D$2:$D$1451,$A20,Cleaned_Data!$Q$2:$Q$1451,"No",Cleaned_Data!$K$2:$K$1451,"<>Active") -> 31 | E20: =IFERROR(D20/COUNTIFS(Cleaned_Data!$D$2:$D$1451,$A20,Cleaned_Data!$Q$2:$Q$1451,"No"),0) -> 0.27433628
A21: Finance & Strategy | B21: =COUNTIFS(Cleaned_Data!$D$2:$D$1451,$A21,Cleaned_Data!$Q$2:$Q$1451,"Yes",Cleaned_Data!$K$2:$K$1451,"<>Active") -> 15 | C21: =IFERROR(B21/COUNTIFS(Cleaned_Data!$D$2:$D$1451,$A21,Cleaned_Data!$Q$2:$Q$1451,"Yes"),0) -> 0.34883721 | D21: =COUNTIFS(Cleaned_Data!$D$2:$D$1451,$A21,Cleaned_Data!$Q$2:$Q$1451,"No",Cleaned_Data!$K$2:$K$1451,"<>Active") -> 16 | E21: =IFERROR(D21/COUNTIFS(Cleaned_Data!$D$2:$D$1451,$A21,Cleaned_Data!$Q$2:$Q$1451,"No"),0) -> 0.19047619
A22: People & Talent | B22: =COUNTIFS(Cleaned_Data!$D$2:$D$1451,$A22,Cleaned_Data!$Q$2:$Q$1451,"Yes",Cleaned_Data!$K$2:$K$1451,"<>Active") -> 14 | C22: =IFERROR(B22/COUNTIFS(Cleaned_Data!$D$2:$D$1451,$A22,Cleaned_Data!$Q$2:$Q$1451,"Yes"),0) -> 0.35897436 | D22: =COUNTIFS(Cleaned_Data!$D$2:$D$1451,$A22,Cleaned_Data!$Q$2:$Q$1451,"No",Cleaned_Data!$K$2:$K$1451,"<>Active") -> 10 | E22: =IFERROR(D22/COUNTIFS(Cleaned_Data!$D$2:$D$1451,$A22,Cleaned_Data!$Q$2:$Q$1451,"No"),0) -> 0.12987013
A25: Cross-Tab 3: Active Workforce Retention Risk Segmentation (High / Moderate / Low Risk)
A26: Department | B26: High Risk (Active) | C26: Moderate Risk (Active) | D26: Low Risk (Active) | E26: High Risk Share_%
A27: Engineering & Product | B27: =COUNTIFS(Cleaned_Data!$D$2:$D$1451,$A27,Cleaned_Data!$AF$2:$AF$1451,"High Risk") -> 54 | C27: =COUNTIFS(Cleaned_Data!$D$2:$D$1451,$A27,Cleaned_Data!$AF$2:$AF$1451,"Moderate Risk") -> 102 | D27: =COUNTIFS(Cleaned_Data!$D$2:$D$1451,$A27,Cleaned_Data!$AF$2:$AF$1451,"Low Risk") -> 210 | E27: =IFERROR(B27/SUM(B27:D27),0) -> 0.14754098
A28: Enterprise Sales | B28: =COUNTIFS(Cleaned_Data!$D$2:$D$1451,$A28,Cleaned_Data!$AF$2:$AF$1451,"High Risk") -> 53 | C28: =COUNTIFS(Cleaned_Data!$D$2:$D$1451,$A28,Cleaned_Data!$AF$2:$AF$1451,"Moderate Risk") -> 69 | D28: =COUNTIFS(Cleaned_Data!$D$2:$D$1451,$A28,Cleaned_Data!$AF$2:$AF$1451,"Low Risk") -> 79 | E28: =IFERROR(B28/SUM(B28:D28),0) -> 0.26368159
A29: Customer Operations | B29: =COUNTIFS(Cleaned_Data!$D$2:$D$1451,$A29,Cleaned_Data!$AF$2:$AF$1451,"High Risk") -> 44 | C29: =COUNTIFS(Cleaned_Data!$D$2:$D$1451,$A29,Cleaned_Data!$AF$2:$AF$1451,"Moderate Risk") -> 61 | D29: =COUNTIFS(Cleaned_Data!$D$2:$D$1451,$A29,Cleaned_Data!$AF$2:$AF$1451,"Low Risk") -> 63 | E29: =IFERROR(B29/SUM(B29:D29),0) -> 0.26190476
A30: Growth Marketing | B30: =COUNTIFS(Cleaned_Data!$D$2:$D$1451,$A30,Cleaned_Data!$AF$2:$AF$1451,"High Risk") -> 20 | C30: =COUNTIFS(Cleaned_Data!$D$2:$D$1451,$A30,Cleaned_Data!$AF$2:$AF$1451,"Moderate Risk") -> 31 | D30: =COUNTIFS(Cleaned_Data!$D$2:$D$1451,$A30,Cleaned_Data!$AF$2:$AF$1451,"Low Risk") -> 68 | E30: =IFERROR(B30/SUM(B30:D30),0) -> 0.16806723
A31: Finance & Strategy | B31: =COUNTIFS(Cleaned_Data!$D$2:$D$1451,$A31,Cleaned_Data!$AF$2:$AF$1451,"High Risk") -> 17 | C31: =COUNTIFS(Cleaned_Data!$D$2:$D$1451,$A31,Cleaned_Data!$AF$2:$AF$1451,"Moderate Risk") -> 22 | D31: =COUNTIFS(Cleaned_Data!$D$2:$D$1451,$A31,Cleaned_Data!$AF$2:$AF$1451,"Low Risk") -> 57 | E31: =IFERROR(B31/SUM(B31:D31),0) -> 0.17708333
A32: People & Talent | B32: =COUNTIFS(Cleaned_Data!$D$2:$D$1451,$A32,Cleaned_Data!$AF$2:$AF$1451,"High Risk") -> 15 | C32: =COUNTIFS(Cleaned_Data!$D$2:$D$1451,$A32,Cleaned_Data!$AF$2:$AF$1451,"Moderate Risk") -> 23 | D32: =COUNTIFS(Cleaned_Data!$D$2:$D$1451,$A32,Cleaned_Data!$AF$2:$AF$1451,"Low Risk") -> 54 | E32: =IFERROR(B32/SUM(B32:D32),0) -> 0.16304348
A33: Total Active Risk Pool | B33: =SUM(B27:B32) -> 203 | C33: =SUM(C27:C32) -> 308 | D33: =SUM(D27:D32) -> 531 | E33: =IFERROR(B33/SUM(B33:D33),0) -> 0.19481766

Sheet Cleaned_Data
A1: Employee_ID | B1: Full_Name | C1: Dept_Code | D1: Department | E1: Job_Level_Code | F1: Job_Level | G1: Job_Title | H1: Location | I1: Work_Mode | J1: Hire_Date | K1: Employment_Status | L1: Exit_Date | M1: Exit_Reason | N1: Recruitment_Source | O1: Annual_Salary_INR | P1: Performance_Rating | Q1: Overtime_Flag | R1: Training_Hours | S1: Manager_ID | T1: Emp_Serial_MID | U1: Dept_Abbr_LEFT | V1: Level_Check_RIGHT | W1: Manager_Name_VLOOKUP | X1: Cost_Center_VLOOKUP | Y1: Salary_Band_INDEX_MATCH | Z1: Band_Midpoint_XLOOKUP | AA1: Compa_Ratio | AB1: Hire_Year | AC1: Exit_Year | AD1: Tenure_Years | AE1: Tenure_Band_IF | AF1: Retention_Risk_Flag
A2: EMP-11004 | B2: Aarav Shah | C2: DEP-MKT | D2: Growth Marketing | E2: MKT-L1 | F2: L1 | G2: Marketing Associate | H2: Remote-India | I2: Remote | J2: 43466 | K2: Active | M2: N/A - Active | N2: Employee Referral | O2: 674000 | P2: 5 | Q2: No | R2: 31 | S2: MGR-602 | T2: =VALUE(MID(A2,5,5)) -> 11004 | U2: =LEFT(E2,3) -> MKT | V2: =RIGHT(E2,2) -> L1 | W2: =PROPER(TRIM(VLOOKUP(S2,Employee_Lookups!$I$4:$M$19,2,FALSE()))) -> Arjun Sengupta | X2: =VLOOKUP(C2,Employee_Lookups!$A$4:$G$9,4,FALSE()) -> CC-606 | Y2: =INDEX(Employee_Lookups!$C$13:$C$17,MATCH(F2,Employee_Lookups!$A$13:$A$17,0)) -> Band A (Entry) | Z2: =_xlfn.XLOOKUP(F2,Employee_Lookups!$A$13:$A$17,Employee_Lookups!$E$13:$E$17,0) -> 700000 | AA2: =ROUND(O2/INDEX(Employee_Lookups!$E$13:$E$17,MATCH(F2,Employee_Lookups!$A$13:$A$17,0)),3) -> 0.963 | AB2: =YEAR(J2) -> 2019 | AC2: =IF(ISBLANK(L2),"",YEAR(L2)) | AD2: =ROUND((IF(ISBLANK(L2),Employee_Lookups!$O$14,L2)-J2)/365.25,2) -> 7 | AE2: =IF(AD2<1,"< 1 Yr (New)",IF(AD2<3,"1 - 3 Yrs",IF(AD2<5,"3 - 5 Yrs","5+ Yrs"))) -> 5+ Yrs | AF2: =IF(K2<>"Active","Exited",IF(AND(Q2="Yes",OR(P2>=4,AA2<0.95)),"High Risk",IF(OR(Q2="Yes",AND(NOT(ISBLANK(P2)),P2<=2)),"Moderate Risk","Low Risk"))) -> Low Risk
A3: EMP-10815 | B3: Pranav Chitnis | C3: DEP-OPS | D3: Customer Operations | E3: OPS-L4 | F3: L4 | G3: Director of Operations | H3: Pune | I3: Hybrid | J3: 43470 | K3: Involuntary Exit | L3: 45702 | M3: Performance / Restructuring | N3: Campus Recruitment | O3: 2693000 | P3: 2 | Q3: Yes | R3: 32 | S3: MGR-302 | T3: =VALUE(MID(A3,5,5)) -> 10815 | U3: =LEFT(E3,3) -> OPS | V3: =RIGHT(E3,2) -> L4 | W3: =PROPER(TRIM(VLOOKUP(S3,Employee_Lookups!$I$4:$M$19,2,FALSE()))) -> Deepak Patil | X3: =VLOOKUP(C3,Employee_Lookups!$A$4:$G$9,4,FALSE()) -> CC-303 | Y3: =INDEX(Employee_Lookups!$C$13:$C$17,MATCH(F3,Employee_Lookups!$A$13:$A$17,0)) -> Band D (Leadership) | Z3: =_xlfn.XLOOKUP(F3,Employee_Lookups!$A$13:$A$17,Employee_Lookups!$E$13:$E$17,0) -> 2750000 | AA3: =ROUND(O3/INDEX(Employee_Lookups!$E$13:$E$17,MATCH(F3,Employee_Lookups!$A$13:$A$17,0)),3) -> 0.979 | AB3: =YEAR(J3) -> 2019 | AC3: =IF(ISBLANK(L3),"",YEAR(L3)) -> 2025 | AD3: =ROUND((IF(ISBLANK(L3),Employee_Lookups!$O$14,L3)-J3)/365.25,2) -> 6.11 | AE3: =IF(AD3<1,"< 1 Yr (New)",IF(AD3<3,"1 - 3 Yrs",IF(AD3<5,"3 - 5 Yrs","5+ Yrs"))) -> 5+ Yrs | AF3: =IF(K3<>"Active","Exited",IF(AND(Q3="Yes",OR(P3>=4,AA3<0.95)),"High Risk",IF(OR(Q3="Yes",AND(NOT(ISBLANK(P3)),P3<=2)),"Moderate Risk","Low Risk"))) -> Exited
A4: EMP-10751 | B4: Vihaan Menon | C4: DEP-ENG | D4: Engineering & Product | E4: ENG-L2 | F4: L2 | G4: Software Engineer II | H4: Bengaluru | I4: Hybrid | J4: 43471 | K4: Active | M4: N/A - Active | N4: Company Career Portal | O4: 1088000 | P4: 3 | Q4: No | R4: 42 | S4: MGR-101 | T4: =VALUE(MID(A4,5,5)) -> 10751 | U4: =LEFT(E4,3) -> ENG | V4: =RIGHT(E4,2) -> L2 | W4: =PROPER(TRIM(VLOOKUP(S4,Employee_Lookups!$I$4:$M$19,2,FALSE()))) -> Aarav Deshmukh | X4: =VLOOKUP(C4,Employee_Lookups!$A$4:$G$9,4,FALSE()) -> CC-101 | Y4: =INDEX(Employee_Lookups!$C$13:$C$17,MATCH(F4,Employee_Lookups!$A$13:$A$17,0)) -> Band B (Mid) | Z4: =_xlfn.XLOOKUP(F4,Employee_Lookups!$A$13:$A$17,Employee_Lookups!$E$13:$E$17,0) -> 1100000 | AA4: =ROUND(O4/INDEX(Employee_Lookups!$E$13:$E$17,MATCH(F4,Employee_Lookups!$A$13:$A$17,0)),3) -> 0.989 | AB4: =YEAR(J4) -> 2019 | AC4: =IF(ISBLANK(L4),"",YEAR(L4)) | AD4: =ROUND((IF(ISBLANK(L4),Employee_Lookups!$O$14,L4)-J4)/365.25,2) -> 6.98 | AE4: =IF(AD4<1,"< 1 Yr (New)",IF(AD4<3,"1 - 3 Yrs",IF(AD4<5,"3 - 5 Yrs","5+ Yrs"))) -> 5+ Yrs | AF4: =IF(K4<>"Active","Exited",IF(AND(Q4="Yes",OR(P4>=4,AA4<0.95)),"High Risk",IF(OR(Q4="Yes",AND(NOT(ISBLANK(P4)),P4<=2)),"Moderate Risk","Low Risk"))) -> Low Risk
A5: EMP-10863 | B5: Yash Bhatt | C5: DEP-ENG | D5: Engineering & Product | E5: ENG-L1 | F5: L1 | G5: Software Engineer I | H5: Hyderabad | I5: On-Site | J5: 43479 | K5: Active | M5: N/A - Active | N5: Employee Referral | O5: 586000 | P5: 5 | Q5: No | R5: 48 | S5: MGR-101 | T5: =VALUE(MID(A5,5,5)) -> 10863 | U5: =LEFT(E5,3) -> ENG | V5: =RIGHT(E5,2) -> L1 | W5: =PROPER(TRIM(VLOOKUP(S5,Employee_Lookups!$I$4:$M$19,2,FALSE()))) -> Aarav Deshmukh | X5: =VLOOKUP(C5,Employee_Lookups!$A$4:$G$9,4,FALSE()) -> CC-101 | Y5: =INDEX(Employee_Lookups!$C$13:$C$17,MATCH(F5,Employee_Lookups!$A$13:$A$17,0)) -> Band A (Entry) | Z5: =_xlfn.XLOOKUP(F5,Employee_Lookups!$A$13:$A$17,Employee_Lookups!$E$13:$E$17,0) -> 700000 | AA5: =ROUND(O5/INDEX(Employee_Lookups!$E$13:$E$17,MATCH(F5,Employee_Lookups!$A$13:$A$17,0)),3) -> 0.837 | AB5: =YEAR(J5) -> 2019 | AC5: =IF(ISBLANK(L5),"",YEAR(L5)) | AD5: =ROUND((IF(ISBLANK(L5),Employee_Lookups!$O$14,L5)-J5)/365.25,2) -> 6.96 | AE5: =IF(AD5<1,"< 1 Yr (New)",IF(AD5<3,"1 - 3 Yrs",IF(AD5<5,"3 - 5 Yrs","5+ Yrs"))) -> 5+ Yrs | AF5: =IF(K5<>"Active","Exited",IF(AND(Q5="Yes",OR(P5>=4,AA5<0.95)),"High Risk",IF(OR(Q5="Yes",AND(NOT(ISBLANK(P5)),P5<=2)),"Moderate Risk","Low Risk"))) -> Low Risk
A6: EMP-10356 | B6: Ananya Reddy | C6: DEP-SAL | D6: Enterprise Sales | E6: SAL-L2 | F6: L2 | G6: Account Executive | H6: Pune | I6: Hybrid | J6: 43479 | K6: Voluntary Exit | L6: 44170 | M6: Higher Education | N6: Campus Recruitment | O6: 1194000 | P6: 3 | Q6: Yes | R6: 24 | S6: MGR-202 | T6: =VALUE(MID(A6,5,5)) -> 10356 | U6: =LEFT(E6,3) -> SAL | V6: =RIGHT(E6,2) -> L2 | W6: =PROPER(TRIM(VLOOKUP(S6,Employee_Lookups!$I$4:$M$19,2,FALSE()))) -> Priya Sharma | X6: =VLOOKUP(C6,Employee_Lookups!$A$4:$G$9,4,FALSE()) -> CC-202 | Y6: =INDEX(Employee_Lookups!$C$13:$C$17,MATCH(F6,Employee_Lookups!$A$13:$A$17,0)) -> Band B (Mid) | Z6: =_xlfn.XLOOKUP(F6,Employee_Lookups!$A$13:$A$17,Employee_Lookups!$E$13:$E$17,0) -> 1100000 | AA6: =ROUND(O6/INDEX(Employee_Lookups!$E$13:$E$17,MATCH(F6,Employee_Lookups!$A$13:$A$17,0)),3) -> 1.085 | AB6: =YEAR(J6) -> 2019 | AC6: =IF(ISBLANK(L6),"",YEAR(L6)) -> 2020 | AD6: =ROUND((IF(ISBLANK(L6),Employee_Lookups!$O$14,L6)-J6)/365.25,2) -> 1.89 | AE6: =IF(AD6<1,"< 1 Yr (New)",IF(AD6<3,"1 - 3 Yrs",IF(AD6<5,"3 - 5 Yrs","5+ Yrs"))) -> 1 - 3 Yrs | AF6: =IF(K6<>"Active","Exited",IF(AND(Q6="Yes",OR(P6>=4,AA6<0.95)),"High Risk",IF(OR(Q6="Yes",AND(NOT(ISBLANK(P6)),P6<=2)),"Moderate Risk","Low Risk"))) -> Exited
A7: EMP-10463 | B7: Pranav Malhotra | C7: DEP-SAL | D7: Enterprise Sales | E7: SAL-L3 | F7: L3 | G7: Regional Sales Manager | H7: Bengaluru | I7: Hybrid | J7: 43483 | K7: Voluntary Exit | L7: 43789 | M7: Higher Education | N7: LinkedIn Sourcing | O7: 1630000 | P7: 5 | Q7: Yes | R7: 40 | S7: MGR-201 | T7: =VALUE(MID(A7,5,5)) -> 10463 | U7: =LEFT(E7,3) -> SAL | V7: =RIGHT(E7,2) -> L3 | W7: =PROPER(TRIM(VLOOKUP(S7,Employee_Lookups!$I$4:$M$19,2,FALSE()))) -> Vikramaditya Joshi | X7: =VLOOKUP(C7,Employee_Lookups!$A$4:$G$9,4,FALSE()) -> CC-202 | Y7: =INDEX(Employee_Lookups!$C$13:$C$17,MATCH(F7,Employee_Lookups!$A$13:$A$17,0)) -> Band C (Senior) | Z7: =_xlfn.XLOOKUP(F7,Employee_Lookups!$A$13:$A$17,Employee_Lookups!$E$13:$E$17,0) -> 1725000 | AA7: =ROUND(O7/INDEX(Employee_Lookups!$E$13:$E$17,MATCH(F7,Employee_Lookups!$A$13:$A$17,0)),3) -> 0.945 | AB7: =YEAR(J7) -> 2019 | AC7: =IF(ISBLANK(L7),"",YEAR(L7)) -> 2019 | AD7: =ROUND((IF(ISBLANK(L7),Employee_Lookups!$O$14,L7)-J7)/365.25,2) -> 0.84 | AE7: =IF(AD7<1,"< 1 Yr (New)",IF(AD7<3,"1 - 3 Yrs",IF(AD7<5,"3 - 5 Yrs","5+ Yrs"))) -> < 1 Yr (New) | AF7: =IF(K7<>"Active","Exited",IF(AND(Q7="Yes",OR(P7>=4,AA7<0.95)),"High Risk",IF(OR(Q7="Yes",AND(NOT(ISBLANK(P7)),P7<=2)),"Moderate Risk","Low Risk"))) -> Exited
A8: EMP-11114 | B8: Ira Patil | C8: DEP-ENG | D8: Engineering & Product | E8: ENG-L1 | F8: L1 | G8: Software Engineer I | H8: Bengaluru | I8: Hybrid | J8: 43484 | K8: Active | M8: N/A - Active | N8: Campus Recruitment | O8: 696000 | P8: 4 | Q8: Yes | R8: 31 | S8: MGR-103 | T8: =VALUE(MID(A8,5,5)) -> 11114 | U8: =LEFT(E8,3) -> ENG | V8: =RIGHT(E8,2) -> L1 | W8: =PROPER(TRIM(VLOOKUP(S8,Employee_Lookups!$I$4:$M$19,2,FALSE()))) -> Rohan Verma | X8: =VLOOKUP(C8,Employee_Lookups!$A$4:$G$9,4,FALSE()) -> CC-101 | Y8: =INDEX(Employee_Lookups!$C$13:$C$17,MATCH(F8,Employee_Lookups!$A$13:$A$17,0)) -> Band A (Entry) | Z8: =_xlfn.XLOOKUP(F8,Employee_Lookups!$A$13:$A$17,Employee_Lookups!$E$13:$E$17,0) -> 700000 | AA8: =ROUND(O8/INDEX(Employee_Lookups!$E$13:$E$17,MATCH(F8,Employee_Lookups!$A$13:$A$17,0)),3) -> 0.994 | AB8: =YEAR(J8) -> 2019 | AC8: =IF(ISBLANK(L8),"",YEAR(L8)) | AD8: =ROUND((IF(ISBLANK(L8),Employee_Lookups!$O$14,L8)-J8)/365.25,2) -> 6.95 | AE8: =IF(AD8<1,"< 1 Yr (New)",IF(AD8<3,"1 - 3 Yrs",IF(AD8<5,"3 - 5 Yrs","5+ Yrs"))) -> 5+ Yrs | AF8: =IF(K8<>"Active","Exited",IF(AND(Q8="Yes",OR(P8>=4,AA8<0.95)),"High Risk",IF(OR(Q8="Yes",AND(NOT(ISBLANK(P8)),P8<=2)),"Moderate Risk","Low Risk"))) -> High Risk
A9: EMP-11174 | B9: Yash Joshi | C9: DEP-SAL | D9: Enterprise Sales | E9: SAL-L4 | F9: L4 | G9: Director of Enterprise Sales | H9: Bengaluru | I9: Hybrid | J9: 43485 | K9: Involuntary Exit | L9: 45713 | M9: Performance / Restructuring | N9: Campus Recruitment | O9: 3181000 | P9: 5 | Q9: Yes | R9: 46 | S9: MGR-202 | T9: =VALUE(MID(A9,5,5)) -> 11174 | U9: =LEFT(E9,3) -> SAL | V9: =RIGHT(E9,2) -> L4 | W9: =PROPER(TRIM(VLOOKUP(S9,Employee_Lookups!$I$4:$M$19,2,FALSE()))) -> Priya Sharma | X9: =VLOOKUP(C9,Employee_Lookups!$A$4:$G$9,4,FALSE()) -> CC-202 | Y9: =INDEX(Employee_Lookups!$C$13:$C$17,MATCH(F9,Employee_Lookups!$A$13:$A$17,0)) -> Band D (Leadership) | Z9: =_xlfn.XLOOKUP(F9,Employee_Lookups!$A$13:$A$17,Employee_Lookups!$E$13:$E$17,0) -> 2750000 | AA9: =ROUND(O9/INDEX(Employee_Lookups!$E$13:$E$17,MATCH(F9,Employee_Lookups!$A$13:$A$17,0)),3) -> 1.157 | AB9: =YEAR(J9) -> 2019 | AC9: =IF(ISBLANK(L9),"",YEAR(L9)) -> 2025 | AD9: =ROUND((IF(ISBLANK(L9),Employee_Lookups!$O$14,L9)-J9)/365.25,2) -> 6.1 | AE9: =IF(AD9<1,"< 1 Yr (New)",IF(AD9<3,"1 - 3 Yrs",IF(AD9<5,"3 - 5 Yrs","5+ Yrs"))) -> 5+ Yrs | AF9: =IF(K9<>"Active","Exited",IF(AND(Q9="Yes",OR(P9>=4,AA9<0.95)),"High Risk",IF(OR(Q9="Yes",AND(NOT(ISBLANK(P9)),P9<=2)),"Moderate Risk","Low Risk"))) -> Exited
A10: EMP-10746 | B10: Tejas Rao | C10: DEP-ENG | D10: Engineering & Product | E10: ENG-L1 | F10: L1 | G10: Software Engineer I | H10: Pune | I10: Hybrid | J10: 43486 | K10: Involuntary Exit | L10: 43637 | M10: Performance / Restructuring | N10: Company Career Portal | O10: 601000 | P10: 2 | Q10: No | R10: 16 | S10: MGR-103 | T10: =VALUE(MID(A10,5,5)) -> 10746 | U10: =LEFT(E10,3) -> ENG | V10: =RIGHT(E10,2) -> L1 | W10: =PROPER(TRIM(VLOOKUP(S10,Employee_Lookups!$I$4:$M$19,2,FALSE()))) -> Rohan Verma | X10: =VLOOKUP(C10,Employee_Lookups!$A$4:$G$9,4,FALSE()) -> CC-101 | Y10: =INDEX(Employee_Lookups!$C$13:$C$17,MATCH(F10,Employee_Lookups!$A$13:$A$17,0)) -> Band A (Entry) | Z10: =_xlfn.XLOOKUP(F10,Employee_Lookups!$A$13:$A$17,Employee_Lookups!$E$13:$E$17,0) -> 700000 | AA10: =ROUND(O10/INDEX(Employee_Lookups!$E$13:$E$17,MATCH(F10,Employee_Lookups!$A$13:$A$17,0)),3) -> 0.859 | AB10: =YEAR(J10) -> 2019 | AC10: =IF(ISBLANK(L10),"",YEAR(L10)) -> 2019 | AD10: =ROUND((IF(ISBLANK(L10),Employee_Lookups!$O$14,L10)-J10)/365.25,2) -> 0.41 | AE10: =IF(AD10<1,"< 1 Yr (New)",IF(AD10<3,"1 - 3 Yrs",IF(AD10<5,"3 - 5 Yrs","5+ Yrs"))) -> < 1 Yr (New) | AF10: =IF(K10<>"Active","Exited",IF(AND(Q10="Yes",OR(P10>=4,AA10<0.95)),"High Risk",IF(OR(Q10="Yes",AND(NOT(ISBLANK(P10)),P10<=2)),"Moderate Risk","Low Risk"))) -> Exited
A11: EMP-11431 | B11: Pranav Joshi | C11: DEP-FIN | D11: Finance & Strategy | E11: FIN-L1 | F11: L1 | G11: Financial Analyst | H11: Bengaluru | I11: Hybrid | J11: 43492 | K11: Active | M11: N/A - Active | N11: Company Career Portal | O11: 757000 | P11: 5 | Q11: No | R11: 25 | S11: MGR-401 | T11: =VALUE(MID(A11,5,5)) -> 11431 | U11: =LEFT(E11,3) -> FIN | V11: =RIGHT(E11,2) -> L1 | W11: =PROPER(TRIM(VLOOKUP(S11,Employee_Lookups!$I$4:$M$19,2,FALSE()))) -> Rajeshwari Rao | X11: =VLOOKUP(C11,Employee_Lookups!$A$4:$G$9,4,FALSE()) -> CC-404 | Y11: =INDEX(Employee_Lookups!$C$13:$C$17,MATCH(F11,Employee_Lookups!$A$13:$A$17,0)) -> Band A (Entry) | Z11: =_xlfn.XLOOKUP(F11,Employee_Lookups!$A$13:$A$17,Employee_Lookups!$E$13:$E$17,0) -> 700000 | AA11: =ROUND(O11/INDEX(Employee_Lookups!$E$13:$E$17,MATCH(F11,Employee_Lookups!$A$13:$A$17,0)),3) -> 1.081 | AB11: =YEAR(J11) -> 2019 | AC11: =IF(ISBLANK(L11),"",YEAR(L11)) | AD11: =ROUND((IF(ISBLANK(L11),Employee_Lookups!$O$14,L11)-J11)/365.25,2) -> 6.93 | AE11: =IF(AD11<1,"< 1 Yr (New)",IF(AD11<3,"1 - 3 Yrs",IF(AD11<5,"3 - 5 Yrs","5+ Yrs"))) -> 5+ Yrs | AF11: =IF(K11<>"Active","Exited",IF(AND(Q11="Yes",OR(P11>=4,AA11<0.95)),"High Risk",IF(OR(Q11="Yes",AND(NOT(ISBLANK(P11)),P11<=2)),"Moderate Risk","Low Risk"))) -> Low Risk
A12: EMP-10360 | B12: Neha Sharma | C12: DEP-FIN | D12: Finance & Strategy | E12: FIN-L2 | F12: L2 | G12: Senior FP&A Analyst | H12: Bengaluru | I12: Hybrid | J12: 43504 | K12: Voluntary Exit | L12: 43692 | M12: Career Growth | N12: LinkedIn Sourcing | O12: 1215000 | P12: 3 | Q12: No | R12: 38 | S12: MGR-402 | T12: =VALUE(MID(A12,5,5)) -> 10360 | U12: =LEFT(E12,3) -> FIN | V12: =RIGHT(E12,2) -> L2 | W12: =PROPER(TRIM(VLOOKUP(S12,Employee_Lookups!$I$4:$M$19,2,FALSE()))) -> Aditya Gokhale | X12: =VLOOKUP(C12,Employee_Lookups!$A$4:$G$9,4,FALSE()) -> CC-404 | Y12: =INDEX(Employee_Lookups!$C$13:$C$17,MATCH(F12,Employee_Lookups!$A$13:$A$17,0)) -> Band B (Mid) | Z12: =_xlfn.XLOOKUP(F12,Employee_Lookups!$A$13:$A$17,Employee_Lookups!$E$13:$E$17,0) -> 1100000 | AA12: =ROUND(O12/INDEX(Employee_Lookups!$E$13:$E$17,MATCH(F12,Employee_Lookups!$A$13:$A$17,0)),3) -> 1.105 | AB12: =YEAR(J12) -> 2019 | AC12: =IF(ISBLANK(L12),"",YEAR(L12)) -> 2019 | AD12: =ROUND((IF(ISBLANK(L12),Employee_Lookups!$O$14,L12)-J12)/365.25,2) -> 0.51 | AE12: =IF(AD12<1,"< 1 Yr (New)",IF(AD12<3,"1 - 3 Yrs",IF(AD12<5,"3 - 5 Yrs","5+ Yrs"))) -> < 1 Yr (New) | AF12: =IF(K12<>"Active","Exited",IF(AND(Q12="Yes",OR(P12>=4,AA12<0.95)),"High Risk",IF(OR(Q12="Yes",AND(NOT(ISBLANK(P12)),P12<=2)),"Moderate Risk","Low Risk"))) -> Exited
A13: EMP-10920 | B13: Shruti Joshi | C13: DEP-ENG | D13: Engineering & Product | E13: ENG-L3 | F13: L3 | G13: Engineering Manager | H13: Pune | I13: Hybrid | J13: 43508 | K13: Involuntary Exit | L13: 43803 | M13: Performance / Restructuring | N13: LinkedIn Sourcing | O13: 2001000 | P13: 4 | Q13: Yes | R13: 32 | S13: MGR-102 | T13: =VALUE(MID(A13,5,5)) -> 10920 | U13: =LEFT(E13,3) -> ENG | V13: =RIGHT(E13,2) -> L3 | W13: =PROPER(TRIM(VLOOKUP(S13,Employee_Lookups!$I$4:$M$19,2,FALSE()))) -> Neha Kulkarni | X13: =VLOOKUP(C13,Employee_Lookups!$A$4:$G$9,4,FALSE()) -> CC-101 | Y13: =INDEX(Employee_Lookups!$C$13:$C$17,MATCH(F13,Employee_Lookups!$A$13:$A$17,0)) -> Band C (Senior) | Z13: =_xlfn.XLOOKUP(F13,Employee_Lookups!$A$13:$A$17,Employee_Lookups!$E$13:$E$17,0) -> 1725000 | AA13: =ROUND(O13/INDEX(Employee_Lookups!$E$13:$E$17,MATCH(F13,Employee_Lookups!$A$13:$A$17,0)),3) -> 1.16 | AB13: =YEAR(J13) -> 2019 | AC13: =IF(ISBLANK(L13),"",YEAR(L13)) -> 2019 | AD13: =ROUND((IF(ISBLANK(L13),Employee_Lookups!$O$14,L13)-J13)/365.25,2) -> 0.81 | AE13: =IF(AD13<1,"< 1 Yr (New)",IF(AD13<3,"1 - 3 Yrs",IF(AD13<5,"3 - 5 Yrs","5+ Yrs"))) -> < 1 Yr (New) | AF13: =IF(K13<>"Active","Exited",IF(AND(Q13="Yes",OR(P13>=4,AA13<0.95)),"High Risk",IF(OR(Q13="Yes",AND(NOT(ISBLANK(P13)),P13<=2)),"Moderate Risk","Low Risk"))) -> Exited
A14: EMP-10123 | B14: Diya Verma | C14: DEP-MKT | D14: Growth Marketing | E14: MKT-L2 | F14: L2 | G14: Growth Specialist | H14: Bengaluru | I14: Hybrid | J14: 43516 | K14: Voluntary Exit | L14: 44142 | M14: Career Growth | N14: LinkedIn Sourcing | O14: 1160000 | P14: 5 | Q14: No | R14: 38 | S14: MGR-601 | T14: =VALUE(MID(A14,5,5)) -> 10123 | U14: =LEFT(E14,3) -> MKT | V14: =RIGHT(E14,2) -> L2 | W14: =PROPER(TRIM(VLOOKUP(S14,Employee_Lookups!$I$4:$M$19,2,FALSE()))) -> Tanvi Chitnis | X14: =VLOOKUP(C14,Employee_Lookups!$A$4:$G$9,4,FALSE()) -> CC-606 | Y14: =INDEX(Employee_Lookups!$C$13:$C$17,MATCH(F14,Employee_Lookups!$A$13:$A$17,0)) -> Band B (Mid) | Z14: =_xlfn.XLOOKUP(F14,Employee_Lookups!$A$13:$A$17,Employee_Lookups!$E$13:$E$17,0) -> 1100000 | AA14: =ROUND(O14/INDEX(Employee_Lookups!$E$13:$E$17,MATCH(F14,Employee_Lookups!$A$13:$A$17,0)),3) -> 1.055 | AB14: =YEAR(J14) -> 2019 | AC14: =IF(ISBLANK(L14),"",YEAR(L14)) -> 2020 | AD14: =ROUND((IF(ISBLANK(L14),Employee_Lookups!$O$14,L14)-J14)/365.25,2) -> 1.71 | AE14: =IF(AD14<1,"< 1 Yr (New)",IF(AD14<3,"1 - 3 Yrs",IF(AD14<5,"3 - 5 Yrs","5+ Yrs"))) -> 1 - 3 Yrs | AF14: =IF(K14<>"Active","Exited",IF(AND(Q14="Yes",OR(P14>=4,AA14<0.95)),"High Risk",IF(OR(Q14="Yes",AND(NOT(ISBLANK(P14)),P14<=2)),"Moderate Risk","Low Risk"))) -> Exited
A15: EMP-10426 | B15: Vihaan Sharma | C15: DEP-ENG | D15: Engineering & Product | E15: ENG-L2 | F15: L2 | G15: Software Engineer II | H15: Pune | I15: Hybrid | J15: 43518 | K15: Active | M15: N/A - Active | N15: LinkedIn Sourcing | O15: 1121000 | P15: 3 | Q15: Yes | R15: 20 | S15: MGR-101 | T15: =VALUE(MID(A15,5,5)) -> 10426 | U15: =LEFT(E15,3) -> ENG | V15: =RIGHT(E15,2) -> L2 | W15: =PROPER(TRIM(VLOOKUP(S15,Employee_Lookups!$I$4:$M$19,2,FALSE()))) -> Aarav Deshmukh | X15: =VLOOKUP(C15,Employee_Lookups!$A$4:$G$9,4,FALSE()) -> CC-101 | Y15: =INDEX(Employee_Lookups!$C$13:$C$17,MATCH(F15,Employee_Lookups!$A$13:$A$17,0)) -> Band B (Mid) | Z15: =_xlfn.XLOOKUP(F15,Employee_Lookups!$A$13:$A$17,Employee_Lookups!$E$13:$E$17,0) -> 1100000 | AA15: =ROUND(O15/INDEX(Employee_Lookups!$E$13:$E$17,MATCH(F15,Employee_Lookups!$A$13:$A$17,0)),3) -> 1.019 | AB15: =YEAR(J15) -> 2019 | AC15: =IF(ISBLANK(L15),"",YEAR(L15)) | AD15: =ROUND((IF(ISBLANK(L15),Employee_Lookups!$O$14,L15)-J15)/365.25,2) -> 6.86 | AE15: =IF(AD15<1,"< 1 Yr (New)",IF(AD15<3,"1 - 3 Yrs",IF(AD15<5,"3 - 5 Yrs","5+ Yrs"))) -> 5+ Yrs | AF15: =IF(K15<>"Active","Exited",IF(AND(Q15="Yes",OR(P15>=4,AA15<0.95)),"High Risk",IF(OR(Q15="Yes",AND(NOT(ISBLANK(P15)),P15<=2)),"Moderate Risk","Low Risk"))) -> Moderate Risk
A16: EMP-10013 | B16: Krishna Sengupta | C16: DEP-OPS | D16: Customer Operations | E16: OPS-L2 | F16: L2 | G16: Customer Success Specialist | H16: Bengaluru | I16: Hybrid | J16: 43521 | K16: Active | M16: N/A - Active | N16: Employee Referral | O16: 905000 | P16: 3 | Q16: Yes | R16: 37 | S16: MGR-302 | T16: =VALUE(MID(A16,5,5)) -> 10013 | U16: =LEFT(E16,3) -> OPS | V16: =RIGHT(E16,2) -> L2 | W16: =PROPER(TRIM(VLOOKUP(S16,Employee_Lookups!$I$4:$M$19,2,FALSE()))) -> Deepak Patil | X16: =VLOOKUP(C16,Employee_Lookups!$A$4:$G$9,4,FALSE()) -> CC-303 | Y16: =INDEX(Employee_Lookups!$C$13:$C$17,MATCH(F16,Employee_Lookups!$A$13:$A$17,0)) -> Band B (Mid) | Z16: =_xlfn.XLOOKUP(F16,Employee_Lookups!$A$13:$A$17,Employee_Lookups!$E$13:$E$17,0) -> 1100000 | AA16: =ROUND(O16/INDEX(Employee_Lookups!$E$13:$E$17,MATCH(F16,Employee_Lookups!$A$13:$A$17,0)),3) -> 0.823 | AB16: =YEAR(J16) -> 2019 | AC16: =IF(ISBLANK(L16),"",YEAR(L16)) | AD16: =ROUND((IF(ISBLANK(L16),Employee_Lookups!$O$14,L16)-J16)/365.25,2) -> 6.85 | AE16: =IF(AD16<1,"< 1 Yr (New)",IF(AD16<3,"1 - 3 Yrs",IF(AD16<5,"3 - 5 Yrs","5+ Yrs"))) -> 5+ Yrs | AF16: =IF(K16<>"Active","Exited",IF(AND(Q16="Yes",OR(P16>=4,AA16<0.95)),"High Risk",IF(OR(Q16="Yes",AND(NOT(ISBLANK(P16)),P16<=2)),"Moderate Risk","Low Risk"))) -> High Risk
A17: EMP-10687 | B17: Omkar Sharma | C17: DEP-MKT | D17: Growth Marketing | E17: MKT-L1 | F17: L1 | G17: Marketing Associate | H17: Hyderabad | I17: On-Site | J17: 43530 | K17: Voluntary Exit | L17: 45397 | M17: Higher Education | N17: External Agency | O17: 565000 | P17: 3 | Q17: No | R17: 24 | S17: MGR-601 | T17: =VALUE(MID(A17,5,5)) -> 10687 | U17: =LEFT(E17,3) -> MKT | V17: =RIGHT(E17,2) -> L1 | W17: =PROPER(TRIM(VLOOKUP(S17,Employee_Lookups!$I$4:$M$19,2,FALSE()))) -> Tanvi Chitnis | X17: =VLOOKUP(C17,Employee_Lookups!$A$4:$G$9,4,FALSE()) -> CC-606 | Y17: =INDEX(Employee_Lookups!$C$13:$C$17,MATCH(F17,Employee_Lookups!$A$13:$A$17,0)) -> Band A (Entry) | Z17: =_xlfn.XLOOKUP(F17,Employee_Lookups!$A$13:$A$17,Employee_Lookups!$E$13:$E$17,0) -> 700000 | AA17: =ROUND(O17/INDEX(Employee_Lookups!$E$13:$E$17,MATCH(F17,Employee_Lookups!$A$13:$A$17,0)),3) -> 0.807 | AB17: =YEAR(J17) -> 2019 | AC17: =IF(ISBLANK(L17),"",YEAR(L17)) -> 2024 | AD17: =ROUND((IF(ISBLANK(L17),Employee_Lookups!$O$14,L17)-J17)/365.25,2) -> 5.11 | AE17: =IF(AD17<1,"< 1 Yr (New)",IF(AD17<3,"1 - 3 Yrs",IF(AD17<5,"3 - 5 Yrs","5+ Yrs"))) -> 5+ Yrs | AF17: =IF(K17<>"Active","Exited",IF(AND(Q17="Yes",OR(P17>=4,AA17<0.95)),"High Risk",IF(OR(Q17="Yes",AND(NOT(ISBLANK(P17)),P17<=2)),"Moderate Risk","Low Risk"))) -> Exited
A18: EMP-10004 | B18: Neha Gokhale | C18: DEP-FIN | D18: Finance & Strategy | E18: FIN-L1 | F18: L1 | G18: Financial Analyst | H18: Pune | I18: Hybrid | J18: 43531 | K18: Voluntary Exit | L18: 43742 | M18: Career Growth | N18: Campus Recruitment | O18: 651000 | P18: 3 | Q18: No | R18: 19 | S18: MGR-402 | T18: =VALUE(MID(A18,5,5)) -> 10004 | U18: =LEFT(E18,3) -> FIN | V18: =RIGHT(E18,2) -> L1 | W18: =PROPER(TRIM(VLOOKUP(S18,Employee_Lookups!$I$4:$M$19,2,FALSE()))) -> Aditya Gokhale | X18: =VLOOKUP(C18,Employee_Lookups!$A$4:$G$9,4,FALSE()) -> CC-404 | Y18: =INDEX(Employee_Lookups!$C$13:$C$17,MATCH(F18,Employee_Lookups!$A$13:$A$17,0)) -> Band A (Entry) | Z18: =_xlfn.XLOOKUP(F18,Employee_Lookups!$A$13:$A$17,Employee_Lookups!$E$13:$E$17,0) -> 700000 | AA18: =ROUND(O18/INDEX(Employee_Lookups!$E$13:$E$17,MATCH(F18,Employee_Lookups!$A$13:$A$17,0)),3) -> 0.93 | AB18: =YEAR(J18) -> 2019 | AC18: =IF(ISBLANK(L18),"",YEAR(L18)) -> 2019 | AD18: =ROUND((IF(ISBLANK(L18),Employee_Lookups!$O$14,L18)-J18)/365.25,2) -> 0.58 | AE18: =IF(AD18<1,"< 1 Yr (New)",IF(AD18<3,"1 - 3 Yrs",IF(AD18<5,"3 - 5 Yrs","5+ Yrs"))) -> < 1 Yr (New) | AF18: =IF(K18<>"Active","Exited",IF(AND(Q18="Yes",OR(P18>=4,AA18<0.95)),"High Risk",IF(OR(Q18="Yes",AND(NOT(ISBLANK(P18)),P18<=2)),"Moderate Risk","Low Risk"))) -> Exited
A19: EMP-11084 | B19: Reyansh Bhatt | C19: DEP-SAL | D19: Enterprise Sales | E19: SAL-L2 | F19: L2 | G19: Account Executive | H19: Bengaluru | I19: Hybrid | J19: 43533 | K19: Active | M19: N/A - Active | N19: Employee Referral | O19: 1150000 | P19: 3 | Q19: No | R19: 34 | S19: MGR-203 | T19: =VALUE(MID(A19,5,5)) -> 11084 | U19: =LEFT(E19,3) -> SAL | V19: =RIGHT(E19,2) -> L2 | W19: =PROPER(TRIM(VLOOKUP(S19,Employee_Lookups!$I$4:$M$19,2,FALSE()))) -> Karan Malhotra | X19: =VLOOKUP(C19,Employee_Lookups!$A$4:$G$9,4,FALSE()) -> CC-202 | Y19: =INDEX(Employee_Lookups!$C$13:$C$17,MATCH(F19,Employee_Lookups!$A$13:$A$17,0)) -> Band B (Mid) | Z19: =_xlfn.XLOOKUP(F19,Employee_Lookups!$A$13:$A$17,Employee_Lookups!$E$13:$E$17,0) -> 1100000 | AA19: =ROUND(O19/INDEX(Employee_Lookups!$E$13:$E$17,MATCH(F19,Employee_Lookups!$A$13:$A$17,0)),3) -> 1.045 | AB19: =YEAR(J19) -> 2019 | AC19: =IF(ISBLANK(L19),"",YEAR(L19)) | AD19: =ROUND((IF(ISBLANK(L19),Employee_Lookups!$O$14,L19)-J19)/365.25,2) -> 6.81 | AE19: =IF(AD19<1,"< 1 Yr (New)",IF(AD19<3,"1 - 3 Yrs",IF(AD19<5,"3 - 5 Yrs","5+ Yrs"))) -> 5+ Yrs | AF19: =IF(K19<>"Active","Exited",IF(AND(Q19="Yes",OR(P19>=4,AA19<0.95)),"High Risk",IF(OR(Q19="Yes",AND(NOT(ISBLANK(P19)),P19<=2)),"Moderate Risk","Low Risk"))) -> Low Risk
A20: EMP-10414 | B20: Omkar Joshi | C20: DEP-OPS | D20: Customer Operations | E20: OPS-L3 | F20: L3 | G20: Operations Lead | H20: Hyderabad | I20: On-Site | J20: 43535 | K20: Active | M20: N/A - Active | N20: Campus Recruitment | O20: 1528000 | P20: 3 | Q20: No | R20: 38 | S20: MGR-302 | T20: =VALUE(MID(A20,5,5)) -> 10414 | U20: =LEFT(E20,3) -> OPS | V20: =RIGHT(E20,2) -> L3 | W20: =PROPER(TRIM(VLOOKUP(S20,Employee_Lookups!$I$4:$M$19,2,FALSE()))) -> Deepak Patil | X20: =VLOOKUP(C20,Employee_Lookups!$A$4:$G$9,4,FALSE()) -> CC-303 | Y20: =INDEX(Employee_Lookups!$C$13:$C$17,MATCH(F20,Employee_Lookups!$A$13:$A$17,0)) -> Band C (Senior) | Z20: =_xlfn.XLOOKUP(F20,Employee_Lookups!$A$13:$A$17,Employee_Lookups!$E$13:$E$17,0) -> 1725000 | AA20: =ROUND(O20/INDEX(Employee_Lookups!$E$13:$E$17,MATCH(F20,Employee_Lookups!$A$13:$A$17,0)),3) -> 0.886 | AB20: =YEAR(J20) -> 2019 | AC20: =IF(ISBLANK(L20),"",YEAR(L20)) | AD20: =ROUND((IF(ISBLANK(L20),Employee_Lookups!$O$14,L20)-J20)/365.25,2) -> 6.81 | AE20: =IF(AD20<1,"< 1 Yr (New)",IF(AD20<3,"1 - 3 Yrs",IF(AD20<5,"3 - 5 Yrs","5+ Yrs"))) -> 5+ Yrs | AF20: =IF(K20<>"Active","Exited",IF(AND(Q20="Yes",OR(P20>=4,AA20<0.95)),"High Risk",IF(OR(Q20="Yes",AND(NOT(ISBLANK(P20)),P20<=2)),"Moderate Risk","Low Risk"))) -> Low Risk
A21: EMP-11177 | B21: Neha Chatterjee | C21: DEP-ENG | D21: Engineering & Product | E21: ENG-L3 | F21: L3 | G21: Engineering Manager | H21: Remote-India | I21: Remote | J21: 43536 | K21: Active | M21: N/A - Active | N21: LinkedIn Sourcing | O21: 1603000 | P21: 2 | Q21: No | R21: 31 | S21: MGR-104 | T21: =VALUE(MID(A21,5,5)) -> 11177 | U21: =LEFT(E21,3) -> ENG | V21: =RIGHT(E21,2) -> L3 | W21: =PROPER(TRIM(VLOOKUP(S21,Employee_Lookups!$I$4:$M$19,2,FALSE()))) -> Siddharth Nair | X21: =VLOOKUP(C21,Employee_Lookups!$A$4:$G$9,4,FALSE()) -> CC-101 | Y21: =INDEX(Employee_Lookups!$C$13:$C$17,MATCH(F21,Employee_Lookups!$A$13:$A$17,0)) -> Band C (Senior) | Z21: =_xlfn.XLOOKUP(F21,Employee_Lookups!$A$13:$A$17,Employee_Lookups!$E$13:$E$17,0) -> 1725000 | AA21: =ROUND(O21/INDEX(Employee_Lookups!$E$13:$E$17,MATCH(F21,Employee_Lookups!$A$13:$A$17,0)),3) -> 0.929 | AB21: =YEAR(J21) -> 2019 | AC21: =IF(ISBLANK(L21),"",YEAR(L21)) | AD21: =ROUND((IF(ISBLANK(L21),Employee_Lookups!$O$14,L21)-J21)/365.25,2) -> 6.81 | AE21: =IF(AD21<1,"< 1 Yr (New)",IF(AD21<3,"1 - 3 Yrs",IF(AD21<5,"3 - 5 Yrs","5+ Yrs"))) -> 5+ Yrs | AF21: =IF(K21<>"Active","Exited",IF(AND(Q21="Yes",OR(P21>=4,AA21<0.95)),"High Risk",IF(OR(Q21="Yes",AND(NOT(ISBLANK(P21)),P21<=2)),"Moderate Risk","Low Risk"))) -> Moderate Risk
A22: EMP-10739 | B22: Tejas Kapoor | C22: DEP-SAL | D22: Enterprise Sales | E22: SAL-L3 | F22: L3 | G22: Regional Sales Manager | H22: Hyderabad | I22: On-Site | J22: 43539 | K22: Active | M22: N/A - Active | N22: LinkedIn Sourcing | O22: 1764000 | P22: 3 | Q22: No | R22: 45 | S22: MGR-203 | T22: =VALUE(MID(A22,5,5)) -> 10739 | U22: =LEFT(E22,3) -> SAL | V22: =RIGHT(E22,2) -> L3 | W22: =PROPER(TRIM(VLOOKUP(S22,Employee_Lookups!$I$4:$M$19,2,FALSE()))) -> Karan Malhotra | X22: =VLOOKUP(C22,Employee_Lookups!$A$4:$G$9,4,FALSE()) -> CC-202 | Y22: =INDEX(Employee_Lookups!$C$13:$C$17,MATCH(F22,Employee_Lookups!$A$13:$A$17,0)) -> Band C (Senior) | Z22: =_xlfn.XLOOKUP(F22,Employee_Lookups!$A$13:$A$17,Employee_Lookups!$E$13:$E$17,0) -> 1725000 | AA22: =ROUND(O22/INDEX(Employee_Lookups!$E$13:$E$17,MATCH(F22,Employee_Lookups!$A$13:$A$17,0)),3) -> 1.023 | AB22: =YEAR(J22) -> 2019 | AC22: =IF(ISBLANK(L22),"",YEAR(L22)) | AD22: =ROUND((IF(ISBLANK(L22),Employee_Lookups!$O$14,L22)-J22)/365.25,2) -> 6.8 | AE22: =IF(AD22<1,"< 1 Yr (New)",IF(AD22<3,"1 - 3 Yrs",IF(AD22<5,"3 - 5 Yrs","5+ Yrs"))) -> 5+ Yrs | AF22: =IF(K22<>"Active","Exited",IF(AND(Q22="Yes",OR(P22>=4,AA22<0.95)),"High Risk",IF(OR(Q22="Yes",AND(NOT(ISBLANK(P22)),P22<=2)),"Moderate Risk","Low Risk"))) -> Low Risk
A23: EMP-11332 | B23: Navya Iyer | C23: DEP-OPS | D23: Customer Operations | E23: OPS-L3 | F23: L3 | G23: Operations Lead | H23: Pune | I23: Hybrid | J23: 43544 | K23: Active | M23: N/A - Active | N23: LinkedIn Sourcing | O23: 1806000 | P23: 4 | Q23: Yes | R23: 0 | S23: MGR-302 | T23: =VALUE(MID(A23,5,5)) -> 11332 | U23: =LEFT(E23,3) -> OPS | V23: =RIGHT(E23,2) -> L3 | W23: =PROPER(TRIM(VLOOKUP(S23,Employee_Lookups!$I$4:$M$19,2,FALSE()))) -> Deepak Patil | X23: =VLOOKUP(C23,Employee_Lookups!$A$4:$G$9,4,FALSE()) -> CC-303 | Y23: =INDEX(Employee_Lookups!$C$13:$C$17,MATCH(F23,Employee_Lookups!$A$13:$A$17,0)) -> Band C (Senior) | Z23: =_xlfn.XLOOKUP(F23,Employee_Lookups!$A$13:$A$17,Employee_Lookups!$E$13:$E$17,0) -> 1725000 | AA23: =ROUND(O23/INDEX(Employee_Lookups!$E$13:$E$17,MATCH(F23,Employee_Lookups!$A$13:$A$17,0)),3) -> 1.047 | AB23: =YEAR(J23) -> 2019 | AC23: =IF(ISBLANK(L23),"",YEAR(L23)) | AD23: =ROUND((IF(ISBLANK(L23),Employee_Lookups!$O$14,L23)-J23)/365.25,2) -> 6.78 | AE23: =IF(AD23<1,"< 1 Yr (New)",IF(AD23<3,"1 - 3 Yrs",IF(AD23<5,"3 - 5 Yrs","5+ Yrs"))) -> 5+ Yrs | AF23: =IF(K23<>"Active","Exited",IF(AND(Q23="Yes",OR(P23>=4,AA23<0.95)),"High Risk",IF(OR(Q23="Yes",AND(NOT(ISBLANK(P23)),P23<=2)),"Moderate Risk","Low Risk"))) -> High Risk
A24: EMP-11268 | B24: Meera Iyer | C24: DEP-HR | D24: People & Talent | E24: -HR-L2 | F24: L2 | G24: Talent Acquisition Partner | H24: Bengaluru | I24: Hybrid | J24: 43551 | K24: Active | M24: N/A - Active | N24: Employee Referral | O24: 1297000 | P24: 3 | Q24: Yes | R24: 39 | S24: MGR-502 | T24: =VALUE(MID(A24,5,5)) -> 11268 | U24: =LEFT(E24,3) -> -HR | V24: =RIGHT(E24,2) -> L2 | W24: =PROPER(TRIM(VLOOKUP(S24,Employee_Lookups!$I$4:$M$19,2,FALSE()))) -> Nikhil Chatterjee | X24: =VLOOKUP(C24,Employee_Lookups!$A$4:$G$9,4,FALSE()) -> CC-505 | Y24: =INDEX(Employee_Lookups!$C$13:$C$17,MATCH(F24,Employee_Lookups!$A$13:$A$17,0)) -> Band B (Mid) | Z24: =_xlfn.XLOOKUP(F24,Employee_Lookups!$A$13:$A$17,Employee_Lookups!$E$13:$E$17,0) -> 1100000 | AA24: =ROUND(O24/INDEX(Employee_Lookups!$E$13:$E$17,MATCH(F24,Employee_Lookups!$A$13:$A$17,0)),3) -> 1.179 | AB24: =YEAR(J24) -> 2019 | AC24: =IF(ISBLANK(L24),"",YEAR(L24)) | AD24: =ROUND((IF(ISBLANK(L24),Employee_Lookups!$O$14,L24)-J24)/365.25,2) -> 6.77 | AE24: =IF(AD24<1,"< 1 Yr (New)",IF(AD24<3,"1 - 3 Yrs",IF(AD24<5,"3 - 5 Yrs","5+ Yrs"))) -> 5+ Yrs | AF24: =IF(K24<>"Active","Exited",IF(AND(Q24="Yes",OR(P24>=4,AA24<0.95)),"High Risk",IF(OR(Q24="Yes",AND(NOT(ISBLANK(P24)),P24<=2)),"Moderate Risk","Low Risk"))) -> Moderate Risk
A25: EMP-11152 | B25: Ayaan Iyer | C25: DEP-ENG | D25: Engineering & Product | E25: ENG-L2 | F25: L2 | G25: Software Engineer II | H25: Hyderabad | I25: On-Site | J25: 43552 | K25: Active | M25: N/A - Active | N25: LinkedIn Sourcing | O25: 940000 | P25: 4 | Q25: No | R25: 26 | S25: MGR-101 | T25: =VALUE(MID(A25,5,5)) -> 11152 | U25: =LEFT(E25,3) -> ENG | V25: =RIGHT(E25,2) -> L2 | W25: =PROPER(TRIM(VLOOKUP(S25,Employee_Lookups!$I$4:$M$19,2,FALSE()))) -> Aarav Deshmukh | X25: =VLOOKUP(C25,Employee_Lookups!$A$4:$G$9,4,FALSE()) -> CC-101 | Y25: =INDEX(Employee_Lookups!$C$13:$C$17,MATCH(F25,Employee_Lookups!$A$13:$A$17,0)) -> Band B (Mid) | Z25: =_xlfn.XLOOKUP(F25,Employee_Lookups!$A$13:$A$17,Employee_Lookups!$E$13:$E$17,0) -> 1100000 | AA25: =ROUND(O25/INDEX(Employee_Lookups!$E$13:$E$17,MATCH(F25,Employee_Lookups!$A$13:$A$17,0)),3) -> 0.855 | AB25: =YEAR(J25) -> 2019 | AC25: =IF(ISBLANK(L25),"",YEAR(L25)) | AD25: =ROUND((IF(ISBLANK(L25),Employee_Lookups!$O$14,L25)-J25)/365.25,2) -> 6.76 | AE25: =IF(AD25<1,"< 1 Yr (New)",IF(AD25<3,"1 - 3 Yrs",IF(AD25<5,"3 - 5 Yrs","5+ Yrs"))) -> 5+ Yrs | AF25: =IF(K25<>"Active","Exited",IF(AND(Q25="Yes",OR(P25>=4,AA25<0.95)),"High Risk",IF(OR(Q25="Yes",AND(NOT(ISBLANK(P25)),P25<=2)),"Moderate Risk","Low Risk"))) -> Low Risk
A26: EMP-10245 | B26: Myra Shah | C26: DEP-ENG | D26: Engineering & Product | E26: ENG-L2 | F26: L2 | G26: Software Engineer II | H26: Remote-India | I26: Remote | J26: 43563 | K26: Active | M26: N/A - Active | N26: Company Career Portal | O26: 999000 | P26: 2 | Q26: Yes | R26: 26 | S26: MGR-104 | T26: =VALUE(MID(A26,5,5)) -> 10245 | U26: =LEFT(E26,3) -> ENG | V26: =RIGHT(E26,2) -> L2 | W26: =PROPER(TRIM(VLOOKUP(S26,Employee_Lookups!$I$4:$M$19,2,FALSE()))) -> Siddharth Nair | X26: =VLOOKUP(C26,Employee_Lookups!$A$4:$G$9,4,FALSE()) -> CC-101 | Y26: =INDEX(Employee_Lookups!$C$13:$C$17,MATCH(F26,Employee_Lookups!$A$13:$A$17,0)) -> Band B (Mid) | Z26: =_xlfn.XLOOKUP(F26,Employee_Lookups!$A$13:$A$17,Employee_Lookups!$E$13:$E$17,0) -> 1100000 | AA26: =ROUND(O26/INDEX(Employee_Lookups!$E$13:$E$17,MATCH(F26,Employee_Lookups!$A$13:$A$17,0)),3) -> 0.908 | AB26: =YEAR(J26) -> 2019 | AC26: =IF(ISBLANK(L26),"",YEAR(L26)) | AD26: =ROUND((IF(ISBLANK(L26),Employee_Lookups!$O$14,L26)-J26)/365.25,2) -> 6.73 | AE26: =IF(AD26<1,"< 1 Yr (New)",IF(AD26<3,"1 - 3 Yrs",IF(AD26<5,"3 - 5 Yrs","5+ Yrs"))) -> 5+ Yrs | AF26: =IF(K26<>"Active","Exited",IF(AND(Q26="Yes",OR(P26>=4,AA26<0.95)),"High Risk",IF(OR(Q26="Yes",AND(NOT(ISBLANK(P26)),P26<=2)),"Moderate Risk","Low Risk"))) -> High Risk
A27: EMP-10019 | B27: Riya Nair | C27: DEP-ENG | D27: Engineering & Product | E27: ENG-L2 | F27: L2 | G27: Software Engineer II | H27: Bengaluru | I27: Hybrid | J27: 43574 | K27: Active | M27: N/A - Active | N27: LinkedIn Sourcing | O27: 893000 | P27: 3 | Q27: No | R27: 28 | S27: MGR-101 | T27: =VALUE(MID(A27,5,5)) -> 10019 | U27: =LEFT(E27,3) -> ENG | V27: =RIGHT(E27,2) -> L2 | W27: =PROPER(TRIM(VLOOKUP(S27,Employee_Lookups!$I$4:$M$19,2,FALSE()))) -> Aarav Deshmukh | X27: =VLOOKUP(C27,Employee_Lookups!$A$4:$G$9,4,FALSE()) -> CC-101 | Y27: =INDEX(Employee_Lookups!$C$13:$C$17,MATCH(F27,Employee_Lookups!$A$13:$A$17,0)) -> Band B (Mid) | Z27: =_xlfn.XLOOKUP(F27,Employee_Lookups!$A$13:$A$17,Employee_Lookups!$E$13:$E$17,0) -> 1100000 | AA27: =ROUND(O27/INDEX(Employee_Lookups!$E$13:$E$17,MATCH(F27,Employee_Lookups!$A$13:$A$17,0)),3) -> 0.812 | AB27: =YEAR(J27) -> 2019 | AC27: =IF(ISBLANK(L27),"",YEAR(L27)) | AD27: =ROUND((IF(ISBLANK(L27),Employee_Lookups!$O$14,L27)-J27)/365.25,2) -> 6.7 | AE27: =IF(AD27<1,"< 1 Yr (New)",IF(AD27<3,"1 - 3 Yrs",IF(AD27<5,"3 - 5 Yrs","5+ Yrs"))) -> 5+ Yrs | AF27: =IF(K27<>"Active","Exited",IF(AND(Q27="Yes",OR(P27>=4,AA27<0.95)),"High Risk",IF(OR(Q27="Yes",AND(NOT(ISBLANK(P27)),P27<=2)),"Moderate Risk","Low Risk"))) -> Low Risk
A28: EMP-11308 | B28: Vikram Nair | C28: DEP-OPS | D28: Customer Operations | E28: OPS-L4 | F28: L4 | G28: Director of Operations | H28: Hyderabad | I28: On-Site | J28: 43577 | K28: Voluntary Exit | L28: 43617 | M28: Career Growth | N28: External Agency | O28: 2289000 | P28: 3 | Q28: Yes | R28: 33 | S28: MGR-301 | T28: =VALUE(MID(A28,5,5)) -> 11308 | U28: =LEFT(E28,3) -> OPS | V28: =RIGHT(E28,2) -> L4 | W28: =PROPER(TRIM(VLOOKUP(S28,Employee_Lookups!$I$4:$M$19,2,FALSE()))) -> Ananya Iyer | X28: =VLOOKUP(C28,Employee_Lookups!$A$4:$G$9,4,FALSE()) -> CC-303 | Y28: =INDEX(Employee_Lookups!$C$13:$C$17,MATCH(F28,Employee_Lookups!$A$13:$A$17,0)) -> Band D (Leadership) | Z28: =_xlfn.XLOOKUP(F28,Employee_Lookups!$A$13:$A$17,Employee_Lookups!$E$13:$E$17,0) -> 2750000 | AA28: =ROUND(O28/INDEX(Employee_Lookups!$E$13:$E$17,MATCH(F28,Employee_Lookups!$A$13:$A$17,0)),3) -> 0.832 | AB28: =YEAR(J28) -> 2019 | AC28: =IF(ISBLANK(L28),"",YEAR(L28)) -> 2019 | AD28: =ROUND((IF(ISBLANK(L28),Employee_Lookups!$O$14,L28)-J28)/365.25,2) -> 0.11 | AE28: =IF(AD28<1,"< 1 Yr (New)",IF(AD28<3,"1 - 3 Yrs",IF(AD28<5,"3 - 5 Yrs","5+ Yrs"))) -> < 1 Yr (New) | AF28: =IF(K28<>"Active","Exited",IF(AND(Q28="Yes",OR(P28>=4,AA28<0.95)),"High Risk",IF(OR(Q28="Yes",AND(NOT(ISBLANK(P28)),P28<=2)),"Moderate Risk","Low Risk"))) -> Exited
A29: EMP-11214 | B29: Kavya Sharma | C29: DEP-ENG | D29: Engineering & Product | E29: ENG-L1 | F29: L1 | G29: Software Engineer I | H29: Bengaluru | I29: Hybrid | J29: 43579 | K29: Active | M29: N/A - Active | N29: Company Career Portal | O29: 661000 | P29: 2 | Q29: No | R29: 25 | S29: MGR-104 | T29: =VALUE(MID(A29,5,5)) -> 11214 | U29: =LEFT(E29,3) -> ENG | V29: =RIGHT(E29,2) -> L1 | W29: =PROPER(TRIM(VLOOKUP(S29,Employee_Lookups!$I$4:$M$19,2,FALSE()))) -> Siddharth Nair | X29: =VLOOKUP(C29,Employee_Lookups!$A$4:$G$9,4,FALSE()) -> CC-101 | Y29: =INDEX(Employee_Lookups!$C$13:$C$17,MATCH(F29,Employee_Lookups!$A$13:$A$17,0)) -> Band A (Entry) | Z29: =_xlfn.XLOOKUP(F29,Employee_Lookups!$A$13:$A$17,Employee_Lookups!$E$13:$E$17,0) -> 700000 | AA29: =ROUND(O29/INDEX(Employee_Lookups!$E$13:$E$17,MATCH(F29,Employee_Lookups!$A$13:$A$17,0)),3) -> 0.944 | AB29: =YEAR(J29) -> 2019 | AC29: =IF(ISBLANK(L29),"",YEAR(L29)) | AD29: =ROUND((IF(ISBLANK(L29),Employee_Lookups!$O$14,L29)-J29)/365.25,2) -> 6.69 | AE29: =IF(AD29<1,"< 1 Yr (New)",IF(AD29<3,"1 - 3 Yrs",IF(AD29<5,"3 - 5 Yrs","5+ Yrs"))) -> 5+ Yrs | AF29: =IF(K29<>"Active","Exited",IF(AND(Q29="Yes",OR(P29>=4,AA29<0.95)),"High Risk",IF(OR(Q29="Yes",AND(NOT(ISBLANK(P29)),P29<=2)),"Moderate Risk","Low Risk"))) -> Moderate Risk
A30: EMP-11425 | B30: Navya Nair | C30: DEP-ENG | D30: Engineering & Product | E30: ENG-L3 | F30: L3 | G30: Engineering Manager | H30: Bengaluru | I30: Hybrid | J30: 43581 | K30: Active | M30: N/A - Active | N30: External Agency | O30: 1621000 | P30: 3 | Q30: No | R30: 24 | S30: MGR-103 | T30: =VALUE(MID(A30,5,5)) -> 11425 | U30: =LEFT(E30,3) -> ENG | V30: =RIGHT(E30,2) -> L3 | W30: =PROPER(TRIM(VLOOKUP(S30,Employee_Lookups!$I$4:$M$19,2,FALSE()))) -> Rohan Verma | X30: =VLOOKUP(C30,Employee_Lookups!$A$4:$G$9,4,FALSE()) -> CC-101 | Y30: =INDEX(Employee_Lookups!$C$13:$C$17,MATCH(F30,Employee_Lookups!$A$13:$A$17,0)) -> Band C (Senior) | Z30: =_xlfn.XLOOKUP(F30,Employee_Lookups!$A$13:$A$17,Employee_Lookups!$E$13:$E$17,0) -> 1725000 | AA30: =ROUND(O30/INDEX(Employee_Lookups!$E$13:$E$17,MATCH(F30,Employee_Lookups!$A$13:$A$17,0)),3) -> 0.94 | AB30: =YEAR(J30) -> 2019 | AC30: =IF(ISBLANK(L30),"",YEAR(L30)) | AD30: =ROUND((IF(ISBLANK(L30),Employee_Lookups!$O$14,L30)-J30)/365.25,2) -> 6.68 | AE30: =IF(AD30<1,"< 1 Yr (New)",IF(AD30<3,"1 - 3 Yrs",IF(AD30<5,"3 - 5 Yrs","5+ Yrs"))) -> 5+ Yrs | AF30: =IF(K30<>"Active","Exited",IF(AND(Q30="Yes",OR(P30>=4,AA30<0.95)),"High Risk",IF(OR(Q30="Yes",AND(NOT(ISBLANK(P30)),P30<=2)),"Moderate Risk","Low Risk"))) -> Low Risk
A31: EMP-11185 | B31: Pari Joshi | C31: DEP-ENG | D31: Engineering & Product | E31: ENG-L2 | F31: L2 | G31: Software Engineer II | H31: Bengaluru | I31: Hybrid | J31: 43587 | K31: Voluntary Exit | L31: 43723 | M31: Work-Life Balance | N31: Company Career Portal | O31: 1061000 | P31: 3 | Q31: Yes | R31: 20 | S31: MGR-102 | T31: =VALUE(MID(A31,5,5)) -> 11185 | U31: =LEFT(E31,3) -> ENG | V31: =RIGHT(E31,2) -> L2 | W31: =PROPER(TRIM(VLOOKUP(S31,Employee_Lookups!$I$4:$M$19,2,FALSE()))) -> Neha Kulkarni | X31: =VLOOKUP(C31,Employee_Lookups!$A$4:$G$9,4,FALSE()) -> CC-101 | Y31: =INDEX(Employee_Lookups!$C$13:$C$17,MATCH(F31,Employee_Lookups!$A$13:$A$17,0)) -> Band B (Mid) | Z31: =_xlfn.XLOOKUP(F31,Employee_Lookups!$A$13:$A$17,Employee_Lookups!$E$13:$E$17,0) -> 1100000 | AA31: =ROUND(O31/INDEX(Employee_Lookups!$E$13:$E$17,MATCH(F31,Employee_Lookups!$A$13:$A$17,0)),3) -> 0.965 | AB31: =YEAR(J31) -> 2019 | AC31: =IF(ISBLANK(L31),"",YEAR(L31)) -> 2019 | AD31: =ROUND((IF(ISBLANK(L31),Employee_Lookups!$O$14,L31)-J31)/365.25,2) -> 0.37 | AE31: =IF(AD31<1,"< 1 Yr (New)",IF(AD31<3,"1 - 3 Yrs",IF(AD31<5,"3 - 5 Yrs","5+ Yrs"))) -> < 1 Yr (New) | AF31: =IF(K31<>"Active","Exited",IF(AND(Q31="Yes",OR(P31>=4,AA31<0.95)),"High Risk",IF(OR(Q31="Yes",AND(NOT(ISBLANK(P31)),P31<=2)),"Moderate Risk","Low Risk"))) -> Exited
A32: EMP-11334 | B32: Kiara Patil | C32: DEP-FIN | D32: Finance & Strategy | E32: FIN-L2 | F32: L2 | G32: Senior FP&A Analyst | H32: Bengaluru | I32: Hybrid | J32: 43593 | K32: Active | M32: N/A - Active | N32: LinkedIn Sourcing | O32: 1200000 | P32: 3 | Q32: No | R32: 21 | S32: MGR-401 | T32: =VALUE(MID(A32,5,5)) -> 11334 | U32: =LEFT(E32,3) -> FIN | V32: =RIGHT(E32,2) -> L2 | W32: =PROPER(TRIM(VLOOKUP(S32,Employee_Lookups!$I$4:$M$19,2,FALSE()))) -> Rajeshwari Rao | X32: =VLOOKUP(C32,Employee_Lookups!$A$4:$G$9,4,FALSE()) -> CC-404 | Y32: =INDEX(Employee_Lookups!$C$13:$C$17,MATCH(F32,Employee_Lookups!$A$13:$A$17,0)) -> Band B (Mid) | Z32: =_xlfn.XLOOKUP(F32,Employee_Lookups!$A$13:$A$17,Employee_Lookups!$E$13:$E$17,0) -> 1100000 | AA32: =ROUND(O32/INDEX(Employee_Lookups!$E$13:$E$17,MATCH(F32,Employee_Lookups!$A$13:$A$17,0)),3) -> 1.091 | AB32: =YEAR(J32) -> 2019 | AC32: =IF(ISBLANK(L32),"",YEAR(L32)) | AD32: =ROUND((IF(ISBLANK(L32),Employee_Lookups!$O$14,L32)-J32)/365.25,2) -> 6.65 | AE32: =IF(AD32<1,"< 1 Yr (New)",IF(AD32<3,"1 - 3 Yrs",IF(AD32<5,"3 - 5 Yrs","5+ Yrs"))) -> 5+ Yrs | AF32: =IF(K32<>"Active","Exited",IF(AND(Q32="Yes",OR(P32>=4,AA32<0.95)),"High Risk",IF(OR(Q32="Yes",AND(NOT(ISBLANK(P32)),P32<=2)),"Moderate Risk","Low Risk"))) -> Low Risk
A33: EMP-10701 | B33: Aarav Iyer | C33: DEP-OPS | D33: Customer Operations | E33: OPS-L2 | F33: L2 | G33: Customer Success Specialist | H33: Bengaluru | I33: Hybrid | J33: 43594 | K33: Active | M33: N/A - Active | N33: External Agency | O33: 1004000 | P33: 4 | Q33: No | R33: 34 | S33: MGR-303 | T33: =VALUE(MID(A33,5,5)) -> 10701 | U33: =LEFT(E33,3) -> OPS | V33: =RIGHT(E33,2) -> L2 | W33: =PROPER(TRIM(VLOOKUP(S33,Employee_Lookups!$I$4:$M$19,2,FALSE()))) -> Meera Krishnan | X33: =VLOOKUP(C33,Employee_Lookups!$A$4:$G$9,4,FALSE()) -> CC-303 | Y33: =INDEX(Employee_Lookups!$C$13:$C$17,MATCH(F33,Employee_Lookups!$A$13:$A$17,0)) -> Band B (Mid) | Z33: =_xlfn.XLOOKUP(F33,Employee_Lookups!$A$13:$A$17,Employee_Lookups!$E$13:$E$17,0) -> 1100000 | AA33: =ROUND(O33/INDEX(Employee_Lookups!$E$13:$E$17,MATCH(F33,Employee_Lookups!$A$13:$A$17,0)),3) -> 0.913 | AB33: =YEAR(J33) -> 2019 | AC33: =IF(ISBLANK(L33),"",YEAR(L33)) | AD33: =ROUND((IF(ISBLANK(L33),Employee_Lookups!$O$14,L33)-J33)/365.25,2) -> 6.65 | AE33: =IF(AD33<1,"< 1 Yr (New)",IF(AD33<3,"1 - 3 Yrs",IF(AD33<5,"3 - 5 Yrs","5+ Yrs"))) -> 5+ Yrs | AF33: =IF(K33<>"Active","Exited",IF(AND(Q33="Yes",OR(P33>=4,AA33<0.95)),"High Risk",IF(OR(Q33="Yes",AND(NOT(ISBLANK(P33)),P33<=2)),"Moderate Risk","Low Risk"))) -> Low Risk
A34: EMP-10695 | B34: Krishna Joshi | C34: DEP-OPS | D34: Customer Operations | E34: OPS-L1 | F34: L1 | G34: Operations Coordinator | H34: Mumbai | I34: On-Site | J34: 43596 | K34: Active | M34: N/A - Active | N34: LinkedIn Sourcing | O34: 707000 | P34: 3 | Q34: Yes | R34: 47 | S34: MGR-303 | T34: =VALUE(MID(A34,5,5)) -> 10695 | U34: =LEFT(E34,3) -> OPS | V34: =RIGHT(E34,2) -> L1 | W34: =PROPER(TRIM(VLOOKUP(S34,Employee_Lookups!$I$4:$M$19,2,FALSE()))) -> Meera Krishnan | X34: =VLOOKUP(C34,Employee_Lookups!$A$4:$G$9,4,FALSE()) -> CC-303 | Y34: =INDEX(Employee_Lookups!$C$13:$C$17,MATCH(F34,Employee_Lookups!$A$13:$A$17,0)) -> Band A (Entry) | Z34: =_xlfn.XLOOKUP(F34,Employee_Lookups!$A$13:$A$17,Employee_Lookups!$E$13:$E$17,0) -> 700000 | AA34: =ROUND(O34/INDEX(Employee_Lookups!$E$13:$E$17,MATCH(F34,Employee_Lookups!$A$13:$A$17,0)),3) -> 1.01 | AB34: =YEAR(J34) -> 2019 | AC34: =IF(ISBLANK(L34),"",YEAR(L34)) | AD34: =ROUND((IF(ISBLANK(L34),Employee_Lookups!$O$14,L34)-J34)/365.25,2) -> 6.64 | AE34: =IF(AD34<1,"< 1 Yr (New)",IF(AD34<3,"1 - 3 Yrs",IF(AD34<5,"3 - 5 Yrs","5+ Yrs"))) -> 5+ Yrs | AF34: =IF(K34<>"Active","Exited",IF(AND(Q34="Yes",OR(P34>=4,AA34<0.95)),"High Risk",IF(OR(Q34="Yes",AND(NOT(ISBLANK(P34)),P34<=2)),"Moderate Risk","Low Risk"))) -> Moderate Risk
A35: EMP-10817 | B35: Omkar Sharma | C35: DEP-SAL | D35: Enterprise Sales | E35: SAL-L5 | F35: L5 | G35: VP of Sales | H35: Bengaluru | I35: Hybrid | J35: 43597 | K35: Voluntary Exit | L35: 43808 | M35: Compensation | N35: Employee Referral | O35: 4412000 | P35: 3 | Q35: Yes | R35: 72 | S35: MGR-202 | T35: =VALUE(MID(A35,5,5)) -> 10817 | U35: =LEFT(E35,3) -> SAL | V35: =RIGHT(E35,2) -> L5 | W35: =PROPER(TRIM(VLOOKUP(S35,Employee_Lookups!$I$4:$M$19,2,FALSE()))) -> Priya Sharma | X35: =VLOOKUP(C35,Employee_Lookups!$A$4:$G$9,4,FALSE()) -> CC-202 | Y35: =INDEX(Employee_Lookups!$C$13:$C$17,MATCH(F35,Employee_Lookups!$A$13:$A$17,0)) -> Band E (Executive) | Z35: =_xlfn.XLOOKUP(F35,Employee_Lookups!$A$13:$A$17,Employee_Lookups!$E$13:$E$17,0) -> 4300000 | AA35: =ROUND(O35/INDEX(Employee_Lookups!$E$13:$E$17,MATCH(F35,Employee_Lookups!$A$13:$A$17,0)),3) -> 1.026 | AB35: =YEAR(J35) -> 2019 | AC35: =IF(ISBLANK(L35),"",YEAR(L35)) -> 2019 | AD35: =ROUND((IF(ISBLANK(L35),Employee_Lookups!$O$14,L35)-J35)/365.25,2) -> 0.58 | AE35: =IF(AD35<1,"< 1 Yr (New)",IF(AD35<3,"1 - 3 Yrs",IF(AD35<5,"3 - 5 Yrs","5+ Yrs"))) -> < 1 Yr (New) | AF35: =IF(K35<>"Active","Exited",IF(AND(Q35="Yes",OR(P35>=4,AA35<0.95)),"High Risk",IF(OR(Q35="Yes",AND(NOT(ISBLANK(P35)),P35<=2)),"Moderate Risk","Low Risk"))) -> Exited
A36: EMP-10124 | B36: Aadhya Reddy | C36: DEP-OPS | D36: Customer Operations | E36: OPS-L2 | F36: L2 | G36: Customer Success Specialist | H36: Hyderabad | I36: On-Site | J36: 43600 | K36: Active | M36: N/A - Active | N36: Employee Referral | O36: 855000 | P36: 2 | Q36: Yes | R36: 10 | S36: MGR-303 | T36: =VALUE(MID(A36,5,5)) -> 10124 | U36: =LEFT(E36,3) -> OPS | V36: =RIGHT(E36,2) -> L2 | W36: =PROPER(TRIM(VLOOKUP(S36,Employee_Lookups!$I$4:$M$19,2,FALSE()))) -> Meera Krishnan | X36: =VLOOKUP(C36,Employee_Lookups!$A$4:$G$9,4,FALSE()) -> CC-303 | Y36: =INDEX(Employee_Lookups!$C$13:$C$17,MATCH(F36,Employee_Lookups!$A$13:$A$17,0)) -> Band B (Mid) | Z36: =_xlfn.XLOOKUP(F36,Employee_Lookups!$A$13:$A$17,Employee_Lookups!$E$13:$E$17,0) -> 1100000 | AA36: =ROUND(O36/INDEX(Employee_Lookups!$E$13:$E$17,MATCH(F36,Employee_Lookups!$A$13:$A$17,0)),3) -> 0.777 | AB36: =YEAR(J36) -> 2019 | AC36: =IF(ISBLANK(L36),"",YEAR(L36)) | AD36: =ROUND((IF(ISBLANK(L36),Employee_Lookups!$O$14,L36)-J36)/365.25,2) -> 6.63 | AE36: =IF(AD36<1,"< 1 Yr (New)",IF(AD36<3,"1 - 3 Yrs",IF(AD36<5,"3 - 5 Yrs","5+ Yrs"))) -> 5+ Yrs | AF36: =IF(K36<>"Active","Exited",IF(AND(Q36="Yes",OR(P36>=4,AA36<0.95)),"High Risk",IF(OR(Q36="Yes",AND(NOT(ISBLANK(P36)),P36<=2)),"Moderate Risk","Low Risk"))) -> High Risk
A37: EMP-10654 | B37: Kiara Nair | C37: DEP-FIN | D37: Finance & Strategy | E37: FIN-L3 | F37: L3 | G37: Finance Manager | H37: Hyderabad | I37: On-Site | J37: 43610 | K37: Active | M37: N/A - Active | N37: LinkedIn Sourcing | O37: 1864000 | P37: 3 | Q37: No | R37: 42 | S37: MGR-401 | T37: =VALUE(MID(A37,5,5)) -> 10654 | U37: =LEFT(E37,3) -> FIN | V37: =RIGHT(E37,2) -> L3 | W37: =PROPER(TRIM(VLOOKUP(S37,Employee_Lookups!$I$4:$M$19,2,FALSE()))) -> Rajeshwari Rao | X37: =VLOOKUP(C37,Employee_Lookups!$A$4:$G$9,4,FALSE()) -> CC-404 | Y37: =INDEX(Employee_Lookups!$C$13:$C$17,MATCH(F37,Employee_Lookups!$A$13:$A$17,0)) -> Band C (Senior) | Z37: =_xlfn.XLOOKUP(F37,Employee_Lookups!$A$13:$A$17,Employee_Lookups!$E$13:$E$17,0) -> 1725000 | AA37: =ROUND(O37/INDEX(Employee_Lookups!$E$13:$E$17,MATCH(F37,Employee_Lookups!$A$13:$A$17,0)),3) -> 1.081 | AB37: =YEAR(J37) -> 2019 | AC37: =IF(ISBLANK(L37),"",YEAR(L37)) | AD37: =ROUND((IF(ISBLANK(L37),Employee_Lookups!$O$14,L37)-J37)/365.25,2) -> 6.6 | AE37: =IF(AD37<1,"< 1 Yr (New)",IF(AD37<3,"1 - 3 Yrs",IF(AD37<5,"3 - 5 Yrs","5+ Yrs"))) -> 5+ Yrs | AF37: =IF(K37<>"Active","Exited",IF(AND(Q37="Yes",OR(P37>=4,AA37<0.95)),"High Risk",IF(OR(Q37="Yes",AND(NOT(ISBLANK(P37)),P37<=2)),"Moderate Risk","Low Risk"))) -> Low Risk
A38: EMP-11437 | B38: Aadhya Rao | C38: DEP-HR | D38: People & Talent | E38: -HR-L2 | F38: L2 | G38: Talent Acquisition Partner | H38: Mumbai | I38: On-Site | J38: 43618 | K38: Active | M38: N/A - Active | N38: Company Career Portal | O38: 1299000 | P38: 3 | Q38: No | R38: 53 | S38: MGR-502 | T38: =VALUE(MID(A38,5,5)) -> 11437 | U38: =LEFT(E38,3) -> -HR | V38: =RIGHT(E38,2) -> L2 | W38: =PROPER(TRIM(VLOOKUP(S38,Employee_Lookups!$I$4:$M$19,2,FALSE()))) -> Nikhil Chatterjee | X38: =VLOOKUP(C38,Employee_Lookups!$A$4:$G$9,4,FALSE()) -> CC-505 | Y38: =INDEX(Employee_Lookups!$C$13:$C$17,MATCH(F38,Employee_Lookups!$A$13:$A$17,0)) -> Band B (Mid) | Z38: =_xlfn.XLOOKUP(F38,Employee_Lookups!$A$13:$A$17,Employee_Lookups!$E$13:$E$17,0) -> 1100000 | AA38: =ROUND(O38/INDEX(Employee_Lookups!$E$13:$E$17,MATCH(F38,Employee_Lookups!$A$13:$A$17,0)),3) -> 1.181 | AB38: =YEAR(J38) -> 2019 | AC38: =IF(ISBLANK(L38),"",YEAR(L38)) | AD38: =ROUND((IF(ISBLANK(L38),Employee_Lookups!$O$14,L38)-J38)/365.25,2) -> 6.58 | AE38: =IF(AD38<1,"< 1 Yr (New)",IF(AD38<3,"1 - 3 Yrs",IF(AD38<5,"3 - 5 Yrs","5+ Yrs"))) -> 5+ Yrs | AF38: =IF(K38<>"Active","Exited",IF(AND(Q38="Yes",OR(P38>=4,AA38<0.95)),"High Risk",IF(OR(Q38="Yes",AND(NOT(ISBLANK(P38)),P38<=2)),"Moderate Risk","Low Risk"))) -> Low Risk
A39: EMP-10692 | B39: Omkar Shah | C39: DEP-SAL | D39: Enterprise Sales | E39: SAL-L2 | F39: L2 | G39: Account Executive | H39: Pune | I39: Hybrid | J39: 43619 | K39: Voluntary Exit | L39: 46003 | M39: Work-Life Balance | N39: LinkedIn Sourcing | O39: 1058000 | P39: 4 | Q39: Yes | R39: 48 | S39: MGR-202 | T39: =VALUE(MID(A39,5,5)) -> 10692 | U39: =LEFT(E39,3) -> SAL | V39: =RIGHT(E39,2) -> L2 | W39: =PROPER(TRIM(VLOOKUP(S39,Employee_Lookups!$I$4:$M$19,2,FALSE()))) -> Priya Sharma | X39: =VLOOKUP(C39,Employee_Lookups!$A$4:$G$9,4,FALSE()) -> CC-202 | Y39: =INDEX(Employee_Lookups!$C$13:$C$17,MATCH(F39,Employee_Lookups!$A$13:$A$17,0)) -> Band B (Mid) | Z39: =_xlfn.XLOOKUP(F39,Employee_Lookups!$A$13:$A$17,Employee_Lookups!$E$13:$E$17,0) -> 1100000 | AA39: =ROUND(O39/INDEX(Employee_Lookups!$E$13:$E$17,MATCH(F39,Employee_Lookups!$A$13:$A$17,0)),3) -> 0.962 | AB39: =YEAR(J39) -> 2019 | AC39: =IF(ISBLANK(L39),"",YEAR(L39)) -> 2025 | AD39: =ROUND((IF(ISBLANK(L39),Employee_Lookups!$O$14,L39)-J39)/365.25,2) -> 6.53 | AE39: =IF(AD39<1,"< 1 Yr (New)",IF(AD39<3,"1 - 3 Yrs",IF(AD39<5,"3 - 5 Yrs","5+ Yrs"))) -> 5+ Yrs | AF39: =IF(K39<>"Active","Exited",IF(AND(Q39="Yes",OR(P39>=4,AA39<0.95)),"High Risk",IF(OR(Q39="Yes",AND(NOT(ISBLANK(P39)),P39<=2)),"Moderate Risk","Low Risk"))) -> Exited
A40: EMP-10274 | B40: Aadhya Nair | C40: DEP-SAL | D40: Enterprise Sales | E40: SAL-L5 | F40: L5 | G40: VP of Sales | H40: Hyderabad | I40: On-Site | J40: 43621 | K40: Active | M40: N/A - Active | N40: Employee Referral | O40: 5087000 | P40: 3 | Q40: Yes | R40: 42 | S40: MGR-202 | T40: =VALUE(MID(A40,5,5)) -> 10274 | U40: =LEFT(E40,3) -> SAL | V40: =RIGHT(E40,2) -> L5 | W40: =PROPER(TRIM(VLOOKUP(S40,Employee_Lookups!$I$4:$M$19,2,FALSE()))) -> Priya Sharma | X40: =VLOOKUP(C40,Employee_Lookups!$A$4:$G$9,4,FALSE()) -> CC-202 | Y40: =INDEX(Employee_Lookups!$C$13:$C$17,MATCH(F40,Employee_Lookups!$A$13:$A$17,0)) -> Band E (Executive) | Z40: =_xlfn.XLOOKUP(F40,Employee_Lookups!$A$13:$A$17,Employee_Lookups!$E$13:$E$17,0) -> 4300000 | AA40: =ROUND(O40/INDEX(Employee_Lookups!$E$13:$E$17,MATCH(F40,Employee_Lookups!$A$13:$A$17,0)),3) -> 1.183 | AB40: =YEAR(J40) -> 2019 | AC40: =IF(ISBLANK(L40),"",YEAR(L40)) | AD40: =ROUND((IF(ISBLANK(L40),Employee_Lookups!$O$14,L40)-J40)/365.25,2) -> 6.57 | AE40: =IF(AD40<1,"< 1 Yr (New)",IF(AD40<3,"1 - 3 Yrs",IF(AD40<5,"3 - 5 Yrs","5+ Yrs"))) -> 5+ Yrs | AF40: =IF(K40<>"Active","Exited",IF(AND(Q40="Yes",OR(P40>=4,AA40<0.95)),"High Risk",IF(OR(Q40="Yes",AND(NOT(ISBLANK(P40)),P40<=2)),"Moderate Risk","Low Risk"))) -> Moderate Risk
A41: EMP-10808 | B41: Vihaan Patil | C41: DEP-SAL | D41: Enterprise Sales | E41: SAL-L2 | F41: L2 | G41: Account Executive | H41: Bengaluru | I41: Hybrid | J41: 43631 | K41: Voluntary Exit | L41: 45853 | M41: Career Growth | N41: External Agency | O41: 1113000 | P41: 4 | Q41: Yes | R41: 31 | S41: MGR-202 | T41: =VALUE(MID(A41,5,5)) -> 10808 | U41: =LEFT(E41,3) -> SAL | V41: =RIGHT(E41,2) -> L2 | W41: =PROPER(TRIM(VLOOKUP(S41,Employee_Lookups!$I$4:$M$19,2,FALSE()))) -> Priya Sharma | X41: =VLOOKUP(C41,Employee_Lookups!$A$4:$G$9,4,FALSE()) -> CC-202 | Y41: =INDEX(Employee_Lookups!$C$13:$C$17,MATCH(F41,Employee_Lookups!$A$13:$A$17,0)) -> Band B (Mid) | Z41: =_xlfn.XLOOKUP(F41,Employee_Lookups!$A$13:$A$17,Employee_Lookups!$E$13:$E$17,0) -> 1100000 | AA41: =ROUND(O41/INDEX(Employee_Lookups!$E$13:$E$17,MATCH(F41,Employee_Lookups!$A$13:$A$17,0)),3) -> 1.012 | AB41: =YEAR(J41) -> 2019 | AC41: =IF(ISBLANK(L41),"",YEAR(L41)) -> 2025 | AD41: =ROUND((IF(ISBLANK(L41),Employee_Lookups!$O$14,L41)-J41)/365.25,2) -> 6.08 | AE41: =IF(AD41<1,"< 1 Yr (New)",IF(AD41<3,"1 - 3 Yrs",IF(AD41<5,"3 - 5 Yrs","5+ Yrs"))) -> 5+ Yrs | AF41: =IF(K41<>"Active","Exited",IF(AND(Q41="Yes",OR(P41>=4,AA41<0.95)),"High Risk",IF(OR(Q41="Yes",AND(NOT(ISBLANK(P41)),P41<=2)),"Moderate Risk","Low Risk"))) -> Exited
A42: EMP-10263 | B42: Riya Joshi | C42: DEP-FIN | D42: Finance & Strategy | E42: FIN-L2 | F42: L2 | G42: Senior FP&A Analyst | H42: Remote-India | I42: Remote | J42: 43636 | K42: Active | M42: N/A - Active | N42: Employee Referral | O42: 1329000 | P42: 3 | Q42: Yes | R42: 25 | S42: MGR-402 | T42: =VALUE(MID(A42,5,5)) -> 10263 | U42: =LEFT(E42,3) -> FIN | V42: =RIGHT(E42,2) -> L2 | W42: =PROPER(TRIM(VLOOKUP(S42,Employee_Lookups!$I$4:$M$19,2,FALSE()))) -> Aditya Gokhale | X42: =VLOOKUP(C42,Employee_Lookups!$A$4:$G$9,4,FALSE()) -> CC-404 | Y42: =INDEX(Employee_Lookups!$C$13:$C$17,MATCH(F42,Employee_Lookups!$A$13:$A$17,0)) -> Band B (Mid) | Z42: =_xlfn.XLOOKUP(F42,Employee_Lookups!$A$13:$A$17,Employee_Lookups!$E$13:$E$17,0) -> 1100000 | AA42: =ROUND(O42/INDEX(Employee_Lookups!$E$13:$E$17,MATCH(F42,Employee_Lookups!$A$13:$A$17,0)),3) -> 1.208 | AB42: =YEAR(J42) -> 2019 | AC42: =IF(ISBLANK(L42),"",YEAR(L42)) | AD42: =ROUND((IF(ISBLANK(L42),Employee_Lookups!$O$14,L42)-J42)/365.25,2) -> 6.53 | AE42: =IF(AD42<1,"< 1 Yr (New)",IF(AD42<3,"1 - 3 Yrs",IF(AD42<5,"3 - 5 Yrs","5+ Yrs"))) -> 5+ Yrs | AF42: =IF(K42<>"Active","Exited",IF(AND(Q42="Yes",OR(P42>=4,AA42<0.95)),"High Risk",IF(OR(Q42="Yes",AND(NOT(ISBLANK(P42)),P42<=2)),"Moderate Risk","Low Risk"))) -> Moderate Risk
A43: EMP-10115 | B43: Aadhya Kapoor | C43: DEP-ENG | D43: Engineering & Product | E43: ENG-L1 | F43: L1 | G43: Software Engineer I | H43: Hyderabad | I43: On-Site | J43: 43640 | K43: Active | M43: N/A - Active | N43: Campus Recruitment | O43: 824000 | P43: 3 | Q43: No | R43: 44 | S43: MGR-101 | T43: =VALUE(MID(A43,5,5)) -> 10115 | U43: =LEFT(E43,3) -> ENG | V43: =RIGHT(E43,2) -> L1 | W43: =PROPER(TRIM(VLOOKUP(S43,Employee_Lookups!$I$4:$M$19,2,FALSE()))) -> Aarav Deshmukh | X43: =VLOOKUP(C43,Employee_Lookups!$A$4:$G$9,4,FALSE()) -> CC-101 | Y43: =INDEX(Employee_Lookups!$C$13:$C$17,MATCH(F43,Employee_Lookups!$A$13:$A$17,0)) -> Band A (Entry) | Z43: =_xlfn.XLOOKUP(F43,Employee_Lookups!$A$13:$A$17,Employee_Lookups!$E$13:$E$17,0) -> 700000 | AA43: =ROUND(O43/INDEX(Employee_Lookups!$E$13:$E$17,MATCH(F43,Employee_Lookups!$A$13:$A$17,0)),3) -> 1.177 | AB43: =YEAR(J43) -> 2019 | AC43: =IF(ISBLANK(L43),"",YEAR(L43)) | AD43: =ROUND((IF(ISBLANK(L43),Employee_Lookups!$O$14,L43)-J43)/365.25,2) -> 6.52 | AE43: =IF(AD43<1,"< 1 Yr (New)",IF(AD43<3,"1 - 3 Yrs",IF(AD43<5,"3 - 5 Yrs","5+ Yrs"))) -> 5+ Yrs | AF43: =IF(K43<>"Active","Exited",IF(AND(Q43="Yes",OR(P43>=4,AA43<0.95)),"High Risk",IF(OR(Q43="Yes",AND(NOT(ISBLANK(P43)),P43<=2)),"Moderate Risk","Low Risk"))) -> Low Risk
A44: EMP-10235 | B44: Krishna Joshi | C44: DEP-ENG | D44: Engineering & Product | E44: ENG-L2 | F44: L2 | G44: Software Engineer II | H44: Pune | I44: Hybrid | J44: 43642 | K44: Involuntary Exit | L44: 43985 | M44: Performance / Restructuring | N44: External Agency | O44: 1129000 | P44: 2 | Q44: No | R44: 17 | S44: MGR-104 | T44: =VALUE(MID(A44,5,5)) -> 10235 | U44: =LEFT(E44,3) -> ENG | V44: =RIGHT(E44,2) -> L2 | W44: =PROPER(TRIM(VLOOKUP(S44,Employee_Lookups!$I$4:$M$19,2,FALSE()))) -> Siddharth Nair | X44: =VLOOKUP(C44,Employee_Lookups!$A$4:$G$9,4,FALSE()) -> CC-101 | Y44: =INDEX(Employee_Lookups!$C$13:$C$17,MATCH(F44,Employee_Lookups!$A$13:$A$17,0)) -> Band B (Mid) | Z44: =_xlfn.XLOOKUP(F44,Employee_Lookups!$A$13:$A$17,Employee_Lookups!$E$13:$E$17,0) -> 1100000 | AA44: =ROUND(O44/INDEX(Employee_Lookups!$E$13:$E$17,MATCH(F44,Employee_Lookups!$A$13:$A$17,0)),3) -> 1.026 | AB44: =YEAR(J44) -> 2019 | AC44: =IF(ISBLANK(L44),"",YEAR(L44)) -> 2020 | AD44: =ROUND((IF(ISBLANK(L44),Employee_Lookups!$O$14,L44)-J44)/365.25,2) -> 0.94 | AE44: =IF(AD44<1,"< 1 Yr (New)",IF(AD44<3,"1 - 3 Yrs",IF(AD44<5,"3 - 5 Yrs","5+ Yrs"))) -> < 1 Yr (New) | AF44: =IF(K44<>"Active","Exited",IF(AND(Q44="Yes",OR(P44>=4,AA44<0.95)),"High Risk",IF(OR(Q44="Yes",AND(NOT(ISBLANK(P44)),P44<=2)),"Moderate Risk","Low Risk"))) -> Exited
A45: EMP-11318 | B45: Sai Iyer | C45: DEP-OPS | D45: Customer Operations | E45: OPS-L3 | F45: L3 | G45: Operations Lead | H45: Hyderabad | I45: On-Site | J45: 43643 | K45: Active | M45: N/A - Active | N45: Company Career Portal | O45: 2092000 | P45: 1 | Q45: No | R45: 18 | S45: MGR-303 | T45: =VALUE(MID(A45,5,5)) -> 11318 | U45: =LEFT(E45,3) -> OPS | V45: =RIGHT(E45,2) -> L3 | W45: =PROPER(TRIM(VLOOKUP(S45,Employee_Lookups!$I$4:$M$19,2,FALSE()))) -> Meera Krishnan | X45: =VLOOKUP(C45,Employee_Lookups!$A$4:$G$9,4,FALSE()) -> CC-303 | Y45: =INDEX(Employee_Lookups!$C$13:$C$17,MATCH(F45,Employee_Lookups!$A$13:$A$17,0)) -> Band C (Senior) | Z45: =_xlfn.XLOOKUP(F45,Employee_Lookups!$A$13:$A$17,Employee_Lookups!$E$13:$E$17,0) -> 1725000 | AA45: =ROUND(O45/INDEX(Employee_Lookups!$E$13:$E$17,MATCH(F45,Employee_Lookups!$A$13:$A$17,0)),3) -> 1.213 | AB45: =YEAR(J45) -> 2019 | AC45: =IF(ISBLANK(L45),"",YEAR(L45)) | AD45: =ROUND((IF(ISBLANK(L45),Employee_Lookups!$O$14,L45)-J45)/365.25,2) -> 6.51 | AE45: =IF(AD45<1,"< 1 Yr (New)",IF(AD45<3,"1 - 3 Yrs",IF(AD45<5,"3 - 5 Yrs","5+ Yrs"))) -> 5+ Yrs | AF45: =IF(K45<>"Active","Exited",IF(AND(Q45="Yes",OR(P45>=4,AA45<0.95)),"High Risk",IF(OR(Q45="Yes",AND(NOT(ISBLANK(P45)),P45<=2)),"Moderate Risk","Low Risk"))) -> Moderate Risk
A46: EMP-10354 | B46: Saanvi Chatterjee | C46: DEP-ENG | D46: Engineering & Product | E46: ENG-L3 | F46: L3 | G46: Engineering Manager | H46: Bengaluru | I46: Hybrid | J46: 43643 | K46: Involuntary Exit | L46: 45090 | M46: Performance / Restructuring | N46: LinkedIn Sourcing | O46: 1760000 | P46: 2 | Q46: No | R46: 0 | S46: MGR-103 | T46: =VALUE(MID(A46,5,5)) -> 10354 | U46: =LEFT(E46,3) -> ENG | V46: =RIGHT(E46,2) -> L3 | W46: =PROPER(TRIM(VLOOKUP(S46,Employee_Lookups!$I$4:$M$19,2,FALSE()))) -> Rohan Verma | X46: =VLOOKUP(C46,Employee_Lookups!$A$4:$G$9,4,FALSE()) -> CC-101 | Y46: =INDEX(Employee_Lookups!$C$13:$C$17,MATCH(F46,Employee_Lookups!$A$13:$A$17,0)) -> Band C (Senior) | Z46: =_xlfn.XLOOKUP(F46,Employee_Lookups!$A$13:$A$17,Employee_Lookups!$E$13:$E$17,0) -> 1725000 | AA46: =ROUND(O46/INDEX(Employee_Lookups!$E$13:$E$17,MATCH(F46,Employee_Lookups!$A$13:$A$17,0)),3) -> 1.02 | AB46: =YEAR(J46) -> 2019 | AC46: =IF(ISBLANK(L46),"",YEAR(L46)) -> 2023 | AD46: =ROUND((IF(ISBLANK(L46),Employee_Lookups!$O$14,L46)-J46)/365.25,2) -> 3.96 | AE46: =IF(AD46<1,"< 1 Yr (New)",IF(AD46<3,"1 - 3 Yrs",IF(AD46<5,"3 - 5 Yrs","5+ Yrs"))) -> 3 - 5 Yrs | AF46: =IF(K46<>"Active","Exited",IF(AND(Q46="Yes",OR(P46>=4,AA46<0.95)),"High Risk",IF(OR(Q46="Yes",AND(NOT(ISBLANK(P46)),P46<=2)),"Moderate Risk","Low Risk"))) -> Exited
A47: EMP-10750 | B47: Ishaan Chatterjee | C47: DEP-OPS | D47: Customer Operations | E47: OPS-L3 | F47: L3 | G47: Operations Lead | H47: Hyderabad | I47: On-Site | J47: 43654 | K47: Voluntary Exit | L47: 45107 | M47: Relocation | N47: Company Career Portal | O47: 1894000 | P47: 4 | Q47: No | R47: 51 | S47: MGR-302 | T47: =VALUE(MID(A47,5,5)) -> 10750 | U47: =LEFT(E47,3) -> OPS | V47: =RIGHT(E47,2) -> L3 | W47: =PROPER(TRIM(VLOOKUP(S47,Employee_Lookups!$I$4:$M$19,2,FALSE()))) -> Deepak Patil | X47: =VLOOKUP(C47,Employee_Lookups!$A$4:$G$9,4,FALSE()) -> CC-303 | Y47: =INDEX(Employee_Lookups!$C$13:$C$17,MATCH(F47,Employee_Lookups!$A$13:$A$17,0)) -> Band C (Senior) | Z47: =_xlfn.XLOOKUP(F47,Employee_Lookups!$A$13:$A$17,Employee_Lookups!$E$13:$E$17,0) -> 1725000 | AA47: =ROUND(O47/INDEX(Employee_Lookups!$E$13:$E$17,MATCH(F47,Employee_Lookups!$A$13:$A$17,0)),3) -> 1.098 | AB47: =YEAR(J47) -> 2019 | AC47: =IF(ISBLANK(L47),"",YEAR(L47)) -> 2023 | AD47: =ROUND((IF(ISBLANK(L47),Employee_Lookups!$O$14,L47)-J47)/365.25,2) -> 3.98 | AE47: =IF(AD47<1,"< 1 Yr (New)",IF(AD47<3,"1 - 3 Yrs",IF(AD47<5,"3 - 5 Yrs","5+ Yrs"))) -> 3 - 5 Yrs | AF47: =IF(K47<>"Active","Exited",IF(AND(Q47="Yes",OR(P47>=4,AA47<0.95)),"High Risk",IF(OR(Q47="Yes",AND(NOT(ISBLANK(P47)),P47<=2)),"Moderate Risk","Low Risk"))) -> Exited
A48: EMP-10401 | B48: Vikram Mehta | C48: DEP-ENG | D48: Engineering & Product | E48: ENG-L1 | F48: L1 | G48: Software Engineer I | H48: Pune | I48: Hybrid | J48: 43655 | K48: Voluntary Exit | L48: 44845 | M48: Work-Life Balance | N48: Company Career Portal | O48: 646000 | P48: 3 | Q48: Yes | R48: 33 | S48: MGR-103 | T48: =VALUE(MID(A48,5,5)) -> 10401 | U48: =LEFT(E48,3) -> ENG | V48: =RIGHT(E48,2) -> L1 | W48: =PROPER(TRIM(VLOOKUP(S48,Employee_Lookups!$I$4:$M$19,2,FALSE()))) -> Rohan Verma | X48: =VLOOKUP(C48,Employee_Lookups!$A$4:$G$9,4,FALSE()) -> CC-101 | Y48: =INDEX(Employee_Lookups!$C$13:$C$17,MATCH(F48,Employee_Lookups!$A$13:$A$17,0)) -> Band A (Entry) | Z48: =_xlfn.XLOOKUP(F48,Employee_Lookups!$A$13:$A$17,Employee_Lookups!$E$13:$E$17,0) -> 700000 | AA48: =ROUND(O48/INDEX(Employee_Lookups!$E$13:$E$17,MATCH(F48,Employee_Lookups!$A$13:$A$17,0)),3) -> 0.923 | AB48: =YEAR(J48) -> 2019 | AC48: =IF(ISBLANK(L48),"",YEAR(L48)) -> 2022 | AD48: =ROUND((IF(ISBLANK(L48),Employee_Lookups!$O$14,L48)-J48)/365.25,2) -> 3.26 | AE48: =IF(AD48<1,"< 1 Yr (New)",IF(AD48<3,"1 - 3 Yrs",IF(AD48<5,"3 - 5 Yrs","5+ Yrs"))) -> 3 - 5 Yrs | AF48: =IF(K48<>"Active","Exited",IF(AND(Q48="Yes",OR(P48>=4,AA48<0.95)),"High Risk",IF(OR(Q48="Yes",AND(NOT(ISBLANK(P48)),P48<=2)),"Moderate Risk","Low Risk"))) -> Exited
A49: EMP-11022 | B49: Swati Kulkarni | C49: DEP-MKT | D49: Growth Marketing | E49: MKT-L2 | F49: L2 | G49: Growth Specialist | H49: Pune | I49: Hybrid | J49: 43659 | K49: Involuntary Exit | L49: 43742 | M49: Performance / Restructuring | N49: Employee Referral | O49: 1226000 | P49: 4 | Q49: Yes | R49: 25 | S49: MGR-602 | T49: =VALUE(MID(A49,5,5)) -> 11022 | U49: =LEFT(E49,3) -> MKT | V49: =RIGHT(E49,2) -> L2 | W49: =PROPER(TRIM(VLOOKUP(S49,Employee_Lookups!$I$4:$M$19,2,FALSE()))) -> Arjun Sengupta | X49: =VLOOKUP(C49,Employee_Lookups!$A$4:$G$9,4,FALSE()) -> CC-606 | Y49: =INDEX(Employee_Lookups!$C$13:$C$17,MATCH(F49,Employee_Lookups!$A$13:$A$17,0)) -> Band B (Mid) | Z49: =_xlfn.XLOOKUP(F49,Employee_Lookups!$A$13:$A$17,Employee_Lookups!$E$13:$E$17,0) -> 1100000 | AA49: =ROUND(O49/INDEX(Employee_Lookups!$E$13:$E$17,MATCH(F49,Employee_Lookups!$A$13:$A$17,0)),3) -> 1.115 | AB49: =YEAR(J49) -> 2019 | AC49: =IF(ISBLANK(L49),"",YEAR(L49)) -> 2019 | AD49: =ROUND((IF(ISBLANK(L49),Employee_Lookups!$O$14,L49)-J49)/365.25,2) -> 0.23 | AE49: =IF(AD49<1,"< 1 Yr (New)",IF(AD49<3,"1 - 3 Yrs",IF(AD49<5,"3 - 5 Yrs","5+ Yrs"))) -> < 1 Yr (New) | AF49: =IF(K49<>"Active","Exited",IF(AND(Q49="Yes",OR(P49>=4,AA49<0.95)),"High Risk",IF(OR(Q49="Yes",AND(NOT(ISBLANK(P49)),P49<=2)),"Moderate Risk","Low Risk"))) -> Exited
A50: EMP-11193 | B50: Sai Kulkarni | C50: DEP-OPS | D50: Customer Operations | E50: OPS-L1 | F50: L1 | G50: Operations Coordinator | H50: Bengaluru | I50: Hybrid | J50: 43663 | K50: Voluntary Exit | L50: 43943 | M50: Relocation | N50: Employee Referral | O50: 740000 | P50: 3 | Q50: Yes | R50: 20 | S50: MGR-302 | T50: =VALUE(MID(A50,5,5)) -> 11193 | U50: =LEFT(E50,3) -> OPS | V50: =RIGHT(E50,2) -> L1 | W50: =PROPER(TRIM(VLOOKUP(S50,Employee_Lookups!$I$4:$M$19,2,FALSE()))) -> Deepak Patil | X50: =VLOOKUP(C50,Employee_Lookups!$A$4:$G$9,4,FALSE()) -> CC-303 | Y50: =INDEX(Employee_Lookups!$C$13:$C$17,MATCH(F50,Employee_Lookups!$A$13:$A$17,0)) -> Band A (Entry) | Z50: =_xlfn.XLOOKUP(F50,Employee_Lookups!$A$13:$A$17,Employee_Lookups!$E$13:$E$17,0) -> 700000 | AA50: =ROUND(O50/INDEX(Employee_Lookups!$E$13:$E$17,MATCH(F50,Employee_Lookups!$A$13:$A$17,0)),3) -> 1.057 | AB50: =YEAR(J50) -> 2019 | AC50: =IF(ISBLANK(L50),"",YEAR(L50)) -> 2020 | AD50: =ROUND((IF(ISBLANK(L50),Employee_Lookups!$O$14,L50)-J50)/365.25,2) -> 0.77 | AE50: =IF(AD50<1,"< 1 Yr (New)",IF(AD50<3,"1 - 3 Yrs",IF(AD50<5,"3 - 5 Yrs","5+ Yrs"))) -> < 1 Yr (New) | AF50: =IF(K50<>"Active","Exited",IF(AND(Q50="Yes",OR(P50>=4,AA50<0.95)),"High Risk",IF(OR(Q50="Yes",AND(NOT(ISBLANK(P50)),P50<=2)),"Moderate Risk","Low Risk"))) -> Exited
A51: EMP-10397 | B51: Kavya Chatterjee | C51: DEP-HR | D51: People & Talent | E51: -HR-L4 | F51: L4 | G51: Director of People | H51: Bengaluru | I51: Hybrid | J51: 43668 | K51: Active | M51: N/A - Active | N51: Campus Recruitment | O51: 2560000 | P51: 3 | Q51: No | R51: 23 | S51: MGR-501 | T51: =VALUE(MID(A51,5,5)) -> 10397 | U51: =LEFT(E51,3) -> -HR | V51: =RIGHT(E51,2) -> L4 | W51: =PROPER(TRIM(VLOOKUP(S51,Employee_Lookups!$I$4:$M$19,2,FALSE()))) -> Kavita Menon | X51: =VLOOKUP(C51,Employee_Lookups!$A$4:$G$9,4,FALSE()) -> CC-505 | Y51: =INDEX(Employee_Lookups!$C$13:$C$17,MATCH(F51,Employee_Lookups!$A$13:$A$17,0)) -> Band D (Leadership) | Z51: =_xlfn.XLOOKUP(F51,Employee_Lookups!$A$13:$A$17,Employee_Lookups!$E$13:$E$17,0) -> 2750000 | AA51: =ROUND(O51/INDEX(Employee_Lookups!$E$13:$E$17,MATCH(F51,Employee_Lookups!$A$13:$A$17,0)),3) -> 0.931 | AB51: =YEAR(J51) -> 2019 | AC51: =IF(ISBLANK(L51),"",YEAR(L51)) | AD51: =ROUND((IF(ISBLANK(L51),Employee_Lookups!$O$14,L51)-J51)/365.25,2) -> 6.44 | AE51: =IF(AD51<1,"< 1 Yr (New)",IF(AD51<3,"1 - 3 Yrs",IF(AD51<5,"3 - 5 Yrs","5+ Yrs"))) -> 5+ Yrs | AF51: =IF(K51<>"Active","Exited",IF(AND(Q51="Yes",OR(P51>=4,AA51<0.95)),"High Risk",IF(OR(Q51="Yes",AND(NOT(ISBLANK(P51)),P51<=2)),"Moderate Risk","Low Risk"))) -> Low Risk
A52: EMP-10901 | B52: Krishna Shah | C52: DEP-SAL | D52: Enterprise Sales | E52: SAL-L1 | F52: L1 | G52: Sales Development Rep | H52: Bengaluru | I52: Hybrid | J52: 43672 | K52: Active | M52: N/A - Active | N52: External Agency | O52: 685000 | P52: 1 | Q52: No | R52: 20 | S52: MGR-203 | T52: =VALUE(MID(A52,5,5)) -> 10901 | U52: =LEFT(E52,3) -> SAL | V52: =RIGHT(E52,2) -> L1 | W52: =PROPER(TRIM(VLOOKUP(S52,Employee_Lookups!$I$4:$M$19,2,FALSE()))) -> Karan Malhotra | X52: =VLOOKUP(C52,Employee_Lookups!$A$4:$G$9,4,FALSE()) -> CC-202 | Y52: =INDEX(Employee_Lookups!$C$13:$C$17,MATCH(F52,Employee_Lookups!$A$13:$A$17,0)) -> Band A (Entry) | Z52: =_xlfn.XLOOKUP(F52,Employee_Lookups!$A$13:$A$17,Employee_Lookups!$E$13:$E$17,0) -> 700000 | AA52: =ROUND(O52/INDEX(Employee_Lookups!$E$13:$E$17,MATCH(F52,Employee_Lookups!$A$13:$A$17,0)),3) -> 0.979 | AB52: =YEAR(J52) -> 2019 | AC52: =IF(ISBLANK(L52),"",YEAR(L52)) | AD52: =ROUND((IF(ISBLANK(L52),Employee_Lookups!$O$14,L52)-J52)/365.25,2) -> 6.43 | AE52: =IF(AD52<1,"< 1 Yr (New)",IF(AD52<3,"1 - 3 Yrs",IF(AD52<5,"3 - 5 Yrs","5+ Yrs"))) -> 5+ Yrs | AF52: =IF(K52<>"Active","Exited",IF(AND(Q52="Yes",OR(P52>=4,AA52<0.95)),"High Risk",IF(OR(Q52="Yes",AND(NOT(ISBLANK(P52)),P52<=2)),"Moderate Risk","Low Risk"))) -> Moderate Risk
A53: EMP-11104 | B53: Neha Nair | C53: DEP-ENG | D53: Engineering & Product | E53: ENG-L1 | F53: L1 | G53: Software Engineer I | H53: Bengaluru | I53: Hybrid | J53: 43679 | K53: Active | M53: N/A - Active | N53: Campus Recruitment | O53: 658000 | P53: 2 | Q53: No | R53: 35 | S53: MGR-102 | T53: =VALUE(MID(A53,5,5)) -> 11104 | U53: =LEFT(E53,3) -> ENG | V53: =RIGHT(E53,2) -> L1 | W53: =PROPER(TRIM(VLOOKUP(S53,Employee_Lookups!$I$4:$M$19,2,FALSE()))) -> Neha Kulkarni | X53: =VLOOKUP(C53,Employee_Lookups!$A$4:$G$9,4,FALSE()) -> CC-101 | Y53: =INDEX(Employee_Lookups!$C$13:$C$17,MATCH(F53,Employee_Lookups!$A$13:$A$17,0)) -> Band A (Entry) | Z53: =_xlfn.XLOOKUP(F53,Employee_Lookups!$A$13:$A$17,Employee_Lookups!$E$13:$E$17,0) -> 700000 | AA53: =ROUND(O53/INDEX(Employee_Lookups!$E$13:$E$17,MATCH(F53,Employee_Lookups!$A$13:$A$17,0)),3) -> 0.94 | AB53: =YEAR(J53) -> 2019 | AC53: =IF(ISBLANK(L53),"",YEAR(L53)) | AD53: =ROUND((IF(ISBLANK(L53),Employee_Lookups!$O$14,L53)-J53)/365.25,2) -> 6.41 | AE53: =IF(AD53<1,"< 1 Yr (New)",IF(AD53<3,"1 - 3 Yrs",IF(AD53<5,"3 - 5 Yrs","5+ Yrs"))) -> 5+ Yrs | AF53: =IF(K53<>"Active","Exited",IF(AND(Q53="Yes",OR(P53>=4,AA53<0.95)),"High Risk",IF(OR(Q53="Yes",AND(NOT(ISBLANK(P53)),P53<=2)),"Moderate Risk","Low Risk"))) -> Moderate Risk
A54: EMP-11124 | B54: Swati Reddy | C54: DEP-ENG | D54: Engineering & Product | E54: ENG-L5 | F54: L5 | G54: VP of Engineering | H54: Bengaluru | I54: Hybrid | J54: 43681 | K54: Active | M54: N/A - Active | N54: External Agency | O54: 4373000 | P54: 3 | Q54: No | R54: 27 | S54: MGR-102 | T54: =VALUE(MID(A54,5,5)) -> 11124 | U54: =LEFT(E54,3) -> ENG | V54: =RIGHT(E54,2) -> L5 | W54: =PROPER(TRIM(VLOOKUP(S54,Employee_Lookups!$I$4:$M$19,2,FALSE()))) -> Neha Kulkarni | X54: =VLOOKUP(C54,Employee_Lookups!$A$4:$G$9,4,FALSE()) -> CC-101 | Y54: =INDEX(Employee_Lookups!$C$13:$C$17,MATCH(F54,Employee_Lookups!$A$13:$A$17,0)) -> Band E (Executive) | Z54: =_xlfn.XLOOKUP(F54,Employee_Lookups!$A$13:$A$17,Employee_Lookups!$E$13:$E$17,0) -> 4300000 | AA54: =ROUND(O54/INDEX(Employee_Lookups!$E$13:$E$17,MATCH(F54,Employee_Lookups!$A$13:$A$17,0)),3) -> 1.017 | AB54: =YEAR(J54) -> 2019 | AC54: =IF(ISBLANK(L54),"",YEAR(L54)) | AD54: =ROUND((IF(ISBLANK(L54),Employee_Lookups!$O$14,L54)-J54)/365.25,2) -> 6.41 | AE54: =IF(AD54<1,"< 1 Yr (New)",IF(AD54<3,"1 - 3 Yrs",IF(AD54<5,"3 - 5 Yrs","5+ Yrs"))) -> 5+ Yrs | AF54: =IF(K54<>"Active","Exited",IF(AND(Q54="Yes",OR(P54>=4,AA54<0.95)),"High Risk",IF(OR(Q54="Yes",AND(NOT(ISBLANK(P54)),P54<=2)),"Moderate Risk","Low Risk"))) -> Low Risk
A55: EMP-11448 | B55: Aadhya Iyer | C55: DEP-SAL | D55: Enterprise Sales | E55: SAL-L1 | F55: L1 | G55: Sales Development Rep | H55: Mumbai | I55: On-Site | J55: 43682 | K55: Involuntary Exit | L55: 44042 | M55: Performance / Restructuring | N55: Employee Referral | O55: 606000 | P55: 1 | Q55: Yes | R55: 13 | S55: MGR-202 | T55: =VALUE(MID(A55,5,5)) -> 11448 | U55: =LEFT(E55,3) -> SAL | V55: =RIGHT(E55,2) -> L1 | W55: =PROPER(TRIM(VLOOKUP(S55,Employee_Lookups!$I$4:$M$19,2,FALSE()))) -> Priya Sharma | X55: =VLOOKUP(C55,Employee_Lookups!$A$4:$G$9,4,FALSE()) -> CC-202 | Y55: =INDEX(Employee_Lookups!$C$13:$C$17,MATCH(F55,Employee_Lookups!$A$13:$A$17,0)) -> Band A (Entry) | Z55: =_xlfn.XLOOKUP(F55,Employee_Lookups!$A$13:$A$17,Employee_Lookups!$E$13:$E$17,0) -> 700000 | AA55: =ROUND(O55/INDEX(Employee_Lookups!$E$13:$E$17,MATCH(F55,Employee_Lookups!$A$13:$A$17,0)),3) -> 0.866 | AB55: =YEAR(J55) -> 2019 | AC55: =IF(ISBLANK(L55),"",YEAR(L55)) -> 2020 | AD55: =ROUND((IF(ISBLANK(L55),Employee_Lookups!$O$14,L55)-J55)/365.25,2) -> 0.99 | AE55: =IF(AD55<1,"< 1 Yr (New)",IF(AD55<3,"1 - 3 Yrs",IF(AD55<5,"3 - 5 Yrs","5+ Yrs"))) -> < 1 Yr (New) | AF55: =IF(K55<>"Active","Exited",IF(AND(Q55="Yes",OR(P55>=4,AA55<0.95)),"High Risk",IF(OR(Q55="Yes",AND(NOT(ISBLANK(P55)),P55<=2)),"Moderate Risk","Low Risk"))) -> Exited
A56: EMP-10542 | B56: Ananya Sengupta | C56: DEP-MKT | D56: Growth Marketing | E56: MKT-L2 | F56: L2 | G56: Growth Specialist | H56: Pune | I56: Hybrid | J56: 43683 | K56: Active | M56: N/A - Active | N56: LinkedIn Sourcing | O56: 1324000 | P56: 2 | Q56: Yes | R56: 22 | S56: MGR-601 | T56: =VALUE(MID(A56,5,5)) -> 10542 | U56: =LEFT(E56,3) -> MKT | V56: =RIGHT(E56,2) -> L2 | W56: =PROPER(TRIM(VLOOKUP(S56,Employee_Lookups!$I$4:$M$19,2,FALSE()))) -> Tanvi Chitnis | X56: =VLOOKUP(C56,Employee_Lookups!$A$4:$G$9,4,FALSE()) -> CC-606 | Y56: =INDEX(Employee_Lookups!$C$13:$C$17,MATCH(F56,Employee_Lookups!$A$13:$A$17,0)) -> Band B (Mid) | Z56: =_xlfn.XLOOKUP(F56,Employee_Lookups!$A$13:$A$17,Employee_Lookups!$E$13:$E$17,0) -> 1100000 | AA56: =ROUND(O56/INDEX(Employee_Lookups!$E$13:$E$17,MATCH(F56,Employee_Lookups!$A$13:$A$17,0)),3) -> 1.204 | AB56: =YEAR(J56) -> 2019 | AC56: =IF(ISBLANK(L56),"",YEAR(L56)) | AD56: =ROUND((IF(ISBLANK(L56),Employee_Lookups!$O$14,L56)-J56)/365.25,2) -> 6.4 | AE56: =IF(AD56<1,"< 1 Yr (New)",IF(AD56<3,"1 - 3 Yrs",IF(AD56<5,"3 - 5 Yrs","5+ Yrs"))) -> 5+ Yrs | AF56: =IF(K56<>"Active","Exited",IF(AND(Q56="Yes",OR(P56>=4,AA56<0.95)),"High Risk",IF(OR(Q56="Yes",AND(NOT(ISBLANK(P56)),P56<=2)),"Moderate Risk","Low Risk"))) -> Moderate Risk
A57: EMP-10213 | B57: Mrunal Rao | C57: DEP-OPS | D57: Customer Operations | E57: OPS-L2 | F57: L2 | G57: Customer Success Specialist | H57: Hyderabad | I57: On-Site | J57: 43684 | K57: Voluntary Exit | L57: 45547 | M57: Compensation | N57: LinkedIn Sourcing | O57: 1276000 | P57: 3 | Q57: Yes | R57: 24 | S57: MGR-303 | T57: =VALUE(MID(A57,5,5)) -> 10213 | U57: =LEFT(E57,3) -> OPS | V57: =RIGHT(E57,2) -> L2 | W57: =PROPER(TRIM(VLOOKUP(S57,Employee_Lookups!$I$4:$M$19,2,FALSE()))) -> Meera Krishnan | X57: =VLOOKUP(C57,Employee_Lookups!$A$4:$G$9,4,FALSE()) -> CC-303 | Y57: =INDEX(Employee_Lookups!$C$13:$C$17,MATCH(F57,Employee_Lookups!$A$13:$A$17,0)) -> Band B (Mid) | Z57: =_xlfn.XLOOKUP(F57,Employee_Lookups!$A$13:$A$17,Employee_Lookups!$E$13:$E$17,0) -> 1100000 | AA57: =ROUND(O57/INDEX(Employee_Lookups!$E$13:$E$17,MATCH(F57,Employee_Lookups!$A$13:$A$17,0)),3) -> 1.16 | AB57: =YEAR(J57) -> 2019 | AC57: =IF(ISBLANK(L57),"",YEAR(L57)) -> 2024 | AD57: =ROUND((IF(ISBLANK(L57),Employee_Lookups!$O$14,L57)-J57)/365.25,2) -> 5.1 | AE57: =IF(AD57<1,"< 1 Yr (New)",IF(AD57<3,"1 - 3 Yrs",IF(AD57<5,"3 - 5 Yrs","5+ Yrs"))) -> 5+ Yrs | AF57: =IF(K57<>"Active","Exited",IF(AND(Q57="Yes",OR(P57>=4,AA57<0.95)),"High Risk",IF(OR(Q57="Yes",AND(NOT(ISBLANK(P57)),P57<=2)),"Moderate Risk","Low Risk"))) -> Exited
A58: EMP-10345 | B58: Kiara Rao | C58: DEP-SAL | D58: Enterprise Sales | E58: SAL-L1 | F58: L1 | G58: Sales Development Rep | H58: Bengaluru | I58: Hybrid | J58: 43686 | K58: Voluntary Exit | L58: 44696 | M58: Career Growth | N58: External Agency | O58: 795000 | P58: 4 | Q58: Yes | R58: 25 | S58: MGR-201 | T58: =VALUE(MID(A58,5,5)) -> 10345 | U58: =LEFT(E58,3) -> SAL | V58: =RIGHT(E58,2) -> L1 | W58: =PROPER(TRIM(VLOOKUP(S58,Employee_Lookups!$I$4:$M$19,2,FALSE()))) -> Vikramaditya Joshi | X58: =VLOOKUP(C58,Employee_Lookups!$A$4:$G$9,4,FALSE()) -> CC-202 | Y58: =INDEX(Employee_Lookups!$C$13:$C$17,MATCH(F58,Employee_Lookups!$A$13:$A$17,0)) -> Band A (Entry) | Z58: =_xlfn.XLOOKUP(F58,Employee_Lookups!$A$13:$A$17,Employee_Lookups!$E$13:$E$17,0) -> 700000 | AA58: =ROUND(O58/INDEX(Employee_Lookups!$E$13:$E$17,MATCH(F58,Employee_Lookups!$A$13:$A$17,0)),3) -> 1.136 | AB58: =YEAR(J58) -> 2019 | AC58: =IF(ISBLANK(L58),"",YEAR(L58)) -> 2022 | AD58: =ROUND((IF(ISBLANK(L58),Employee_Lookups!$O$14,L58)-J58)/365.25,2) -> 2.77 | AE58: =IF(AD58<1,"< 1 Yr (New)",IF(AD58<3,"1 - 3 Yrs",IF(AD58<5,"3 - 5 Yrs","5+ Yrs"))) -> 1 - 3 Yrs | AF58: =IF(K58<>"Active","Exited",IF(AND(Q58="Yes",OR(P58>=4,AA58<0.95)),"High Risk",IF(OR(Q58="Yes",AND(NOT(ISBLANK(P58)),P58<=2)),"Moderate Risk","Low Risk"))) -> Exited
A59: EMP-11119 | B59: Ira Nair | C59: DEP-ENG | D59: Engineering & Product | E59: ENG-L2 | F59: L2 | G59: Software Engineer II | H59: Pune | I59: Hybrid | J59: 43697 | K59: Active | M59: N/A - Active | N59: LinkedIn Sourcing | O59: 1285000 | P59: 3 | Q59: No | R59: 30 | S59: MGR-103 | T59: =VALUE(MID(A59,5,5)) -> 11119 | U59: =LEFT(E59,3) -> ENG | V59: =RIGHT(E59,2) -> L2 | W59: =PROPER(TRIM(VLOOKUP(S59,Employee_Lookups!$I$4:$M$19,2,FALSE()))) -> Rohan Verma | X59: =VLOOKUP(C59,Employee_Lookups!$A$4:$G$9,4,FALSE()) -> CC-101 | Y59: =INDEX(Employee_Lookups!$C$13:$C$17,MATCH(F59,Employee_Lookups!$A$13:$A$17,0)) -> Band B (Mid) | Z59: =_xlfn.XLOOKUP(F59,Employee_Lookups!$A$13:$A$17,Employee_Lookups!$E$13:$E$17,0) -> 1100000 | AA59: =ROUND(O59/INDEX(Employee_Lookups!$E$13:$E$17,MATCH(F59,Employee_Lookups!$A$13:$A$17,0)),3) -> 1.168 | AB59: =YEAR(J59) -> 2019 | AC59: =IF(ISBLANK(L59),"",YEAR(L59)) | AD59: =ROUND((IF(ISBLANK(L59),Employee_Lookups!$O$14,L59)-J59)/365.25,2) -> 6.37 | AE59: =IF(AD59<1,"< 1 Yr (New)",IF(AD59<3,"1 - 3 Yrs",IF(AD59<5,"3 - 5 Yrs","5+ Yrs"))) -> 5+ Yrs | AF59: =IF(K59<>"Active","Exited",IF(AND(Q59="Yes",OR(P59>=4,AA59<0.95)),"High Risk",IF(OR(Q59="Yes",AND(NOT(ISBLANK(P59)),P59<=2)),"Moderate Risk","Low Risk"))) -> Low Risk
A60: EMP-10522 | B60: Arjun Sharma | C60: DEP-HR | D60: People & Talent | E60: -HR-L4 | F60: L4 | G60: Director of People | H60: Pune | I60: Hybrid | J60: 43700 | K60: Active | M60: N/A - Active | N60: Employee Referral | O60: 2214000 | P60: 3 | Q60: No | R60: 29 | S60: MGR-501 | T60: =VALUE(MID(A60,5,5)) -> 10522 | U60: =LEFT(E60,3) -> -HR | V60: =RIGHT(E60,2) -> L4 | W60: =PROPER(TRIM(VLOOKUP(S60,Employee_Lookups!$I$4:$M$19,2,FALSE()))) -> Kavita Menon | X60: =VLOOKUP(C60,Employee_Lookups!$A$4:$G$9,4,FALSE()) -> CC-505 | Y60: =INDEX(Employee_Lookups!$C$13:$C$17,MATCH(F60,Employee_Lookups!$A$13:$A$17,0)) -> Band D (Leadership) | Z60: =_xlfn.XLOOKUP(F60,Employee_Lookups!$A$13:$A$17,Employee_Lookups!$E$13:$E$17,0) -> 2750000 | AA60: =ROUND(O60/INDEX(Employee_Lookups!$E$13:$E$17,MATCH(F60,Employee_Lookups!$A$13:$A$17,0)),3) -> 0.805 | AB60: =YEAR(J60) -> 2019 | AC60: =IF(ISBLANK(L60),"",YEAR(L60)) | AD60: =ROUND((IF(ISBLANK(L60),Employee_Lookups!$O$14,L60)-J60)/365.25,2) -> 6.36 | AE60: =IF(AD60<1,"< 1 Yr (New)",IF(AD60<3,"1 - 3 Yrs",IF(AD60<5,"3 - 5 Yrs","5+ Yrs"))) -> 5+ Yrs | AF60: =IF(K60<>"Active","Exited",IF(AND(Q60="Yes",OR(P60>=4,AA60<0.95)),"High Risk",IF(OR(Q60="Yes",AND(NOT(ISBLANK(P60)),P60<=2)),"Moderate Risk","Low Risk"))) -> Low Risk
A61: EMP-10187 | B61: Pari Chitnis | C61: DEP-ENG | D61: Engineering & Product | E61: ENG-L1 | F61: L1 | G61: Software Engineer I | H61: Remote-India | I61: Remote | J61: 43702 | K61: Active | M61: N/A - Active | N61: Company Career Portal | O61: 665000 | P61: 5 | Q61: Yes | R61: 46 | S61: MGR-104 | T61: =VALUE(MID(A61,5,5)) -> 10187 | U61: =LEFT(E61,3) -> ENG | V61: =RIGHT(E61,2) -> L1 | W61: =PROPER(TRIM(VLOOKUP(S61,Employee_Lookups!$I$4:$M$19,2,FALSE()))) -> Siddharth Nair | X61: =VLOOKUP(C61,Employee_Lookups!$A$4:$G$9,4,FALSE()) -> CC-101 | Y61: =INDEX(Employee_Lookups!$C$13:$C$17,MATCH(F61,Employee_Lookups!$A$13:$A$17,0)) -> Band A (Entry) | Z61: =_xlfn.XLOOKUP(F61,Employee_Lookups!$A$13:$A$17,Employee_Lookups!$E$13:$E$17,0) -> 700000 | AA61: =ROUND(O61/INDEX(Employee_Lookups!$E$13:$E$17,MATCH(F61,Employee_Lookups!$A$13:$A$17,0)),3) -> 0.95 | AB61: =YEAR(J61) -> 2019 | AC61: =IF(ISBLANK(L61),"",YEAR(L61)) | AD61: =ROUND((IF(ISBLANK(L61),Employee_Lookups!$O$14,L61)-J61)/365.25,2) -> 6.35 | AE61: =IF(AD61<1,"< 1 Yr (New)",IF(AD61<3,"1 - 3 Yrs",IF(AD61<5,"3 - 5 Yrs","5+ Yrs"))) -> 5+ Yrs | AF61: =IF(K61<>"Active","Exited",IF(AND(Q61="Yes",OR(P61>=4,AA61<0.95)),"High Risk",IF(OR(Q61="Yes",AND(NOT(ISBLANK(P61)),P61<=2)),"Moderate Risk","Low Risk"))) -> High Risk
A62: EMP-10417 | B62: Yash Malhotra | C62: DEP-ENG | D62: Engineering & Product | E62: ENG-L3 | F62: L3 | G62: Engineering Manager | H62: Bengaluru | I62: Hybrid | J62: 43703 | K62: Active | M62: N/A - Active | N62: LinkedIn Sourcing | O62: 1838000 | P62: 3 | Q62: No | R62: 27 | S62: MGR-101 | T62: =VALUE(MID(A62,5,5)) -> 10417 | U62: =LEFT(E62,3) -> ENG | V62: =RIGHT(E62,2) -> L3 | W62: =PROPER(TRIM(VLOOKUP(S62,Employee_Lookups!$I$4:$M$19,2,FALSE()))) -> Aarav Deshmukh | X62: =VLOOKUP(C62,Employee_Lookups!$A$4:$G$9,4,FALSE()) -> CC-101 | Y62: =INDEX(Employee_Lookups!$C$13:$C$17,MATCH(F62,Employee_Lookups!$A$13:$A$17,0)) -> Band C (Senior) | Z62: =_xlfn.XLOOKUP(F62,Employee_Lookups!$A$13:$A$17,Employee_Lookups!$E$13:$E$17,0) -> 1725000 | AA62: =ROUND(O62/INDEX(Employee_Lookups!$E$13:$E$17,MATCH(F62,Employee_Lookups!$A$13:$A$17,0)),3) -> 1.066 | AB62: =YEAR(J62) -> 2019 | AC62: =IF(ISBLANK(L62),"",YEAR(L62)) | AD62: =ROUND((IF(ISBLANK(L62),Employee_Lookups!$O$14,L62)-J62)/365.25,2) -> 6.35 | AE62: =IF(AD62<1,"< 1 Yr (New)",IF(AD62<3,"1 - 3 Yrs",IF(AD62<5,"3 - 5 Yrs","5+ Yrs"))) -> 5+ Yrs | AF62: =IF(K62<>"Active","Exited",IF(AND(Q62="Yes",OR(P62>=4,AA62<0.95)),"High Risk",IF(OR(Q62="Yes",AND(NOT(ISBLANK(P62)),P62<=2)),"Moderate Risk","Low Risk"))) -> Low Risk
A63: EMP-11253 | B63: Gaurav Sengupta | C63: DEP-HR | D63: People & Talent | E63: -HR-L2 | F63: L2 | G63: Talent Acquisition Partner | H63: Bengaluru | I63: Hybrid | J63: 43703 | K63: Active | M63: N/A - Active | N63: External Agency | O63: 995000 | P63: 4 | Q63: Yes | R63: 52 | S63: MGR-502 | T63: =VALUE(MID(A63,5,5)) -> 11253 | U63: =LEFT(E63,3) -> -HR | V63: =RIGHT(E63,2) -> L2 | W63: =PROPER(TRIM(VLOOKUP(S63,Employee_Lookups!$I$4:$M$19,2,FALSE()))) -> Nikhil Chatterjee | X63: =VLOOKUP(C63,Employee_Lookups!$A$4:$G$9,4,FALSE()) -> CC-505 | Y63: =INDEX(Employee_Lookups!$C$13:$C$17,MATCH(F63,Employee_Lookups!$A$13:$A$17,0)) -> Band B (Mid) | Z63: =_xlfn.XLOOKUP(F63,Employee_Lookups!$A$13:$A$17,Employee_Lookups!$E$13:$E$17,0) -> 1100000 | AA63: =ROUND(O63/INDEX(Employee_Lookups!$E$13:$E$17,MATCH(F63,Employee_Lookups!$A$13:$A$17,0)),3) -> 0.905 | AB63: =YEAR(J63) -> 2019 | AC63: =IF(ISBLANK(L63),"",YEAR(L63)) | AD63: =ROUND((IF(ISBLANK(L63),Employee_Lookups!$O$14,L63)-J63)/365.25,2) -> 6.35 | AE63: =IF(AD63<1,"< 1 Yr (New)",IF(AD63<3,"1 - 3 Yrs",IF(AD63<5,"3 - 5 Yrs","5+ Yrs"))) -> 5+ Yrs | AF63: =IF(K63<>"Active","Exited",IF(AND(Q63="Yes",OR(P63>=4,AA63<0.95)),"High Risk",IF(OR(Q63="Yes",AND(NOT(ISBLANK(P63)),P63<=2)),"Moderate Risk","Low Risk"))) -> High Risk
A64: EMP-10962 | B64: Neha Kapoor | C64: DEP-SAL | D64: Enterprise Sales | E64: SAL-L1 | F64: L1 | G64: Sales Development Rep | H64: Remote-India | I64: Remote | J64: 43705 | K64: Active | M64: N/A - Active | N64: Campus Recruitment | O64: 755000 | P64: 3 | Q64: Yes | R64: 7 | S64: MGR-202 | T64: =VALUE(MID(A64,5,5)) -> 10962 | U64: =LEFT(E64,3) -> SAL | V64: =RIGHT(E64,2) -> L1 | W64: =PROPER(TRIM(VLOOKUP(S64,Employee_Lookups!$I$4:$M$19,2,FALSE()))) -> Priya Sharma | X64: =VLOOKUP(C64,Employee_Lookups!$A$4:$G$9,4,FALSE()) -> CC-202 | Y64: =INDEX(Employee_Lookups!$C$13:$C$17,MATCH(F64,Employee_Lookups!$A$13:$A$17,0)) -> Band A (Entry) | Z64: =_xlfn.XLOOKUP(F64,Employee_Lookups!$A$13:$A$17,Employee_Lookups!$E$13:$E$17,0) -> 700000 | AA64: =ROUND(O64/INDEX(Employee_Lookups!$E$13:$E$17,MATCH(F64,Employee_Lookups!$A$13:$A$17,0)),3) -> 1.079 | AB64: =YEAR(J64) -> 2019 | AC64: =IF(ISBLANK(L64),"",YEAR(L64)) | AD64: =ROUND((IF(ISBLANK(L64),Employee_Lookups!$O$14,L64)-J64)/365.25,2) -> 6.34 | AE64: =IF(AD64<1,"< 1 Yr (New)",IF(AD64<3,"1 - 3 Yrs",IF(AD64<5,"3 - 5 Yrs","5+ Yrs"))) -> 5+ Yrs | AF64: =IF(K64<>"Active","Exited",IF(AND(Q64="Yes",OR(P64>=4,AA64<0.95)),"High Risk",IF(OR(Q64="Yes",AND(NOT(ISBLANK(P64)),P64<=2)),"Moderate Risk","Low Risk"))) -> Moderate Risk
A65: EMP-10038 | B65: Ayaan Joshi | C65: DEP-OPS | D65: Customer Operations | E65: OPS-L1 | F65: L1 | G65: Operations Coordinator | H65: Pune | I65: Hybrid | J65: 43713 | K65: Active | M65: N/A - Active | N65: Employee Referral | O65: 731000 | P65: 4 | Q65: Yes | R65: 36 | S65: MGR-303 | T65: =VALUE(MID(A65,5,5)) -> 10038 | U65: =LEFT(E65,3) -> OPS | V65: =RIGHT(E65,2) -> L1 | W65: =PROPER(TRIM(VLOOKUP(S65,Employee_Lookups!$I$4:$M$19,2,FALSE()))) -> Meera Krishnan | X65: =VLOOKUP(C65,Employee_Lookups!$A$4:$G$9,4,FALSE()) -> CC-303 | Y65: =INDEX(Employee_Lookups!$C$13:$C$17,MATCH(F65,Employee_Lookups!$A$13:$A$17,0)) -> Band A (Entry) | Z65: =_xlfn.XLOOKUP(F65,Employee_Lookups!$A$13:$A$17,Employee_Lookups!$E$13:$E$17,0) -> 700000 | AA65: =ROUND(O65/INDEX(Employee_Lookups!$E$13:$E$17,MATCH(F65,Employee_Lookups!$A$13:$A$17,0)),3) -> 1.044 | AB65: =YEAR(J65) -> 2019 | AC65: =IF(ISBLANK(L65),"",YEAR(L65)) | AD65: =ROUND((IF(ISBLANK(L65),Employee_Lookups!$O$14,L65)-J65)/365.25,2) -> 6.32 | AE65: =IF(AD65<1,"< 1 Yr (New)",IF(AD65<3,"1 - 3 Yrs",IF(AD65<5,"3 - 5 Yrs","5+ Yrs"))) -> 5+ Yrs | AF65: =IF(K65<>"Active","Exited",IF(AND(Q65="Yes",OR(P65>=4,AA65<0.95)),"High Risk",IF(OR(Q65="Yes",AND(NOT(ISBLANK(P65)),P65<=2)),"Moderate Risk","Low Risk"))) -> High Risk
A66: EMP-10111 | B66: Pranav Nair | C66: DEP-ENG | D66: Engineering & Product | E66: ENG-L5 | F66: L5 | G66: VP of Engineering | H66: Pune | I66: Hybrid | J66: 43713 | K66: Active | M66: N/A - Active | N66: Campus Recruitment | O66: 5059000 | P66: 4 | Q66: No | R66: 38 | S66: MGR-104 | T66: =VALUE(MID(A66,5,5)) -> 10111 | U66: =LEFT(E66,3) -> ENG | V66: =RIGHT(E66,2) -> L5 | W66: =PROPER(TRIM(VLOOKUP(S66,Employee_Lookups!$I$4:$M$19,2,FALSE()))) -> Siddharth Nair | X66: =VLOOKUP(C66,Employee_Lookups!$A$4:$G$9,4,FALSE()) -> CC-101 | Y66: =INDEX(Employee_Lookups!$C$13:$C$17,MATCH(F66,Employee_Lookups!$A$13:$A$17,0)) -> Band E (Executive) | Z66: =_xlfn.XLOOKUP(F66,Employee_Lookups!$A$13:$A$17,Employee_Lookups!$E$13:$E$17,0) -> 4300000 | AA66: =ROUND(O66/INDEX(Employee_Lookups!$E$13:$E$17,MATCH(F66,Employee_Lookups!$A$13:$A$17,0)),3) -> 1.177 | AB66: =YEAR(J66) -> 2019 | AC66: =IF(ISBLANK(L66),"",YEAR(L66)) | AD66: =ROUND((IF(ISBLANK(L66),Employee_Lookups!$O$14,L66)-J66)/365.25,2) -> 6.32 | AE66: =IF(AD66<1,"< 1 Yr (New)",IF(AD66<3,"1 - 3 Yrs",IF(AD66<5,"3 - 5 Yrs","5+ Yrs"))) -> 5+ Yrs | AF66: =IF(K66<>"Active","Exited",IF(AND(Q66="Yes",OR(P66>=4,AA66<0.95)),"High Risk",IF(OR(Q66="Yes",AND(NOT(ISBLANK(P66)),P66<=2)),"Moderate Risk","Low Risk"))) -> Low Risk
A67: EMP-11443 | B67: Omkar Kapoor | C67: DEP-HR | D67: People & Talent | E67: -HR-L1 | F67: L1 | G67: HR Coordinator | H67: Pune | I67: Hybrid | J67: 43713 | K67: Voluntary Exit | L67: 44244 | M67: Compensation | N67: Employee Referral | O67: 638000 | P67: 3 | Q67: No | R67: 31 | S67: MGR-502 | T67: =VALUE(MID(A67,5,5)) -> 11443 | U67: =LEFT(E67,3) -> -HR | V67: =RIGHT(E67,2) -> L1 | W67: =PROPER(TRIM(VLOOKUP(S67,Employee_Lookups!$I$4:$M$19,2,FALSE()))) -> Nikhil Chatterjee | X67: =VLOOKUP(C67,Employee_Lookups!$A$4:$G$9,4,FALSE()) -> CC-505 | Y67: =INDEX(Employee_Lookups!$C$13:$C$17,MATCH(F67,Employee_Lookups!$A$13:$A$17,0)) -> Band A (Entry) | Z67: =_xlfn.XLOOKUP(F67,Employee_Lookups!$A$13:$A$17,Employee_Lookups!$E$13:$E$17,0) -> 700000 | AA67: =ROUND(O67/INDEX(Employee_Lookups!$E$13:$E$17,MATCH(F67,Employee_Lookups!$A$13:$A$17,0)),3) -> 0.911 | AB67: =YEAR(J67) -> 2019 | AC67: =IF(ISBLANK(L67),"",YEAR(L67)) -> 2021 | AD67: =ROUND((IF(ISBLANK(L67),Employee_Lookups!$O$14,L67)-J67)/365.25,2) -> 1.45 | AE67: =IF(AD67<1,"< 1 Yr (New)",IF(AD67<3,"1 - 3 Yrs",IF(AD67<5,"3 - 5 Yrs","5+ Yrs"))) -> 1 - 3 Yrs | AF67: =IF(K67<>"Active","Exited",IF(AND(Q67="Yes",OR(P67>=4,AA67<0.95)),"High Risk",IF(OR(Q67="Yes",AND(NOT(ISBLANK(P67)),P67<=2)),"Moderate Risk","Low Risk"))) -> Exited
A68: EMP-10335 | B68: Arjun Mehta | C68: DEP-MKT | D68: Growth Marketing | E68: MKT-L2 | F68: L2 | G68: Growth Specialist | H68: Hyderabad | I68: On-Site | J68: 43714 | K68: Voluntary Exit | L68: 45758 | M68: Career Growth | N68: LinkedIn Sourcing | O68: 949000 | P68: 4 | Q68: No | R68: 42 | S68: MGR-601 | T68: =VALUE(MID(A68,5,5)) -> 10335 | U68: =LEFT(E68,3) -> MKT | V68: =RIGHT(E68,2) -> L2 | W68: =PROPER(TRIM(VLOOKUP(S68,Employee_Lookups!$I$4:$M$19,2,FALSE()))) -> Tanvi Chitnis | X68: =VLOOKUP(C68,Employee_Lookups!$A$4:$G$9,4,FALSE()) -> CC-606 | Y68: =INDEX(Employee_Lookups!$C$13:$C$17,MATCH(F68,Employee_Lookups!$A$13:$A$17,0)) -> Band B (Mid) | Z68: =_xlfn.XLOOKUP(F68,Employee_Lookups!$A$13:$A$17,Employee_Lookups!$E$13:$E$17,0) -> 1100000 | AA68: =ROUND(O68/INDEX(Employee_Lookups!$E$13:$E$17,MATCH(F68,Employee_Lookups!$A$13:$A$17,0)),3) -> 0.863 | AB68: =YEAR(J68) -> 2019 | AC68: =IF(ISBLANK(L68),"",YEAR(L68)) -> 2025 | AD68: =ROUND((IF(ISBLANK(L68),Employee_Lookups!$O$14,L68)-J68)/365.25,2) -> 5.6 | AE68: =IF(AD68<1,"< 1 Yr (New)",IF(AD68<3,"1 - 3 Yrs",IF(AD68<5,"3 - 5 Yrs","5+ Yrs"))) -> 5+ Yrs | AF68: =IF(K68<>"Active","Exited",IF(AND(Q68="Yes",OR(P68>=4,AA68<0.95)),"High Risk",IF(OR(Q68="Yes",AND(NOT(ISBLANK(P68)),P68<=2)),"Moderate Risk","Low Risk"))) -> Exited
A69: EMP-10234 | B69: Nikhil Sengupta | C69: DEP-OPS | D69: Customer Operations | E69: OPS-L3 | F69: L3 | G69: Operations Lead | H69: Pune | I69: Hybrid | J69: 43717 | K69: Active | M69: N/A - Active | N69: Campus Recruitment | O69: 1817000 | P69: 3 | Q69: No | R69: 28 | S69: MGR-302 | T69: =VALUE(MID(A69,5,5)) -> 10234 | U69: =LEFT(E69,3) -> OPS | V69: =RIGHT(E69,2) -> L3 | W69: =PROPER(TRIM(VLOOKUP(S69,Employee_Lookups!$I$4:$M$19,2,FALSE()))) -> Deepak Patil | X69: =VLOOKUP(C69,Employee_Lookups!$A$4:$G$9,4,FALSE()) -> CC-303 | Y69: =INDEX(Employee_Lookups!$C$13:$C$17,MATCH(F69,Employee_Lookups!$A$13:$A$17,0)) -> Band C (Senior) | Z69: =_xlfn.XLOOKUP(F69,Employee_Lookups!$A$13:$A$17,Employee_Lookups!$E$13:$E$17,0) -> 1725000 | AA69: =ROUND(O69/INDEX(Employee_Lookups!$E$13:$E$17,MATCH(F69,Employee_Lookups!$A$13:$A$17,0)),3) -> 1.053 | AB69: =YEAR(J69) -> 2019 | AC69: =IF(ISBLANK(L69),"",YEAR(L69)) | AD69: =ROUND((IF(ISBLANK(L69),Employee_Lookups!$O$14,L69)-J69)/365.25,2) -> 6.31 | AE69: =IF(AD69<1,"< 1 Yr (New)",IF(AD69<3,"1 - 3 Yrs",IF(AD69<5,"3 - 5 Yrs","5+ Yrs"))) -> 5+ Yrs | AF69: =IF(K69<>"Active","Exited",IF(AND(Q69="Yes",OR(P69>=4,AA69<0.95)),"High Risk",IF(OR(Q69="Yes",AND(NOT(ISBLANK(P69)),P69<=2)),"Moderate Risk","Low Risk"))) -> Low Risk
A70: EMP-10296 | B70: Vivaan Sengupta | C70: DEP-ENG | D70: Engineering & Product | E70: ENG-L1 | F70: L1 | G70: Software Engineer I | H70: Bengaluru | I70: Hybrid | J70: 43718 | K70: Active | M70: N/A - Active | N70: External Agency | O70: 794000 | P70: 3 | Q70: Yes | R70: 38 | S70: MGR-103 | T70: =VALUE(MID(A70,5,5)) -> 10296 | U70: =LEFT(E70,3) -> ENG | V70: =RIGHT(E70,2) -> L1 | W70: =PROPER(TRIM(VLOOKUP(S70,Employee_Lookups!$I$4:$M$19,2,FALSE()))) -> Rohan Verma | X70: =VLOOKUP(C70,Employee_Lookups!$A$4:$G$9,4,FALSE()) -> CC-101 | Y70: =INDEX(Employee_Lookups!$C$13:$C$17,MATCH(F70,Employee_Lookups!$A$13:$A$17,0)) -> Band A (Entry) | Z70: =_xlfn.XLOOKUP(F70,Employee_Lookups!$A$13:$A$17,Employee_Lookups!$E$13:$E$17,0) -> 700000 | AA70: =ROUND(O70/INDEX(Employee_Lookups!$E$13:$E$17,MATCH(F70,Employee_Lookups!$A$13:$A$17,0)),3) -> 1.134 | AB70: =YEAR(J70) -> 2019 | AC70: =IF(ISBLANK(L70),"",YEAR(L70)) | AD70: =ROUND((IF(ISBLANK(L70),Employee_Lookups!$O$14,L70)-J70)/365.25,2) -> 6.31 | AE70: =IF(AD70<1,"< 1 Yr (New)",IF(AD70<3,"1 - 3 Yrs",IF(AD70<5,"3 - 5 Yrs","5+ Yrs"))) -> 5+ Yrs | AF70: =IF(K70<>"Active","Exited",IF(AND(Q70="Yes",OR(P70>=4,AA70<0.95)),"High Risk",IF(OR(Q70="Yes",AND(NOT(ISBLANK(P70)),P70<=2)),"Moderate Risk","Low Risk"))) -> Moderate Risk
A71: EMP-10211 | B71: Arjun Mehta | C71: DEP-ENG | D71: Engineering & Product | E71: ENG-L1 | F71: L1 | G71: Software Engineer I | H71: Bengaluru | I71: Hybrid | J71: 43720 | K71: Voluntary Exit | L71: 43850 | M71: Relocation | N71: LinkedIn Sourcing | O71: 745000 | P71: 4 | Q71: No | R71: 38 | S71: MGR-102 | T71: =VALUE(MID(A71,5,5)) -> 10211 | U71: =LEFT(E71,3) -> ENG | V71: =RIGHT(E71,2) -> L1 | W71: =PROPER(TRIM(VLOOKUP(S71,Employee_Lookups!$I$4:$M$19,2,FALSE()))) -> Neha Kulkarni | X71: =VLOOKUP(C71,Employee_Lookups!$A$4:$G$9,4,FALSE()) -> CC-101 | Y71: =INDEX(Employee_Lookups!$C$13:$C$17,MATCH(F71,Employee_Lookups!$A$13:$A$17,0)) -> Band A (Entry) | Z71: =_xlfn.XLOOKUP(F71,Employee_Lookups!$A$13:$A$17,Employee_Lookups!$E$13:$E$17,0) -> 700000 | AA71: =ROUND(O71/INDEX(Employee_Lookups!$E$13:$E$17,MATCH(F71,Employee_Lookups!$A$13:$A$17,0)),3) -> 1.064 | AB71: =YEAR(J71) -> 2019 | AC71: =IF(ISBLANK(L71),"",YEAR(L71)) -> 2020 | AD71: =ROUND((IF(ISBLANK(L71),Employee_Lookups!$O$14,L71)-J71)/365.25,2) -> 0.36 | AE71: =IF(AD71<1,"< 1 Yr (New)",IF(AD71<3,"1 - 3 Yrs",IF(AD71<5,"3 - 5 Yrs","5+ Yrs"))) -> < 1 Yr (New) | AF71: =IF(K71<>"Active","Exited",IF(AND(Q71="Yes",OR(P71>=4,AA71<0.95)),"High Risk",IF(OR(Q71="Yes",AND(NOT(ISBLANK(P71)),P71<=2)),"Moderate Risk","Low Risk"))) -> Exited
A72: EMP-11391 | B72: Tejas Shah | C72: DEP-OPS | D72: Customer Operations | E72: OPS-L1 | F72: L1 | G72: Operations Coordinator | H72: Bengaluru | I72: Hybrid | J72: 43724 | K72: Voluntary Exit | L72: 44018 | M72: Compensation | N72: Employee Referral | O72: 631000 | P72: 4 | Q72: No | R72: 48 | S72: MGR-301 | T72: =VALUE(MID(A72,5,5)) -> 11391 | U72: =LEFT(E72,3) -> OPS | V72: =RIGHT(E72,2) -> L1 | W72: =PROPER(TRIM(VLOOKUP(S72,Employee_Lookups!$I$4:$M$19,2,FALSE()))) -> Ananya Iyer | X72: =VLOOKUP(C72,Employee_Lookups!$A$4:$G$9,4,FALSE()) -> CC-303 | Y72: =INDEX(Employee_Lookups!$C$13:$C$17,MATCH(F72,Employee_Lookups!$A$13:$A$17,0)) -> Band A (Entry) | Z72: =_xlfn.XLOOKUP(F72,Employee_Lookups!$A$13:$A$17,Employee_Lookups!$E$13:$E$17,0) -> 700000 | AA72: =ROUND(O72/INDEX(Employee_Lookups!$E$13:$E$17,MATCH(F72,Employee_Lookups!$A$13:$A$17,0)),3) -> 0.901 | AB72: =YEAR(J72) -> 2019 | AC72: =IF(ISBLANK(L72),"",YEAR(L72)) -> 2020 | AD72: =ROUND((IF(ISBLANK(L72),Employee_Lookups!$O$14,L72)-J72)/365.25,2) -> 0.8 | AE72: =IF(AD72<1,"< 1 Yr (New)",IF(AD72<3,"1 - 3 Yrs",IF(AD72<5,"3 - 5 Yrs","5+ Yrs"))) -> < 1 Yr (New) | AF72: =IF(K72<>"Active","Exited",IF(AND(Q72="Yes",OR(P72>=4,AA72<0.95)),"High Risk",IF(OR(Q72="Yes",AND(NOT(ISBLANK(P72)),P72<=2)),"Moderate Risk","Low Risk"))) -> Exited
A73: EMP-11413 | B73: Saanvi Kapoor | C73: DEP-MKT | D73: Growth Marketing | E73: MKT-L2 | F73: L2 | G73: Growth Specialist | H73: Pune | I73: Hybrid | J73: 43741 | K73: Voluntary Exit | L73: 43868 | M73: Relocation | N73: Employee Referral | O73: 1155000 | P73: 3 | Q73: Yes | R73: 29 | S73: MGR-601 | T73: =VALUE(MID(A73,5,5)) -> 11413 | U73: =LEFT(E73,3) -> MKT | V73: =RIGHT(E73,2) -> L2 | W73: =PROPER(TRIM(VLOOKUP(S73,Employee_Lookups!$I$4:$M$19,2,FALSE()))) -> Tanvi Chitnis | X73: =VLOOKUP(C73,Employee_Lookups!$A$4:$G$9,4,FALSE()) -> CC-606 | Y73: =INDEX(Employee_Lookups!$C$13:$C$17,MATCH(F73,Employee_Lookups!$A$13:$A$17,0)) -> Band B (Mid) | Z73: =_xlfn.XLOOKUP(F73,Employee_Lookups!$A$13:$A$17,Employee_Lookups!$E$13:$E$17,0) -> 1100000 | AA73: =ROUND(O73/INDEX(Employee_Lookups!$E$13:$E$17,MATCH(F73,Employee_Lookups!$A$13:$A$17,0)),3) -> 1.05 | AB73: =YEAR(J73) -> 2019 | AC73: =IF(ISBLANK(L73),"",YEAR(L73)) -> 2020 | AD73: =ROUND((IF(ISBLANK(L73),Employee_Lookups!$O$14,L73)-J73)/365.25,2) -> 0.35 | AE73: =IF(AD73<1,"< 1 Yr (New)",IF(AD73<3,"1 - 3 Yrs",IF(AD73<5,"3 - 5 Yrs","5+ Yrs"))) -> < 1 Yr (New) | AF73: =IF(K73<>"Active","Exited",IF(AND(Q73="Yes",OR(P73>=4,AA73<0.95)),"High Risk",IF(OR(Q73="Yes",AND(NOT(ISBLANK(P73)),P73<=2)),"Moderate Risk","Low Risk"))) -> Exited
A74: EMP-11089 | B74: Aditya Nair | C74: DEP-OPS | D74: Customer Operations | E74: OPS-L1 | F74: L1 | G74: Operations Coordinator | H74: Hyderabad | I74: On-Site | J74: 43753 | K74: Voluntary Exit | L74: 43955 | M74: Career Growth | N74: Campus Recruitment | O74: 649000 | P74: 3 | Q74: No | R74: 0 | S74: MGR-303 | T74: =VALUE(MID(A74,5,5)) -> 11089 | U74: =LEFT(E74,3) -> OPS | V74: =RIGHT(E74,2) -> L1 | W74: =PROPER(TRIM(VLOOKUP(S74,Employee_Lookups!$I$4:$M$19,2,FALSE()))) -> Meera Krishnan | X74: =VLOOKUP(C74,Employee_Lookups!$A$4:$G$9,4,FALSE()) -> CC-303 | Y74: =INDEX(Employee_Lookups!$C$13:$C$17,MATCH(F74,Employee_Lookups!$A$13:$A$17,0)) -> Band A (Entry) | Z74: =_xlfn.XLOOKUP(F74,Employee_Lookups!$A$13:$A$17,Employee_Lookups!$E$13:$E$17,0) -> 700000 | AA74: =ROUND(O74/INDEX(Employee_Lookups!$E$13:$E$17,MATCH(F74,Employee_Lookups!$A$13:$A$17,0)),3) -> 0.927 | AB74: =YEAR(J74) -> 2019 | AC74: =IF(ISBLANK(L74),"",YEAR(L74)) -> 2020 | AD74: =ROUND((IF(ISBLANK(L74),Employee_Lookups!$O$14,L74)-J74)/365.25,2) -> 0.55 | AE74: =IF(AD74<1,"< 1 Yr (New)",IF(AD74<3,"1 - 3 Yrs",IF(AD74<5,"3 - 5 Yrs","5+ Yrs"))) -> < 1 Yr (New) | AF74: =IF(K74<>"Active","Exited",IF(AND(Q74="Yes",OR(P74>=4,AA74<0.95)),"High Risk",IF(OR(Q74="Yes",AND(NOT(ISBLANK(P74)),P74<=2)),"Moderate Risk","Low Risk"))) -> Exited
A75: EMP-10724 | B75: Ananya Rao | C75: DEP-OPS | D75: Customer Operations | E75: OPS-L1 | F75: L1 | G75: Operations Coordinator | H75: Bengaluru | I75: Hybrid | J75: 43757 | K75: Active | M75: N/A - Active | N75: External Agency | O75: 581000 | P75: 3 | Q75: Yes | R75: 48 | S75: MGR-302 | T75: =VALUE(MID(A75,5,5)) -> 10724 | U75: =LEFT(E75,3) -> OPS | V75: =RIGHT(E75,2) -> L1 | W75: =PROPER(TRIM(VLOOKUP(S75,Employee_Lookups!$I$4:$M$19,2,FALSE()))) -> Deepak Patil | X75: =VLOOKUP(C75,Employee_Lookups!$A$4:$G$9,4,FALSE()) -> CC-303 | Y75: =INDEX(Employee_Lookups!$C$13:$C$17,MATCH(F75,Employee_Lookups!$A$13:$A$17,0)) -> Band A (Entry) | Z75: =_xlfn.XLOOKUP(F75,Employee_Lookups!$A$13:$A$17,Employee_Lookups!$E$13:$E$17,0) -> 700000 | AA75: =ROUND(O75/INDEX(Employee_Lookups!$E$13:$E$17,MATCH(F75,Employee_Lookups!$A$13:$A$17,0)),3) -> 0.83 | AB75: =YEAR(J75) -> 2019 | AC75: =IF(ISBLANK(L75),"",YEAR(L75)) | AD75: =ROUND((IF(ISBLANK(L75),Employee_Lookups!$O$14,L75)-J75)/365.25,2) -> 6.2 | AE75: =IF(AD75<1,"< 1 Yr (New)",IF(AD75<3,"1 - 3 Yrs",IF(AD75<5,"3 - 5 Yrs","5+ Yrs"))) -> 5+ Yrs | AF75: =IF(K75<>"Active","Exited",IF(AND(Q75="Yes",OR(P75>=4,AA75<0.95)),"High Risk",IF(OR(Q75="Yes",AND(NOT(ISBLANK(P75)),P75<=2)),"Moderate Risk","Low Risk"))) -> High Risk
A76: EMP-10157 | B76: Swati Shah | C76: DEP-ENG | D76: Engineering & Product | E76: ENG-L2 | F76: L2 | G76: Software Engineer II | H76: Bengaluru | I76: Hybrid | J76: 43760 | K76: Voluntary Exit | L76: 45065 | M76: Work-Life Balance | N76: Campus Recruitment | O76: 984000 | P76: 4 | Q76: No | R76: 29 | S76: MGR-101 | T76: =VALUE(MID(A76,5,5)) -> 10157 | U76: =LEFT(E76,3) -> ENG | V76: =RIGHT(E76,2) -> L2 | W76: =PROPER(TRIM(VLOOKUP(S76,Employee_Lookups!$I$4:$M$19,2,FALSE()))) -> Aarav Deshmukh | X76: =VLOOKUP(C76,Employee_Lookups!$A$4:$G$9,4,FALSE()) -> CC-101 | Y76: =INDEX(Employee_Lookups!$C$13:$C$17,MATCH(F76,Employee_Lookups!$A$13:$A$17,0)) -> Band B (Mid) | Z76: =_xlfn.XLOOKUP(F76,Employee_Lookups!$A$13:$A$17,Employee_Lookups!$E$13:$E$17,0) -> 1100000 | AA76: =ROUND(O76/INDEX(Employee_Lookups!$E$13:$E$17,MATCH(F76,Employee_Lookups!$A$13:$A$17,0)),3) -> 0.895 | AB76: =YEAR(J76) -> 2019 | AC76: =IF(ISBLANK(L76),"",YEAR(L76)) -> 2023 | AD76: =ROUND((IF(ISBLANK(L76),Employee_Lookups!$O$14,L76)-J76)/365.25,2) -> 3.57 | AE76: =IF(AD76<1,"< 1 Yr (New)",IF(AD76<3,"1 - 3 Yrs",IF(AD76<5,"3 - 5 Yrs","5+ Yrs"))) -> 3 - 5 Yrs | AF76: =IF(K76<>"Active","Exited",IF(AND(Q76="Yes",OR(P76>=4,AA76<0.95)),"High Risk",IF(OR(Q76="Yes",AND(NOT(ISBLANK(P76)),P76<=2)),"Moderate Risk","Low Risk"))) -> Exited
A77: EMP-11002 | B77: Neha Iyer | C77: DEP-MKT | D77: Growth Marketing | E77: MKT-L2 | F77: L2 | G77: Growth Specialist | H77: Hyderabad | I77: On-Site | J77: 43780 | K77: Active | M77: N/A - Active | N77: LinkedIn Sourcing | O77: 1340000 | P77: 2 | Q77: No | R77: 29 | S77: MGR-602 | T77: =VALUE(MID(A77,5,5)) -> 11002 | U77: =LEFT(E77,3) -> MKT | V77: =RIGHT(E77,2) -> L2 | W77: =PROPER(TRIM(VLOOKUP(S77,Employee_Lookups!$I$4:$M$19,2,FALSE()))) -> Arjun Sengupta | X77: =VLOOKUP(C77,Employee_Lookups!$A$4:$G$9,4,FALSE()) -> CC-606 | Y77: =INDEX(Employee_Lookups!$C$13:$C$17,MATCH(F77,Employee_Lookups!$A$13:$A$17,0)) -> Band B (Mid) | Z77: =_xlfn.XLOOKUP(F77,Employee_Lookups!$A$13:$A$17,Employee_Lookups!$E$13:$E$17,0) -> 1100000 | AA77: =ROUND(O77/INDEX(Employee_Lookups!$E$13:$E$17,MATCH(F77,Employee_Lookups!$A$13:$A$17,0)),3) -> 1.218 | AB77: =YEAR(J77) -> 2019 | AC77: =IF(ISBLANK(L77),"",YEAR(L77)) | AD77: =ROUND((IF(ISBLANK(L77),Employee_Lookups!$O$14,L77)-J77)/365.25,2) -> 6.14 | AE77: =IF(AD77<1,"< 1 Yr (New)",IF(AD77<3,"1 - 3 Yrs",IF(AD77<5,"3 - 5 Yrs","5+ Yrs"))) -> 5+ Yrs | AF77: =IF(K77<>"Active","Exited",IF(AND(Q77="Yes",OR(P77>=4,AA77<0.95)),"High Risk",IF(OR(Q77="Yes",AND(NOT(ISBLANK(P77)),P77<=2)),"Moderate Risk","Low Risk"))) -> Moderate Risk
A78: EMP-10555 | B78: Pallavi Verma | C78: DEP-SAL | D78: Enterprise Sales | E78: SAL-L2 | F78: L2 | G78: Account Executive | H78: Pune | I78: Hybrid | J78: 43786 | K78: Involuntary Exit | L78: 44107 | M78: Performance / Restructuring | N78: Employee Referral | O78: 1212000 | P78: 2 | Q78: Yes | R78: 36 | S78: MGR-203 | T78: =VALUE(MID(A78,5,5)) -> 10555 | U78: =LEFT(E78,3) -> SAL | V78: =RIGHT(E78,2) -> L2 | W78: =PROPER(TRIM(VLOOKUP(S78,Employee_Lookups!$I$4:$M$19,2,FALSE()))) -> Karan Malhotra | X78: =VLOOKUP(C78,Employee_Lookups!$A$4:$G$9,4,FALSE()) -> CC-202 | Y78: =INDEX(Employee_Lookups!$C$13:$C$17,MATCH(F78,Employee_Lookups!$A$13:$A$17,0)) -> Band B (Mid) | Z78: =_xlfn.XLOOKUP(F78,Employee_Lookups!$A$13:$A$17,Employee_Lookups!$E$13:$E$17,0) -> 1100000 | AA78: =ROUND(O78/INDEX(Employee_Lookups!$E$13:$E$17,MATCH(F78,Employee_Lookups!$A$13:$A$17,0)),3) -> 1.102 | AB78: =YEAR(J78) -> 2019 | AC78: =IF(ISBLANK(L78),"",YEAR(L78)) -> 2020 | AD78: =ROUND((IF(ISBLANK(L78),Employee_Lookups!$O$14,L78)-J78)/365.25,2) -> 0.88 | AE78: =IF(AD78<1,"< 1 Yr (New)",IF(AD78<3,"1 - 3 Yrs",IF(AD78<5,"3 - 5 Yrs","5+ Yrs"))) -> < 1 Yr (New) | AF78: =IF(K78<>"Active","Exited",IF(AND(Q78="Yes",OR(P78>=4,AA78<0.95)),"High Risk",IF(OR(Q78="Yes",AND(NOT(ISBLANK(P78)),P78<=2)),"Moderate Risk","Low Risk"))) -> Exited
A79: EMP-10997 | B79: Siddharth Reddy | C79: DEP-SAL | D79: Enterprise Sales | E79: SAL-L2 | F79: L2 | G79: Account Executive | H79: Bengaluru | I79: Hybrid | J79: 43786 | K79: Involuntary Exit | L79: 44830 | M79: Performance / Restructuring | N79: Employee Referral | O79: 1334000 | P79: 3 | Q79: Yes | R79: 44 | S79: MGR-201 | T79: =VALUE(MID(A79,5,5)) -> 10997 | U79: =LEFT(E79,3) -> SAL | V79: =RIGHT(E79,2) -> L2 | W79: =PROPER(TRIM(VLOOKUP(S79,Employee_Lookups!$I$4:$M$19,2,FALSE()))) -> Vikramaditya Joshi | X79: =VLOOKUP(C79,Employee_Lookups!$A$4:$G$9,4,FALSE()) -> CC-202 | Y79: =INDEX(Employee_Lookups!$C$13:$C$17,MATCH(F79,Employee_Lookups!$A$13:$A$17,0)) -> Band B (Mid) | Z79: =_xlfn.XLOOKUP(F79,Employee_Lookups!$A$13:$A$17,Employee_Lookups!$E$13:$E$17,0) -> 1100000 | AA79: =ROUND(O79/INDEX(Employee_Lookups!$E$13:$E$17,MATCH(F79,Employee_Lookups!$A$13:$A$17,0)),3) -> 1.213 | AB79: =YEAR(J79) -> 2019 | AC79: =IF(ISBLANK(L79),"",YEAR(L79)) -> 2022 | AD79: =ROUND((IF(ISBLANK(L79),Employee_Lookups!$O$14,L79)-J79)/365.25,2) -> 2.86 | AE79: =IF(AD79<1,"< 1 Yr (New)",IF(AD79<3,"1 - 3 Yrs",IF(AD79<5,"3 - 5 Yrs","5+ Yrs"))) -> 1 - 3 Yrs | AF79: =IF(K79<>"Active","Exited",IF(AND(Q79="Yes",OR(P79>=4,AA79<0.95)),"High Risk",IF(OR(Q79="Yes",AND(NOT(ISBLANK(P79)),P79<=2)),"Moderate Risk","Low Risk"))) -> Exited
A80: EMP-10171 | B80: Omkar Mehta | C80: DEP-OPS | D80: Customer Operations | E80: OPS-L2 | F80: L2 | G80: Customer Success Specialist | H80: Bengaluru | I80: Hybrid | J80: 43788 | K80: Voluntary Exit | L80: 45122 | M80: Work-Life Balance | N80: Company Career Portal | O80: 1343000 | P80: 3 | Q80: No | R80: 44 | S80: MGR-302 | T80: =VALUE(MID(A80,5,5)) -> 10171 | U80: =LEFT(E80,3) -> OPS | V80: =RIGHT(E80,2) -> L2 | W80: =PROPER(TRIM(VLOOKUP(S80,Employee_Lookups!$I$4:$M$19,2,FALSE()))) -> Deepak Patil | X80: =VLOOKUP(C80,Employee_Lookups!$A$4:$G$9,4,FALSE()) -> CC-303 | Y80: =INDEX(Employee_Lookups!$C$13:$C$17,MATCH(F80,Employee_Lookups!$A$13:$A$17,0)) -> Band B (Mid) | Z80: =_xlfn.XLOOKUP(F80,Employee_Lookups!$A$13:$A$17,Employee_Lookups!$E$13:$E$17,0) -> 1100000 | AA80: =ROUND(O80/INDEX(Employee_Lookups!$E$13:$E$17,MATCH(F80,Employee_Lookups!$A$13:$A$17,0)),3) -> 1.221 | AB80: =YEAR(J80) -> 2019 | AC80: =IF(ISBLANK(L80),"",YEAR(L80)) -> 2023 | AD80: =ROUND((IF(ISBLANK(L80),Employee_Lookups!$O$14,L80)-J80)/365.25,2) -> 3.65 | AE80: =IF(AD80<1,"< 1 Yr (New)",IF(AD80<3,"1 - 3 Yrs",IF(AD80<5,"3 - 5 Yrs","5+ Yrs"))) -> 3 - 5 Yrs | AF80: =IF(K80<>"Active","Exited",IF(AND(Q80="Yes",OR(P80>=4,AA80<0.95)),"High Risk",IF(OR(Q80="Yes",AND(NOT(ISBLANK(P80)),P80<=2)),"Moderate Risk","Low Risk"))) -> Exited
A81: EMP-11113 | B81: Myra Kapoor | C81: DEP-ENG | D81: Engineering & Product | E81: ENG-L2 | F81: L2 | G81: Software Engineer II | H81: Bengaluru | I81: Hybrid | J81: 43789 | K81: Involuntary Exit | L81: 43887 | M81: Performance / Restructuring | N81: LinkedIn Sourcing | O81: 1168000 | P81: 2 | Q81: Yes | R81: 13 | S81: MGR-104 | T81: =VALUE(MID(A81,5,5)) -> 11113 | U81: =LEFT(E81,3) -> ENG | V81: =RIGHT(E81,2) -> L2 | W81: =PROPER(TRIM(VLOOKUP(S81,Employee_Lookups!$I$4:$M$19,2,FALSE()))) -> Siddharth Nair | X81: =VLOOKUP(C81,Employee_Lookups!$A$4:$G$9,4,FALSE()) -> CC-101 | Y81: =INDEX(Employee_Lookups!$C$13:$C$17,MATCH(F81,Employee_Lookups!$A$13:$A$17,0)) -> Band B (Mid) | Z81: =_xlfn.XLOOKUP(F81,Employee_Lookups!$A$13:$A$17,Employee_Lookups!$E$13:$E$17,0) -> 1100000 | AA81: =ROUND(O81/INDEX(Employee_Lookups!$E$13:$E$17,MATCH(F81,Employee_Lookups!$A$13:$A$17,0)),3) -> 1.062 | AB81: =YEAR(J81) -> 2019 | AC81: =IF(ISBLANK(L81),"",YEAR(L81)) -> 2020 | AD81: =ROUND((IF(ISBLANK(L81),Employee_Lookups!$O$14,L81)-J81)/365.25,2) -> 0.27 | AE81: =IF(AD81<1,"< 1 Yr (New)",IF(AD81<3,"1 - 3 Yrs",IF(AD81<5,"3 - 5 Yrs","5+ Yrs"))) -> < 1 Yr (New) | AF81: =IF(K81<>"Active","Exited",IF(AND(Q81="Yes",OR(P81>=4,AA81<0.95)),"High Risk",IF(OR(Q81="Yes",AND(NOT(ISBLANK(P81)),P81<=2)),"Moderate Risk","Low Risk"))) -> Exited
A82: EMP-11042 | B82: Ananya Sengupta | C82: DEP-OPS | D82: Customer Operations | E82: OPS-L2 | F82: L2 | G82: Customer Success Specialist | H82: Bengaluru | I82: Hybrid | J82: 43794 | K82: Involuntary Exit | L82: 44020 | M82: Performance / Restructuring | N82: Campus Recruitment | O82: 1099000 | P82: 2 | Q82: Yes | R82: 33 | S82: MGR-302 | T82: =VALUE(MID(A82,5,5)) -> 11042 | U82: =LEFT(E82,3) -> OPS | V82: =RIGHT(E82,2) -> L2 | W82: =PROPER(TRIM(VLOOKUP(S82,Employee_Lookups!$I$4:$M$19,2,FALSE()))) -> Deepak Patil | X82: =VLOOKUP(C82,Employee_Lookups!$A$4:$G$9,4,FALSE()) -> CC-303 | Y82: =INDEX(Employee_Lookups!$C$13:$C$17,MATCH(F82,Employee_Lookups!$A$13:$A$17,0)) -> Band B (Mid) | Z82: =_xlfn.XLOOKUP(F82,Employee_Lookups!$A$13:$A$17,Employee_Lookups!$E$13:$E$17,0) -> 1100000 | AA82: =ROUND(O82/INDEX(Employee_Lookups!$E$13:$E$17,MATCH(F82,Employee_Lookups!$A$13:$A$17,0)),3) -> 0.999 | AB82: =YEAR(J82) -> 2019 | AC82: =IF(ISBLANK(L82),"",YEAR(L82)) -> 2020 | AD82: =ROUND((IF(ISBLANK(L82),Employee_Lookups!$O$14,L82)-J82)/365.25,2) -> 0.62 | AE82: =IF(AD82<1,"< 1 Yr (New)",IF(AD82<3,"1 - 3 Yrs",IF(AD82<5,"3 - 5 Yrs","5+ Yrs"))) -> < 1 Yr (New) | AF82: =IF(K82<>"Active","Exited",IF(AND(Q82="Yes",OR(P82>=4,AA82<0.95)),"High Risk",IF(OR(Q82="Yes",AND(NOT(ISBLANK(P82)),P82<=2)),"Moderate Risk","Low Risk"))) -> Exited
A83: EMP-11001 | B83: Riya Patil | C83: DEP-SAL | D83: Enterprise Sales | E83: SAL-L2 | F83: L2 | G83: Account Executive | H83: Bengaluru | I83: Hybrid | J83: 43803 | K83: Active | M83: N/A - Active | N83: External Agency | O83: 1213000 | P83: 2 | Q83: No | R83: 41 | S83: MGR-202 | T83: =VALUE(MID(A83,5,5)) -> 11001 | U83: =LEFT(E83,3) -> SAL | V83: =RIGHT(E83,2) -> L2 | W83: =PROPER(TRIM(VLOOKUP(S83,Employee_Lookups!$I$4:$M$19,2,FALSE()))) -> Priya Sharma | X83: =VLOOKUP(C83,Employee_Lookups!$A$4:$G$9,4,FALSE()) -> CC-202 | Y83: =INDEX(Employee_Lookups!$C$13:$C$17,MATCH(F83,Employee_Lookups!$A$13:$A$17,0)) -> Band B (Mid) | Z83: =_xlfn.XLOOKUP(F83,Employee_Lookups!$A$13:$A$17,Employee_Lookups!$E$13:$E$17,0) -> 1100000 | AA83: =ROUND(O83/INDEX(Employee_Lookups!$E$13:$E$17,MATCH(F83,Employee_Lookups!$A$13:$A$17,0)),3) -> 1.103 | AB83: =YEAR(J83) -> 2019 | AC83: =IF(ISBLANK(L83),"",YEAR(L83)) | AD83: =ROUND((IF(ISBLANK(L83),Employee_Lookups!$O$14,L83)-J83)/365.25,2) -> 6.08 | AE83: =IF(AD83<1,"< 1 Yr (New)",IF(AD83<3,"1 - 3 Yrs",IF(AD83<5,"3 - 5 Yrs","5+ Yrs"))) -> 5+ Yrs | AF83: =IF(K83<>"Active","Exited",IF(AND(Q83="Yes",OR(P83>=4,AA83<0.95)),"High Risk",IF(OR(Q83="Yes",AND(NOT(ISBLANK(P83)),P83<=2)),"Moderate Risk","Low Risk"))) -> Moderate Risk
A84: EMP-10979 | B84: Gaurav Sengupta | C84: DEP-ENG | D84: Engineering & Product | E84: ENG-L3 | F84: L3 | G84: Engineering Manager | H84: Hyderabad | I84: On-Site | J84: 43806 | K84: Voluntary Exit | L84: 44332 | M84: Compensation | N84: LinkedIn Sourcing | O84: 1374000 | P84: 4 | Q84: No | R84: 13 | S84: MGR-101 | T84: =VALUE(MID(A84,5,5)) -> 10979 | U84: =LEFT(E84,3) -> ENG | V84: =RIGHT(E84,2) -> L3 | W84: =PROPER(TRIM(VLOOKUP(S84,Employee_Lookups!$I$4:$M$19,2,FALSE()))) -> Aarav Deshmukh | X84: =VLOOKUP(C84,Employee_Lookups!$A$4:$G$9,4,FALSE()) -> CC-101 | Y84: =INDEX(Employee_Lookups!$C$13:$C$17,MATCH(F84,Employee_Lookups!$A$13:$A$17,0)) -> Band C (Senior) | Z84: =_xlfn.XLOOKUP(F84,Employee_Lookups!$A$13:$A$17,Employee_Lookups!$E$13:$E$17,0) -> 1725000 | AA84: =ROUND(O84/INDEX(Employee_Lookups!$E$13:$E$17,MATCH(F84,Employee_Lookups!$A$13:$A$17,0)),3) -> 0.797 | AB84: =YEAR(J84) -> 2019 | AC84: =IF(ISBLANK(L84),"",YEAR(L84)) -> 2021 | AD84: =ROUND((IF(ISBLANK(L84),Employee_Lookups!$O$14,L84)-J84)/365.25,2) -> 1.44 | AE84: =IF(AD84<1,"< 1 Yr (New)",IF(AD84<3,"1 - 3 Yrs",IF(AD84<5,"3 - 5 Yrs","5+ Yrs"))) -> 1 - 3 Yrs | AF84: =IF(K84<>"Active","Exited",IF(AND(Q84="Yes",OR(P84>=4,AA84<0.95)),"High Risk",IF(OR(Q84="Yes",AND(NOT(ISBLANK(P84)),P84<=2)),"Moderate Risk","Low Risk"))) -> Exited
A85: EMP-10967 | B85: Saanvi Bhatt | C85: DEP-MKT | D85: Growth Marketing | E85: MKT-L3 | F85: L3 | G85: Product Marketing Manager | H85: Bengaluru | I85: Hybrid | J85: 43811 | K85: Active | M85: N/A - Active | N85: External Agency | O85: 1936000 | P85: 5 | Q85: No | R85: 13 | S85: MGR-602 | T85: =VALUE(MID(A85,5,5)) -> 10967 | U85: =LEFT(E85,3) -> MKT | V85: =RIGHT(E85,2) -> L3 | W85: =PROPER(TRIM(VLOOKUP(S85,Employee_Lookups!$I$4:$M$19,2,FALSE()))) -> Arjun Sengupta | X85: =VLOOKUP(C85,Employee_Lookups!$A$4:$G$9,4,FALSE()) -> CC-606 | Y85: =INDEX(Employee_Lookups!$C$13:$C$17,MATCH(F85,Employee_Lookups!$A$13:$A$17,0)) -> Band C (Senior) | Z85: =_xlfn.XLOOKUP(F85,Employee_Lookups!$A$13:$A$17,Employee_Lookups!$E$13:$E$17,0) -> 1725000 | AA85: =ROUND(O85/INDEX(Employee_Lookups!$E$13:$E$17,MATCH(F85,Employee_Lookups!$A$13:$A$17,0)),3) -> 1.122 | AB85: =YEAR(J85) -> 2019 | AC85: =IF(ISBLANK(L85),"",YEAR(L85)) | AD85: =ROUND((IF(ISBLANK(L85),Employee_Lookups!$O$14,L85)-J85)/365.25,2) -> 6.05 | AE85: =IF(AD85<1,"< 1 Yr (New)",IF(AD85<3,"1 - 3 Yrs",IF(AD85<5,"3 - 5 Yrs","5+ Yrs"))) -> 5+ Yrs | AF85: =IF(K85<>"Active","Exited",IF(AND(Q85="Yes",OR(P85>=4,AA85<0.95)),"High Risk",IF(OR(Q85="Yes",AND(NOT(ISBLANK(P85)),P85<=2)),"Moderate Risk","Low Risk"))) -> Low Risk
A86: EMP-11244 | B86: Kavya Verma | C86: DEP-ENG | D86: Engineering & Product | E86: ENG-L2 | F86: L2 | G86: Software Engineer II | H86: Bengaluru | I86: Hybrid | J86: 43814 | K86: Active | M86: N/A - Active | N86: Employee Referral | O86: 1176000 | P86: 3 | Q86: No | R86: 36 | S86: MGR-101 | T86: =VALUE(MID(A86,5,5)) -> 11244 | U86: =LEFT(E86,3) -> ENG | V86: =RIGHT(E86,2) -> L2 | W86: =PROPER(TRIM(VLOOKUP(S86,Employee_Lookups!$I$4:$M$19,2,FALSE()))) -> Aarav Deshmukh | X86: =VLOOKUP(C86,Employee_Lookups!$A$4:$G$9,4,FALSE()) -> CC-101 | Y86: =INDEX(Employee_Lookups!$C$13:$C$17,MATCH(F86,Employee_Lookups!$A$13:$A$17,0)) -> Band B (Mid) | Z86: =_xlfn.XLOOKUP(F86,Employee_Lookups!$A$13:$A$17,Employee_Lookups!$E$13:$E$17,0) -> 1100000 | AA86: =ROUND(O86/INDEX(Employee_Lookups!$E$13:$E$17,MATCH(F86,Employee_Lookups!$A$13:$A$17,0)),3) -> 1.069 | AB86: =YEAR(J86) -> 2019 | AC86: =IF(ISBLANK(L86),"",YEAR(L86)) | AD86: =ROUND((IF(ISBLANK(L86),Employee_Lookups!$O$14,L86)-J86)/365.25,2) -> 6.05 | AE86: =IF(AD86<1,"< 1 Yr (New)",IF(AD86<3,"1 - 3 Yrs",IF(AD86<5,"3 - 5 Yrs","5+ Yrs"))) -> 5+ Yrs | AF86: =IF(K86<>"Active","Exited",IF(AND(Q86="Yes",OR(P86>=4,AA86<0.95)),"High Risk",IF(OR(Q86="Yes",AND(NOT(ISBLANK(P86)),P86<=2)),"Moderate Risk","Low Risk"))) -> Low Risk
A87: EMP-10292 | B87: Shruti Reddy | C87: DEP-ENG | D87: Engineering & Product | E87: ENG-L4 | F87: L4 | G87: Director of Engineering | H87: Hyderabad | I87: On-Site | J87: 43825 | K87: Active | M87: N/A - Active | N87: External Agency | O87: 2282000 | P87: 5 | Q87: No | R87: 30 | S87: MGR-102 | T87: =VALUE(MID(A87,5,5)) -> 10292 | U87: =LEFT(E87,3) -> ENG | V87: =RIGHT(E87,2) -> L4 | W87: =PROPER(TRIM(VLOOKUP(S87,Employee_Lookups!$I$4:$M$19,2,FALSE()))) -> Neha Kulkarni | X87: =VLOOKUP(C87,Employee_Lookups!$A$4:$G$9,4,FALSE()) -> CC-101 | Y87: =INDEX(Employee_Lookups!$C$13:$C$17,MATCH(F87,Employee_Lookups!$A$13:$A$17,0)) -> Band D (Leadership) | Z87: =_xlfn.XLOOKUP(F87,Employee_Lookups!$A$13:$A$17,Employee_Lookups!$E$13:$E$17,0) -> 2750000 | AA87: =ROUND(O87/INDEX(Employee_Lookups!$E$13:$E$17,MATCH(F87,Employee_Lookups!$A$13:$A$17,0)),3) -> 0.83 | AB87: =YEAR(J87) -> 2019 | AC87: =IF(ISBLANK(L87),"",YEAR(L87)) | AD87: =ROUND((IF(ISBLANK(L87),Employee_Lookups!$O$14,L87)-J87)/365.25,2) -> 6.02 | AE87: =IF(AD87<1,"< 1 Yr (New)",IF(AD87<3,"1 - 3 Yrs",IF(AD87<5,"3 - 5 Yrs","5+ Yrs"))) -> 5+ Yrs | AF87: =IF(K87<>"Active","Exited",IF(AND(Q87="Yes",OR(P87>=4,AA87<0.95)),"High Risk",IF(OR(Q87="Yes",AND(NOT(ISBLANK(P87)),P87<=2)),"Moderate Risk","Low Risk"))) -> Low Risk
A88: EMP-11136 | B88: Sneha Sharma | C88: DEP-FIN | D88: Finance & Strategy | E88: FIN-L2 | F88: L2 | G88: Senior FP&A Analyst | H88: Hyderabad | I88: On-Site | J88: 43825 | K88: Active | M88: N/A - Active | N88: Company Career Portal | O88: 1218000 | P88: 3 | Q88: Yes | R88: 34 | S88: MGR-401 | T88: =VALUE(MID(A88,5,5)) -> 11136 | U88: =LEFT(E88,3) -> FIN | V88: =RIGHT(E88,2) -> L2 | W88: =PROPER(TRIM(VLOOKUP(S88,Employee_Lookups!$I$4:$M$19,2,FALSE()))) -> Rajeshwari Rao | X88: =VLOOKUP(C88,Employee_Lookups!$A$4:$G$9,4,FALSE()) -> CC-404 | Y88: =INDEX(Employee_Lookups!$C$13:$C$17,MATCH(F88,Employee_Lookups!$A$13:$A$17,0)) -> Band B (Mid) | Z88: =_xlfn.XLOOKUP(F88,Employee_Lookups!$A$13:$A$17,Employee_Lookups!$E$13:$E$17,0) -> 1100000 | AA88: =ROUND(O88/INDEX(Employee_Lookups!$E$13:$E$17,MATCH(F88,Employee_Lookups!$A$13:$A$17,0)),3) -> 1.107 | AB88: =YEAR(J88) -> 2019 | AC88: =IF(ISBLANK(L88),"",YEAR(L88)) | AD88: =ROUND((IF(ISBLANK(L88),Employee_Lookups!$O$14,L88)-J88)/365.25,2) -> 6.02 | AE88: =IF(AD88<1,"< 1 Yr (New)",IF(AD88<3,"1 - 3 Yrs",IF(AD88<5,"3 - 5 Yrs","5+ Yrs"))) -> 5+ Yrs | AF88: =IF(K88<>"Active","Exited",IF(AND(Q88="Yes",OR(P88>=4,AA88<0.95)),"High Risk",IF(OR(Q88="Yes",AND(NOT(ISBLANK(P88)),P88<=2)),"Moderate Risk","Low Risk"))) -> Moderate Risk
A89: EMP-10864 | B89: Nikhil Reddy | C89: DEP-OPS | D89: Customer Operations | E89: OPS-L4 | F89: L4 | G89: Director of Operations | H89: Mumbai | I89: On-Site | J89: 43832 | K89: Active | M89: N/A - Active | N89: Employee Referral | O89: 2957000 | P89: 3 | Q89: Yes | R89: 31 | S89: MGR-302 | T89: =VALUE(MID(A89,5,5)) -> 10864 | U89: =LEFT(E89,3) -> OPS | V89: =RIGHT(E89,2) -> L4 | W89: =PROPER(TRIM(VLOOKUP(S89,Employee_Lookups!$I$4:$M$19,2,FALSE()))) -> Deepak Patil | X89: =VLOOKUP(C89,Employee_Lookups!$A$4:$G$9,4,FALSE()) -> CC-303 | Y89: =INDEX(Employee_Lookups!$C$13:$C$17,MATCH(F89,Employee_Lookups!$A$13:$A$17,0)) -> Band D (Leadership) | Z89: =_xlfn.XLOOKUP(F89,Employee_Lookups!$A$13:$A$17,Employee_Lookups!$E$13:$E$17,0) -> 2750000 | AA89: =ROUND(O89/INDEX(Employee_Lookups!$E$13:$E$17,MATCH(F89,Employee_Lookups!$A$13:$A$17,0)),3) -> 1.075 | AB89: =YEAR(J89) -> 2020 | AC89: =IF(ISBLANK(L89),"",YEAR(L89)) | AD89: =ROUND((IF(ISBLANK(L89),Employee_Lookups!$O$14,L89)-J89)/365.25,2) -> 6 | AE89: =IF(AD89<1,"< 1 Yr (New)",IF(AD89<3,"1 - 3 Yrs",IF(AD89<5,"3 - 5 Yrs","5+ Yrs"))) -> 5+ Yrs | AF89: =IF(K89<>"Active","Exited",IF(AND(Q89="Yes",OR(P89>=4,AA89<0.95)),"High Risk",IF(OR(Q89="Yes",AND(NOT(ISBLANK(P89)),P89<=2)),"Moderate Risk","Low Risk"))) -> Moderate Risk
A90: EMP-10543 | B90: Ishaan Chatterjee | C90: DEP-OPS | D90: Customer Operations | E90: OPS-L1 | F90: L1 | G90: Operations Coordinator | H90: Mumbai | I90: On-Site | J90: 43838 | K90: Voluntary Exit | L90: 43978 | M90: Work-Life Balance | N90: LinkedIn Sourcing | O90: 620000 | P90: 4 | Q90: No | R90: 38 | S90: MGR-302 | T90: =VALUE(MID(A90,5,5)) -> 10543 | U90: =LEFT(E90,3) -> OPS | V90: =RIGHT(E90,2) -> L1 | W90: =PROPER(TRIM(VLOOKUP(S90,Employee_Lookups!$I$4:$M$19,2,FALSE()))) -> Deepak Patil | X90: =VLOOKUP(C90,Employee_Lookups!$A$4:$G$9,4,FALSE()) -> CC-303 | Y90: =INDEX(Employee_Lookups!$C$13:$C$17,MATCH(F90,Employee_Lookups!$A$13:$A$17,0)) -> Band A (Entry) | Z90: =_xlfn.XLOOKUP(F90,Employee_Lookups!$A$13:$A$17,Employee_Lookups!$E$13:$E$17,0) -> 700000 | AA90: =ROUND(O90/INDEX(Employee_Lookups!$E$13:$E$17,MATCH(F90,Employee_Lookups!$A$13:$A$17,0)),3) -> 0.886 | AB90: =YEAR(J90) -> 2020 | AC90: =IF(ISBLANK(L90),"",YEAR(L90)) -> 2020 | AD90: =ROUND((IF(ISBLANK(L90),Employee_Lookups!$O$14,L90)-J90)/365.25,2) -> 0.38 | AE90: =IF(AD90<1,"< 1 Yr (New)",IF(AD90<3,"1 - 3 Yrs",IF(AD90<5,"3 - 5 Yrs","5+ Yrs"))) -> < 1 Yr (New) | AF90: =IF(K90<>"Active","Exited",IF(AND(Q90="Yes",OR(P90>=4,AA90<0.95)),"High Risk",IF(OR(Q90="Yes",AND(NOT(ISBLANK(P90)),P90<=2)),"Moderate Risk","Low Risk"))) -> Exited
A91: EMP-11312 | B91: Vihaan Chatterjee | C91: DEP-ENG | D91: Engineering & Product | E91: ENG-L3 | F91: L3 | G91: Engineering Manager | H91: Hyderabad | I91: On-Site | J91: 43839 | K91: Voluntary Exit | L91: 44070 | M91: Work-Life Balance | N91: External Agency | O91: 1443000 | P91: 4 | Q91: No | R91: 24 | S91: MGR-104 | T91: =VALUE(MID(A91,5,5)) -> 11312 | U91: =LEFT(E91,3) -> ENG | V91: =RIGHT(E91,2) -> L3 | W91: =PROPER(TRIM(VLOOKUP(S91,Employee_Lookups!$I$4:$M$19,2,FALSE()))) -> Siddharth Nair | X91: =VLOOKUP(C91,Employee_Lookups!$A$4:$G$9,4,FALSE()) -> CC-101 | Y91: =INDEX(Employee_Lookups!$C$13:$C$17,MATCH(F91,Employee_Lookups!$A$13:$A$17,0)) -> Band C (Senior) | Z91: =_xlfn.XLOOKUP(F91,Employee_Lookups!$A$13:$A$17,Employee_Lookups!$E$13:$E$17,0) -> 1725000 | AA91: =ROUND(O91/INDEX(Employee_Lookups!$E$13:$E$17,MATCH(F91,Employee_Lookups!$A$13:$A$17,0)),3) -> 0.837 | AB91: =YEAR(J91) -> 2020 | AC91: =IF(ISBLANK(L91),"",YEAR(L91)) -> 2020 | AD91: =ROUND((IF(ISBLANK(L91),Employee_Lookups!$O$14,L91)-J91)/365.25,2) -> 0.63 | AE91: =IF(AD91<1,"< 1 Yr (New)",IF(AD91<3,"1 - 3 Yrs",IF(AD91<5,"3 - 5 Yrs","5+ Yrs"))) -> < 1 Yr (New) | AF91: =IF(K91<>"Active","Exited",IF(AND(Q91="Yes",OR(P91>=4,AA91<0.95)),"High Risk",IF(OR(Q91="Yes",AND(NOT(ISBLANK(P91)),P91<=2)),"Moderate Risk","Low Risk"))) -> Exited
A92: EMP-10054 | B92: Riya Malhotra | C92: DEP-OPS | D92: Customer Operations | E92: OPS-L3 | F92: L3 | G92: Operations Lead | H92: Hyderabad | I92: On-Site | J92: 43840 | K92: Voluntary Exit | L92: 45784 | M92: Career Growth | N92: External Agency | O92: 1672000 | P92: 3 | Q92: Yes | R92: 21 | S92: MGR-303 | T92: =VALUE(MID(A92,5,5)) -> 10054 | U92: =LEFT(E92,3) -> OPS | V92: =RIGHT(E92,2) -> L3 | W92: =PROPER(TRIM(VLOOKUP(S92,Employee_Lookups!$I$4:$M$19,2,FALSE()))) -> Meera Krishnan | X92: =VLOOKUP(C92,Employee_Lookups!$A$4:$G$9,4,FALSE()) -> CC-303 | Y92: =INDEX(Employee_Lookups!$C$13:$C$17,MATCH(F92,Employee_Lookups!$A$13:$A$17,0)) -> Band C (Senior) | Z92: =_xlfn.XLOOKUP(F92,Employee_Lookups!$A$13:$A$17,Employee_Lookups!$E$13:$E$17,0) -> 1725000 | AA92: =ROUND(O92/INDEX(Employee_Lookups!$E$13:$E$17,MATCH(F92,Employee_Lookups!$A$13:$A$17,0)),3) -> 0.969 | AB92: =YEAR(J92) -> 2020 | AC92: =IF(ISBLANK(L92),"",YEAR(L92)) -> 2025 | AD92: =ROUND((IF(ISBLANK(L92),Employee_Lookups!$O$14,L92)-J92)/365.25,2) -> 5.32 | AE92: =IF(AD92<1,"< 1 Yr (New)",IF(AD92<3,"1 - 3 Yrs",IF(AD92<5,"3 - 5 Yrs","5+ Yrs"))) -> 5+ Yrs | AF92: =IF(K92<>"Active","Exited",IF(AND(Q92="Yes",OR(P92>=4,AA92<0.95)),"High Risk",IF(OR(Q92="Yes",AND(NOT(ISBLANK(P92)),P92<=2)),"Moderate Risk","Low Risk"))) -> Exited
A93: EMP-10953 | B93: Saanvi Bhatt | C93: DEP-MKT | D93: Growth Marketing | E93: MKT-L1 | F93: L1 | G93: Marketing Associate | H93: Bengaluru | I93: Hybrid | J93: 43842 | K93: Voluntary Exit | L93: 45944 | M93: Compensation | N93: LinkedIn Sourcing | O93: 657000 | P93: 5 | Q93: No | R93: 29 | S93: MGR-601 | T93: =VALUE(MID(A93,5,5)) -> 10953 | U93: =LEFT(E93,3) -> MKT | V93: =RIGHT(E93,2) -> L1 | W93: =PROPER(TRIM(VLOOKUP(S93,Employee_Lookups!$I$4:$M$19,2,FALSE()))) -> Tanvi Chitnis | X93: =VLOOKUP(C93,Employee_Lookups!$A$4:$G$9,4,FALSE()) -> CC-606 | Y93: =INDEX(Employee_Lookups!$C$13:$C$17,MATCH(F93,Employee_Lookups!$A$13:$A$17,0)) -> Band A (Entry) | Z93: =_xlfn.XLOOKUP(F93,Employee_Lookups!$A$13:$A$17,Employee_Lookups!$E$13:$E$17,0) -> 700000 | AA93: =ROUND(O93/INDEX(Employee_Lookups!$E$13:$E$17,MATCH(F93,Employee_Lookups!$A$13:$A$17,0)),3) -> 0.939 | AB93: =YEAR(J93) -> 2020 | AC93: =IF(ISBLANK(L93),"",YEAR(L93)) -> 2025 | AD93: =ROUND((IF(ISBLANK(L93),Employee_Lookups!$O$14,L93)-J93)/365.25,2) -> 5.75 | AE93: =IF(AD93<1,"< 1 Yr (New)",IF(AD93<3,"1 - 3 Yrs",IF(AD93<5,"3 - 5 Yrs","5+ Yrs"))) -> 5+ Yrs | AF93: =IF(K93<>"Active","Exited",IF(AND(Q93="Yes",OR(P93>=4,AA93<0.95)),"High Risk",IF(OR(Q93="Yes",AND(NOT(ISBLANK(P93)),P93<=2)),"Moderate Risk","Low Risk"))) -> Exited
A94: EMP-10757 | B94: Aarav Deshmukh | C94: DEP-OPS | D94: Customer Operations | E94: OPS-L1 | F94: L1 | G94: Operations Coordinator | H94: Bengaluru | I94: Hybrid | J94: 43844 | K94: Involuntary Exit | L94: 44024 | M94: Performance / Restructuring | N94: LinkedIn Sourcing | O94: 581000 | P94: 2 | Q94: Yes | R94: 19 | S94: MGR-301 | T94: =VALUE(MID(A94,5,5)) -> 10757 | U94: =LEFT(E94,3) -> OPS | V94: =RIGHT(E94,2) -> L1 | W94: =PROPER(TRIM(VLOOKUP(S94,Employee_Lookups!$I$4:$M$19,2,FALSE()))) -> Ananya Iyer | X94: =VLOOKUP(C94,Employee_Lookups!$A$4:$G$9,4,FALSE()) -> CC-303 | Y94: =INDEX(Employee_Lookups!$C$13:$C$17,MATCH(F94,Employee_Lookups!$A$13:$A$17,0)) -> Band A (Entry) | Z94: =_xlfn.XLOOKUP(F94,Employee_Lookups!$A$13:$A$17,Employee_Lookups!$E$13:$E$17,0) -> 700000 | AA94: =ROUND(O94/INDEX(Employee_Lookups!$E$13:$E$17,MATCH(F94,Employee_Lookups!$A$13:$A$17,0)),3) -> 0.83 | AB94: =YEAR(J94) -> 2020 | AC94: =IF(ISBLANK(L94),"",YEAR(L94)) -> 2020 | AD94: =ROUND((IF(ISBLANK(L94),Employee_Lookups!$O$14,L94)-J94)/365.25,2) -> 0.49 | AE94: =IF(AD94<1,"< 1 Yr (New)",IF(AD94<3,"1 - 3 Yrs",IF(AD94<5,"3 - 5 Yrs","5+ Yrs"))) -> < 1 Yr (New) | AF94: =IF(K94<>"Active","Exited",IF(AND(Q94="Yes",OR(P94>=4,AA94<0.95)),"High Risk",IF(OR(Q94="Yes",AND(NOT(ISBLANK(P94)),P94<=2)),"Moderate Risk","Low Risk"))) -> Exited
A95: EMP-11351 | B95: Vihaan Chatterjee | C95: DEP-SAL | D95: Enterprise Sales | E95: SAL-L3 | F95: L3 | G95: Regional Sales Manager | H95: Mumbai | I95: On-Site | J95: 43844 | K95: Involuntary Exit | L95: 44024 | M95: Performance / Restructuring | N95: Employee Referral | O95: 1976000 | P95: 3 | Q95: Yes | R95: 32 | S95: MGR-202 | T95: =VALUE(MID(A95,5,5)) -> 11351 | U95: =LEFT(E95,3) -> SAL | V95: =RIGHT(E95,2) -> L3 | W95: =PROPER(TRIM(VLOOKUP(S95,Employee_Lookups!$I$4:$M$19,2,FALSE()))) -> Priya Sharma | X95: =VLOOKUP(C95,Employee_Lookups!$A$4:$G$9,4,FALSE()) -> CC-202 | Y95: =INDEX(Employee_Lookups!$C$13:$C$17,MATCH(F95,Employee_Lookups!$A$13:$A$17,0)) -> Band C (Senior) | Z95: =_xlfn.XLOOKUP(F95,Employee_Lookups!$A$13:$A$17,Employee_Lookups!$E$13:$E$17,0) -> 1725000 | AA95: =ROUND(O95/INDEX(Employee_Lookups!$E$13:$E$17,MATCH(F95,Employee_Lookups!$A$13:$A$17,0)),3) -> 1.146 | AB95: =YEAR(J95) -> 2020 | AC95: =IF(ISBLANK(L95),"",YEAR(L95)) -> 2020 | AD95: =ROUND((IF(ISBLANK(L95),Employee_Lookups!$O$14,L95)-J95)/365.25,2) -> 0.49 | AE95: =IF(AD95<1,"< 1 Yr (New)",IF(AD95<3,"1 - 3 Yrs",IF(AD95<5,"3 - 5 Yrs","5+ Yrs"))) -> < 1 Yr (New) | AF95: =IF(K95<>"Active","Exited",IF(AND(Q95="Yes",OR(P95>=4,AA95<0.95)),"High Risk",IF(OR(Q95="Yes",AND(NOT(ISBLANK(P95)),P95<=2)),"Moderate Risk","Low Risk"))) -> Exited
A96: EMP-10328 | B96: Gaurav Sharma | C96: DEP-FIN | D96: Finance & Strategy | E96: FIN-L1 | F96: L1 | G96: Financial Analyst | H96: Mumbai | I96: On-Site | J96: 43846 | K96: Active | M96: N/A - Active | N96: Company Career Portal | O96: 675000 | P96: 3 | Q96: Yes | R96: 39 | S96: MGR-402 | T96: =VALUE(MID(A96,5,5)) -> 10328 | U96: =LEFT(E96,3) -> FIN | V96: =RIGHT(E96,2) -> L1 | W96: =PROPER(TRIM(VLOOKUP(S96,Employee_Lookups!$I$4:$M$19,2,FALSE()))) -> Aditya Gokhale | X96: =VLOOKUP(C96,Employee_Lookups!$A$4:$G$9,4,FALSE()) -> CC-404 | Y96: =INDEX(Employee_Lookups!$C$13:$C$17,MATCH(F96,Employee_Lookups!$A$13:$A$17,0)) -> Band A (Entry) | Z96: =_xlfn.XLOOKUP(F96,Employee_Lookups!$A$13:$A$17,Employee_Lookups!$E$13:$E$17,0) -> 700000 | AA96: =ROUND(O96/INDEX(Employee_Lookups!$E$13:$E$17,MATCH(F96,Employee_Lookups!$A$13:$A$17,0)),3) -> 0.964 | AB96: =YEAR(J96) -> 2020 | AC96: =IF(ISBLANK(L96),"",YEAR(L96)) | AD96: =ROUND((IF(ISBLANK(L96),Employee_Lookups!$O$14,L96)-J96)/365.25,2) -> 5.96 | AE96: =IF(AD96<1,"< 1 Yr (New)",IF(AD96<3,"1 - 3 Yrs",IF(AD96<5,"3 - 5 Yrs","5+ Yrs"))) -> 5+ Yrs | AF96: =IF(K96<>"Active","Exited",IF(AND(Q96="Yes",OR(P96>=4,AA96<0.95)),"High Risk",IF(OR(Q96="Yes",AND(NOT(ISBLANK(P96)),P96<=2)),"Moderate Risk","Low Risk"))) -> Moderate Risk
A97: EMP-10935 | B97: Vihaan Bhatt | C97: DEP-MKT | D97: Growth Marketing | E97: MKT-L2 | F97: L2 | G97: Growth Specialist | H97: Hyderabad | I97: On-Site | J97: 43847 | K97: Voluntary Exit | L97: 44924 | M97: Career Growth | N97: External Agency | O97: 1062000 | P97: 3 | Q97: Yes | R97: 35 | S97: MGR-601 | T97: =VALUE(MID(A97,5,5)) -> 10935 | U97: =LEFT(E97,3) -> MKT | V97: =RIGHT(E97,2) -> L2 | W97: =PROPER(TRIM(VLOOKUP(S97,Employee_Lookups!$I$4:$M$19,2,FALSE()))) -> Tanvi Chitnis | X97: =VLOOKUP(C97,Employee_Lookups!$A$4:$G$9,4,FALSE()) -> CC-606 | Y97: =INDEX(Employee_Lookups!$C$13:$C$17,MATCH(F97,Employee_Lookups!$A$13:$A$17,0)) -> Band B (Mid) | Z97: =_xlfn.XLOOKUP(F97,Employee_Lookups!$A$13:$A$17,Employee_Lookups!$E$13:$E$17,0) -> 1100000 | AA97: =ROUND(O97/INDEX(Employee_Lookups!$E$13:$E$17,MATCH(F97,Employee_Lookups!$A$13:$A$17,0)),3) -> 0.965 | AB97: =YEAR(J97) -> 2020 | AC97: =IF(ISBLANK(L97),"",YEAR(L97)) -> 2022 | AD97: =ROUND((IF(ISBLANK(L97),Employee_Lookups!$O$14,L97)-J97)/365.25,2) -> 2.95 | AE97: =IF(AD97<1,"< 1 Yr (New)",IF(AD97<3,"1 - 3 Yrs",IF(AD97<5,"3 - 5 Yrs","5+ Yrs"))) -> 1 - 3 Yrs | AF97: =IF(K97<>"Active","Exited",IF(AND(Q97="Yes",OR(P97>=4,AA97<0.95)),"High Risk",IF(OR(Q97="Yes",AND(NOT(ISBLANK(P97)),P97<=2)),"Moderate Risk","Low Risk"))) -> Exited
A98: EMP-10758 | B98: Myra Iyer | C98: DEP-ENG | D98: Engineering & Product | E98: ENG-L1 | F98: L1 | G98: Software Engineer I | H98: Pune | I98: Hybrid | J98: 43850 | K98: Active | M98: N/A - Active | N98: Employee Referral | O98: 832000 | P98: 2 | Q98: Yes | R98: 11 | S98: MGR-101 | T98: =VALUE(MID(A98,5,5)) -> 10758 | U98: =LEFT(E98,3) -> ENG | V98: =RIGHT(E98,2) -> L1 | W98: =PROPER(TRIM(VLOOKUP(S98,Employee_Lookups!$I$4:$M$19,2,FALSE()))) -> Aarav Deshmukh | X98: =VLOOKUP(C98,Employee_Lookups!$A$4:$G$9,4,FALSE()) -> CC-101 | Y98: =INDEX(Employee_Lookups!$C$13:$C$17,MATCH(F98,Employee_Lookups!$A$13:$A$17,0)) -> Band A (Entry) | Z98: =_xlfn.XLOOKUP(F98,Employee_Lookups!$A$13:$A$17,Employee_Lookups!$E$13:$E$17,0) -> 700000 | AA98: =ROUND(O98/INDEX(Employee_Lookups!$E$13:$E$17,MATCH(F98,Employee_Lookups!$A$13:$A$17,0)),3) -> 1.189 | AB98: =YEAR(J98) -> 2020 | AC98: =IF(ISBLANK(L98),"",YEAR(L98)) | AD98: =ROUND((IF(ISBLANK(L98),Employee_Lookups!$O$14,L98)-J98)/365.25,2) -> 5.95 | AE98: =IF(AD98<1,"< 1 Yr (New)",IF(AD98<3,"1 - 3 Yrs",IF(AD98<5,"3 - 5 Yrs","5+ Yrs"))) -> 5+ Yrs | AF98: =IF(K98<>"Active","Exited",IF(AND(Q98="Yes",OR(P98>=4,AA98<0.95)),"High Risk",IF(OR(Q98="Yes",AND(NOT(ISBLANK(P98)),P98<=2)),"Moderate Risk","Low Risk"))) -> Moderate Risk
A99: EMP-10196 | B99: Ishaan Rao | C99: DEP-SAL | D99: Enterprise Sales | E99: SAL-L1 | F99: L1 | G99: Sales Development Rep | H99: Bengaluru | I99: Hybrid | J99: 43850 | K99: Involuntary Exit | L99: 45367 | M99: Performance / Restructuring | N99: LinkedIn Sourcing | O99: 721000 | P99: 3 | Q99: Yes | R99: 54 | S99: MGR-202 | T99: =VALUE(MID(A99,5,5)) -> 10196 | U99: =LEFT(E99,3) -> SAL | V99: =RIGHT(E99,2) -> L1 | W99: =PROPER(TRIM(VLOOKUP(S99,Employee_Lookups!$I$4:$M$19,2,FALSE()))) -> Priya Sharma | X99: =VLOOKUP(C99,Employee_Lookups!$A$4:$G$9,4,FALSE()) -> CC-202 | Y99: =INDEX(Employee_Lookups!$C$13:$C$17,MATCH(F99,Employee_Lookups!$A$13:$A$17,0)) -> Band A (Entry) | Z99: =_xlfn.XLOOKUP(F99,Employee_Lookups!$A$13:$A$17,Employee_Lookups!$E$13:$E$17,0) -> 700000 | AA99: =ROUND(O99/INDEX(Employee_Lookups!$E$13:$E$17,MATCH(F99,Employee_Lookups!$A$13:$A$17,0)),3) -> 1.03 | AB99: =YEAR(J99) -> 2020 | AC99: =IF(ISBLANK(L99),"",YEAR(L99)) -> 2024 | AD99: =ROUND((IF(ISBLANK(L99),Employee_Lookups!$O$14,L99)-J99)/365.25,2) -> 4.15 | AE99: =IF(AD99<1,"< 1 Yr (New)",IF(AD99<3,"1 - 3 Yrs",IF(AD99<5,"3 - 5 Yrs","5+ Yrs"))) -> 3 - 5 Yrs | AF99: =IF(K99<>"Active","Exited",IF(AND(Q99="Yes",OR(P99>=4,AA99<0.95)),"High Risk",IF(OR(Q99="Yes",AND(NOT(ISBLANK(P99)),P99<=2)),"Moderate Risk","Low Risk"))) -> Exited
A100: EMP-11032 | B100: Aditya Chatterjee | C100: DEP-ENG | D100: Engineering & Product | E100: ENG-L1 | F100: L1 | G100: Software Engineer I | H100: Remote-India | I100: Remote | J100: 43851 | K100: Active | M100: N/A - Active | N100: LinkedIn Sourcing | O100: 619000 | P100: 2 | Q100: Yes | R100: 11 | S100: MGR-102 | T100: =VALUE(MID(A100,5,5)) -> 11032 | U100: =LEFT(E100,3) -> ENG | V100: =RIGHT(E100,2) -> L1 | W100: =PROPER(TRIM(VLOOKUP(S100,Employee_Lookups!$I$4:$M$19,2,FALSE()))) -> Neha Kulkarni | X100: =VLOOKUP(C100,Employee_Lookups!$A$4:$G$9,4,FALSE()) -> CC-101 | Y100: =INDEX(Employee_Lookups!$C$13:$C$17,MATCH(F100,Employee_Lookups!$A$13:$A$17,0)) -> Band A (Entry) | Z100: =_xlfn.XLOOKUP(F100,Employee_Lookups!$A$13:$A$17,Employee_Lookups!$E$13:$E$17,0) -> 700000 | AA100: =ROUND(O100/INDEX(Employee_Lookups!$E$13:$E$17,MATCH(F100,Employee_Lookups!$A$13:$A$17,0)),3) -> 0.884 | AB100: =YEAR(J100) -> 2020 | AC100: =IF(ISBLANK(L100),"",YEAR(L100)) | AD100: =ROUND((IF(ISBLANK(L100),Employee_Lookups!$O$14,L100)-J100)/365.25,2) -> 5.94 | AE100: =IF(AD100<1,"< 1 Yr (New)",IF(AD100<3,"1 - 3 Yrs",IF(AD100<5,"3 - 5 Yrs","5+ Yrs"))) -> 5+ Yrs | AF100: =IF(K100<>"Active","Exited",IF(AND(Q100="Yes",OR(P100>=4,AA100<0.95)),"High Risk",IF(OR(Q100="Yes",AND(NOT(ISBLANK(P100)),P100<=2)),"Moderate Risk","Low Risk"))) -> High Risk
...

Sheet Employee_Lookups
A1: MASTER REFERENCE & LOOKUP TABLES (VLOOKUP, INDEX/MATCH, XLOOKUP, & Cleaning Mapping)
I2: Manager Directory (Demonstrating VLOOKUP + PROPER/TRIM) | O2: Dashboard Filter Lists & Parameters
A3: Dept_Code | B3: Standard_Department_Name | C3: Dept_Head | D3: Cost_Center | E3: Approved_HC_Target_2025 | F3: Annual_Dept_Budget_INR | G3: Target_Attrition_Ceiling | I3: Manager_ID | J3: Manager_Name_Raw | K3: Standard_Manager_Name | L3: Dept_Code | M3: Base_Location | O3: Department_Filter_List | P3: Year_Filter_List
A4: DEP-ENG | B4: Engineering & Product | C4: Vikramjit Sen | D4: CC-101 | E4: 380 | F4: 560000000 | G4: 0.1 | I4: MGR-101 | J4: aarav deshmukh | K4: Aarav Deshmukh | L4: DEP-ENG | M4: Bengaluru | O4: All Departments | P4: 2025
A5: DEP-SAL | B5: Enterprise Sales | C5: Meenakshi Iyer | D5: CC-202 | E5: 215 | F5: 295000000 | G5: 0.14 | I5: MGR-102 | J5: NEHA KULKARNI | K5: Neha Kulkarni | L5: DEP-ENG | M5: Pune | O5: Engineering & Product | P5: 2024
A6: DEP-OPS | B6: Customer Operations | C6: Rajeshwar Patil | D6: CC-303 | E6: 180 | F6: 195000000 | G6: 0.14 | I6: MGR-103 | J6: rohan verma | K6: Rohan Verma | L6: DEP-ENG | M6: Hyderabad | O6: Enterprise Sales | P6: 2023
A7: DEP-FIN | B7: Finance & Strategy | C7: Suhasini Kulkarni | D7: CC-404 | E7: 100 | F7: 148000000 | G7: 0.08 | I7: MGR-104 | J7: Siddharth Nair | K7: Siddharth Nair | L7: DEP-ENG | M7: Bengaluru | O7: Customer Operations | P7: 2022
A8: DEP-HR | B8: People & Talent | C8: Nandini Deshmukh | D8: CC-505 | E8: 95 | F8: 118000000 | G8: 0.09 | I8: MGR-201 | J8: vikramaditya joshi | K8: Vikramaditya Joshi | L8: DEP-SAL | M8: Mumbai | O8: Growth Marketing | P8: 2021
A9: DEP-MKT | B9: Growth Marketing | C9: Kabir Malhotra | D9: CC-606 | E9: 125 | F9: 168000000 | G9: 0.12 | I9: MGR-202 | J9: PRIYA SHARMA | K9: Priya Sharma | L9: DEP-SAL | M9: Bengaluru | O9: Finance & Strategy | P9: 2020
I10: MGR-203 | J10: karan malhotra | K10: Karan Malhotra | L10: DEP-SAL | M10: Hyderabad | O10: People & Talent | P10: 2019
A11: Job Level & Salary Band Reference Table | I11: MGR-301 | J11: ananya iyer | K11: Ananya Iyer | L11: DEP-OPS | M11: Pune
A12: Job_Level | B12: Level_Title_Category | C12: Salary_Band_Label | D12: Band_Min_INR | E12: Band_Midpoint_INR | F12: Band_Max_INR | G12: Standard_Training_Target_Hrs | I12: MGR-302 | J12: DEEPAK PATIL | K12: Deepak Patil | L12: DEP-OPS | M12: Hyderabad
A13: L1 | B13: Associate / Analyst | C13: Band A (Entry) | D13: 550000 | E13: 700000 | F13: 850000 | G13: 40 | I13: MGR-303 | J13: meera krishnan | K13: Meera Krishnan | L13: DEP-OPS | M13: Bengaluru | O13: Reporting_Cutoff_Date
A14: L2 | B14: Specialist / Sr. Analyst | C14: Band B (Mid) | D14: 850001 | E14: 1100000 | F14: 1350000 | G14: 36 | I14: MGR-401 | J14: rajeshwari rao | K14: Rajeshwari Rao | L14: DEP-FIN | M14: Mumbai | O14: 46022
A15: L3 | B15: Lead / Manager | C15: Band C (Senior) | D15: 1350001 | E15: 1725000 | F15: 2100000 | G15: 32 | I15: MGR-402 | J15: aditya gokhale | K15: Aditya Gokhale | L15: DEP-FIN | M15: Pune
A16: L4 | B16: Director / Principal | C16: Band D (Leadership) | D16: 2100001 | E16: 2750000 | F16: 3400000 | G16: 28 | I16: MGR-501 | J16: KAVITA MENON | K16: Kavita Menon | L16: DEP-HR | M16: Bengaluru
A17: L5 | B17: VP / Executive | C17: Band E (Executive) | D17: 3400001 | E17: 4300000 | F17: 5200000 | G17: 24 | I17: MGR-502 | J17: nikhil chatterjee | K17: Nikhil Chatterjee | L17: DEP-HR | M17: Pune
I18: MGR-601 | J18: tanvi chitnis | K18: Tanvi Chitnis | L18: DEP-MKT | M18: Bengaluru
A19: Recruitment Channel Cost & SLA Reference | I19: MGR-602 | J19: ARJUN SENGUPTA | K19: Arjun Sengupta | L19: DEP-MKT | M19: Mumbai
A20: Recruitment_Source | B20: Std_Cost_Per_Hire_INR | C20: Target_Time_To_Fill_Days
A21: Campus Recruitment | B21: 35000 | C21: 45
A22: Company Career Portal | B22: 22000 | C22: 30
A23: Employee Referral | B23: 42000 | C23: 28
A24: External Agency | B24: 145000 | C24: 25
A25: LinkedIn Sourcing | B25: 68000 | C25: 38

Sheet Raw_Data
A1: Employee_ID | B1: Full_Name | C1: Dept_Code | D1: Department | E1: Job_Level_Code | F1: Job_Level | G1: Job_Title | H1: Location | I1: Work_Mode | J1: Hire_Date | K1: Employment_Status | L1: Exit_Date | M1: Exit_Reason | N1: Recruitment_Source | O1: Annual_Salary_INR | P1: Performance_Rating | Q1: Overtime_Flag | R1: Training_Hours | S1: Manager_ID | T1: Duplicate_Record_Check
A2: EMP-10001 | B2: Ayaan deshmukh | C2: DEP-SAL | D2: Enterprise Sales | E2: SAL-L4 | F2: L4 | G2: Director of Enterprise Sales | H2: Hyderabad | I2: On-Site | J2: 2021-05-08 | K2: Active | M2: N/A - Active | N2: Campus Recruitment | O2: 3057000 | P2: 2 | Q2: Yes | R2: 40 | S2: MGR-203 | T2: =IF(COUNTIF($A$2:A2,A2)>1,"Duplicate","Unique") -> Unique
A3: EMP-10002 | B3: Yash Patil | C3: DEP-ENG | D3: Engineering & Product | E3: ENG-L4 | F3: L4 | G3: Director of Engineering | H3: Hyderabad | I3: On-Site | J3: 2021-01-01 | K3: Active | M3: N/A - Active | N3: Employee Referral | O3: 2402000 | P3: 3 | Q3: Yes | R3: 45 | S3: MGR-104 | T3: =IF(COUNTIF($A$2:A3,A3)>1,"Duplicate","Unique") -> Unique
A4: EMP-10003 | B4: Swati Iyer | C4: DEP-ENG | D4: Engineering & Product | E4: ENG-L2 | F4: L2 | G4: Software Engineer II | H4: Pune | I4: Hybrid | J4: 2023-04-15 | K4: Involuntary Exit | L4: 2025-05-08 | M4: Performance / Restructuring | N4: LinkedIn Sourcing | O4: 1255000 | P4: 2 | Q4: No | R4: 11 | S4: MGR-104 | T4: =IF(COUNTIF($A$2:A4,A4)>1,"Duplicate","Unique") -> Unique
A5: EMP-10004 | B5: Neha Gokhale | C5: DEP-FIN | D5: Finance & Strategy | E5: FIN-L1 | F5: L1 | G5: Financial Analyst | H5: Pune | I5: Hybrid | J5: 2019-03-07 | K5: Voluntary Exit | L5: 2019-10-04 | M5: Career Growth | N5: Campus Recruitment | O5: 651000 | P5: 3 | Q5: No | R5: 19 | S5: MGR-402 | T5: =IF(COUNTIF($A$2:A5,A5)>1,"Duplicate","Unique") -> Unique
A6: EMP-10005 | B6: Tejas Menon | C6: DEP-ENG | D6: Engineering & Product | E6: ENG-L4 | F6: L4 | G6: Director of Engineering | H6: Remote-India | I6: Remote | J6: 2022-12-15 | K6: Active | M6: N/A - Active | N6: External Agency | O6: 3365000 | P6: 2 | Q6: No | R6: 14 | S6: MGR-101 | T6: =IF(COUNTIF($A$2:A6,A6)>1,"Duplicate","Unique") -> Unique
A7: EMP-10006 | B7: Swati Rao | C7: DEP-ENG | D7: Engineering & Product | E7: ENG-L2 | F7: L2 | G7: Software Engineer II | H7: Bengaluru | I7: Hybrid | J7: 2021-10-07 | K7: Active | M7: N/A - Active | N7: Company Career Portal | O7: 873000 | P7: 4 | Q7: No | R7: 58 | S7: MGR-103 | T7: =IF(COUNTIF($A$2:A7,A7)>1,"Duplicate","Unique") -> Unique
A8: EMP-10007 | B8: Navya Patil | C8: DEP-ENG | D8: Engineering & Product | E8: ENG-L2 | F8: L2 | G8: Software Engineer II | H8: Pune | I8: Hybrid | J8: 2025-02-13 | K8: Active | M8: N/A - Active | N8: Employee Referral | O8: 1168000 | P8: 4 | Q8: Yes | R8: 44 | S8: MGR-102 | T8: =IF(COUNTIF($A$2:A8,A8)>1,"Duplicate","Unique") -> Unique
A9: EMP-10008 | B9: Pooja Chitnis | C9: DEP-ENG | D9: Engineering & Product | E9: ENG-L1 | F9: L1 | G9: Software Engineer I | H9: Bengaluru | I9: Hybrid | J9: 2022-11-09 | K9: Involuntary Exit | L9: 2025-12-16 | M9: Performance / Restructuring | N9: LinkedIn Sourcing | O9: 755000 | P9: 3 | Q9: No | R9: 38 | S9: MGR-102 | T9: =IF(COUNTIF($A$2:A9,A9)>1,"Duplicate","Unique") -> Unique
A10: EMP-10009 | B10: Kiara Verma | C10: DEP-SAL | D10: enterprise sales | E10: SAL-L1 | F10: L1 | G10: Sales Development Rep | H10: Pune | I10: Hybrid | J10: 2024-07-09 | K10: Active | M10: N/A - Active | N10: Employee Referral | O10: 742000 | P10: 2 | Q10: No | R10: 28 | S10: MGR-202 | T10: =IF(COUNTIF($A$2:A10,A10)>1,"Duplicate","Unique") -> Unique
A11: EMP-10010 | B11: Rohan Kulkarni | C11: DEP-FIN | D11: Finance & Strategy | E11: FIN-L3 | F11: L3 | G11: Finance Manager | H11: Bengaluru | I11: Hybrid | J11: 2020-01-26 | K11: Active | M11: N/A - Active | N11: LinkedIn Sourcing | O11: 1551000 | P11: 4 | Q11: No | R11: 46 | S11: MGR-401 | T11: =IF(COUNTIF($A$2:A11,A11)>1,"Duplicate","Unique") -> Unique
A12: EMP-10011 | B12: Omkar Gokhale | C12: DEP-OPS | D12: Customer Operations | E12: OPS-L1 | F12: L1 | G12: Operations Coordinator | H12: Bengaluru | I12: Hybrid | J12: 2022-11-16 | K12: Voluntary Exit | L12: 2023-04-26 | M12: Compensation | N12: LinkedIn Sourcing | O12: 824000 | P12: 4 | Q12: Yes | R12: 46 | S12: MGR-301 | T12: =IF(COUNTIF($A$2:A12,A12)>1,"Duplicate","Unique") -> Unique
A13: EMP-10012 | B13: Swati Bhatt | C13: DEP-ENG | D13: Engineering & Product | E13: ENG-L2 | F13: L2 | G13: Software Engineer II | H13: Hyderabad | I13: On-Site | J13: 2024-12-19 | K13: Active | M13: N/A - Active | N13: Campus Recruitment | O13: 1142000 | P13: 3 | Q13: No | R13: 39 | S13: MGR-103 | T13: =IF(COUNTIF($A$2:A13,A13)>1,"Duplicate","Unique") -> Unique
A14: EMP-10013 | B14: Krishna Sengupta | C14: DEP-OPS | D14: Customer Operations | E14: OPS-L2 | F14: L2 | G14: Customer Success Specialist | H14: Bengaluru | I14: Hybrid | J14: 2019-02-25 | K14: Active | M14: N/A - Active | N14: Employee Referral | O14: 905000 | P14: 3 | Q14: Yes | R14: 37 | S14: MGR-302 | T14: =IF(COUNTIF($A$2:A14,A14)>1,"Duplicate","Unique") -> Unique
A15: EMP-10014 | B15: Neha Shah | C15: DEP-MKT | D15: Growth Marketing | E15: MKT-L1 | F15: L1 | G15: Marketing Associate | H15: Pune | I15: Hybrid | J15: 2021-07-13 | K15: Involuntary Exit | L15: 2021-09-14 | M15: Performance / Restructuring | N15: External Agency | O15: 690000 | P15: 2 | Q15: No | R15: 4 | S15: MGR-601 | T15: =IF(COUNTIF($A$2:A15,A15)>1,"Duplicate","Unique") -> Unique
A16: EMP-10015 | B16: Ayaan bhatt | C16: DEP-ENG | D16: Engineering & Product | E16: ENG-L4 | F16: L4 | G16: Director of Engineering | H16: Hyderabad | I16: On-Site | J16: 2025-11-11 | K16: Active | M16: N/A - Active | N16: Campus Recruitment | O16: 2665000 | Q16: Yes | R16: 52 | S16: MGR-103 | T16: =IF(COUNTIF($A$2:A16,A16)>1,"Duplicate","Unique") -> Unique
A17: EMP-10016 | B17: Myra Sengupta | C17: DEP-MKT | D17: Growth Marketing | E17: MKT-L1 | F17: L1 | G17: Marketing Associate | H17: Bengaluru | I17: Hybrid | J17: 2022-09-04 | K17: Active | M17: N/A - Active | N17: LinkedIn Sourcing | O17: 640000 | P17: 4 | Q17: No | R17: 38 | S17: MGR-601 | T17: =IF(COUNTIF($A$2:A17,A17)>1,"Duplicate","Unique") -> Unique
A18: EMP-10017 | B18: Tejas Iyer | C18: DEP-HR | D18: People & Talent | E18: -HR-L1 | F18: L1 | G18: HR Coordinator | H18: Pune | I18: Hybrid | J18: 2021-06-25 | K18: Active | M18: N/A - Active | N18: LinkedIn Sourcing | O18: 836000 | P18: 2 | Q18: Yes | R18: 27 | S18: MGR-501 | T18: =IF(COUNTIF($A$2:A18,A18)>1,"Duplicate","Unique") -> Unique
A19: EMP-10018 | B19: AARAV SHAH | C19: DEP-SAL | D19: Enterprise Sales | E19: SAL-L2 | F19: L2 | G19: Account Executive | H19: Hyderabad | I19: On-Site | J19: 2025-08-01 | K19: Active | M19: N/A - Active | N19: LinkedIn Sourcing | O19: 1031000 | Q19: Yes | R19: 34 | S19: MGR-202 | T19: =IF(COUNTIF($A$2:A19,A19)>1,"Duplicate","Unique") -> Unique
A20: EMP-10019 | B20: Riya Nair | C20: DEP-ENG | D20: Engineering & Product | E20: ENG-L2 | F20: L2 | G20: Software Engineer II | H20: Bengaluru | I20: Hybrid | J20: 2019-04-19 | K20: Active | M20: N/A - Active | N20: LinkedIn Sourcing | O20: 893000 | P20: 3 | Q20: No | R20: 28 | S20: MGR-101 | T20: =IF(COUNTIF($A$2:A20,A20)>1,"Duplicate","Unique") -> Unique
A21: EMP-10020 | B21: Arjun Bhatt | C21: DEP-ENG | D21: Engineering & Product | E21: ENG-L4 | F21: L4 | G21: Director of Engineering | H21: Bengaluru | I21: Hybrid | J21: 2022-03-22 | K21: Active | M21: N/A - Active | N21: Employee Referral | O21: 2815000 | P21: 5 | Q21: No | R21: 36 | S21: MGR-102 | T21: =IF(COUNTIF($A$2:A21,A21)>1,"Duplicate","Unique") -> Unique
A22: EMP-10021 | B22: Tejas Kapoor | C22: DEP-ENG | D22: Engineering & Product | E22: ENG-L2 | F22: L2 | G22: Software Engineer II | H22: Hyderabad | I22: On-Site | J22: 2024-09-25 | K22: Active | M22: N/A - Active | N22: LinkedIn Sourcing | O22: 951000 | P22: 3 | Q22: No | R22: 52 | S22: MGR-102 | T22: =IF(COUNTIF($A$2:A22,A22)>1,"Duplicate","Unique") -> Unique
A23: EMP-10022 | B23: Pooja Reddy | C23: DEP-OPS | D23: Customer Operations | E23: OPS-L1 | F23: L1 | G23: Operations Coordinator | H23: Hyderabad | I23: On-Site | J23: 2021-08-04 | K23: Involuntary Exit | L23: 2024-12-31 | M23: Performance / Restructuring | N23: LinkedIn Sourcing | O23: 569000 | P23: 2 | Q23: Yes | R23: 38 | S23: MGR-303 | T23: =IF(COUNTIF($A$2:A23,A23)>1,"Duplicate","Unique") -> Unique
A24: EMP-10023 | B24: Aadhya Deshmukh | C24: DEP-OPS | D24: Customer Operations | E24: OPS-L1 | F24: L1 | G24: Operations Coordinator | H24: Pune | I24: Hybrid | J24: 2023-12-21 | K24: Involuntary Exit | L24: 2024-10-14 | M24: Performance / Restructuring | N24: LinkedIn Sourcing | O24: 570000 | P24: 2 | Q24: Yes | R24: 10 | S24: MGR-301 | T24: =IF(COUNTIF($A$2:A24,A24)>1,"Duplicate","Unique") -> Unique
A25: EMP-10024 | B25: Kiara Menon | C25: DEP-ENG | D25: Engineering & Prod | E25: ENG-L1 | F25: L1 | G25: Software Engineer I | H25: Bangalore | I25: Hybrid | J25: 2025-04-18 | K25: Active | M25: N/A - Active | N25: Company Career Portal | O25: 831000 | P25: 3 | Q25: Y | R25: 54 | S25: MGR-104 | T25: =IF(COUNTIF($A$2:A25,A25)>1,"Duplicate","Unique") -> Unique
A26: EMP-10025 | B26: Pranav Nair | C26: DEP-OPS | D26: Customer Operations | E26: OPS-L3 | F26: L3 | G26: Operations Lead | H26: Pune | I26: Hybrid | J26: 2021-07-07 | K26: Involuntary Exit | L26: 2021-09-07 | M26: Performance / Restructuring | N26: Campus Recruitment | O26: 1844000 | P26: 2 | Q26: Yes | R26: 4 | S26: MGR-302 | T26: =IF(COUNTIF($A$2:A26,A26)>1,"Duplicate","Unique") -> Unique
A27: EMP-10026 | B27: Reyansh Kulkarni | C27: DEP-FIN | D27: Finance & Strategy | E27: FIN-L3 | F27: L3 | G27: Finance Manager | H27: Mumbai | I27: On-Site | J27: 2023-12-11 | K27: Involuntary Exit | L27: 2024-06-11 | M27: Performance / Restructuring | N27: External Agency | O27: 1432000 | P27: 2 | Q27: No | R27: 36 | S27: MGR-402 | T27: =IF(COUNTIF($A$2:A27,A27)>1,"Duplicate","Unique") -> Unique
A28: EMP-10027 | B28: Neha Verma | C28: DEP-MKT | D28: Growth Marketing | E28: MKT-L2 | F28: L2 | G28: Growth Specialist | H28: Bengaluru | I28: Hybrid | J28: 2023-08-08 | K28: Active | M28: N/A - Active | N28: Employee Referral | O28: 888000 | P28: 1 | Q28: No | R28: 24 | S28: MGR-602 | T28: =IF(COUNTIF($A$2:A28,A28)>1,"Duplicate","Unique") -> Unique
A29: EMP-10028 | B29: Swati Joshi | C29: DEP-OPS | D29: Customer Operations | E29: OPS-L2 | F29: L2 | G29: Customer Success Specialist | H29: Bengaluru | I29: Hybrid | J29: 2021-11-18 | K29: Active | M29: N/A - Active | N29: External Agency | O29: 1334000 | P29: 3 | Q29: No | R29: 21 | S29: MGR-301 | T29: =IF(COUNTIF($A$2:A29,A29)>1,"Duplicate","Unique") -> Unique
A30: EMP-10029 | B30: Kiara Verma | C30: DEP-FIN | D30: Finance & Strategy | E30: FIN-L2 | F30: L2 | G30: Senior FP&A Analyst | H30: Hyderabad | I30: On-Site | J30: 2023-08-16 | K30: Involuntary Exit | L30: 2024-04-06 | M30: Performance / Restructuring | N30: Campus Recruitment | O30: 1051000 | P30: 2 | Q30: Yes | R30: 5 | S30: MGR-402 | T30: =IF(COUNTIF($A$2:A30,A30)>1,"Duplicate","Unique") -> Unique
A31: EMP-10030 | B31: Myra Reddy | C31: DEP-MKT | D31: Growth Marketing | E31: MKT-L1 | F31: L1 | G31: Marketing Associate | H31: Mumbai | I31: On-Site | J31: 2024-07-23 | K31: Active | M31: N/A - Active | N31: Campus Recruitment | O31: 849000 | P31: 3 | Q31: No | R31: 26 | S31: MGR-602 | T31: =IF(COUNTIF($A$2:A31,A31)>1,"Duplicate","Unique") -> Unique
A32: EMP-10031 | B32: Shruti Sharma | C32: DEP-OPS | D32: Customer Operations | E32: OPS-L2 | F32: L2 | G32: Customer Success Specialist | H32: Bengaluru | I32: Hybrid | J32: 2021-05-07 | K32: Involuntary Exit | L32: 2021-10-11 | M32: Performance / Restructuring | N32: External Agency | O32: 1140000 | P32: 1 | Q32: No | R32: 9 | S32: MGR-301 | T32: =IF(COUNTIF($A$2:A32,A32)>1,"Duplicate","Unique") -> Unique
A33: EMP-10032 | B33: Pranav Sengupta | C33: DEP-MKT | D33: Growth Marketing | E33: MKT-L4 | F33: L4 | G33: Director of Marketing | H33: Bengaluru | I33: Hybrid | J33: 2025-01-17 | K33: Active | M33: N/A - Active | N33: Employee Referral | O33: 2342000 | P33: 3 | Q33: Yes | R33: 41 | S33: MGR-601 | T33: =IF(COUNTIF($A$2:A33,A33)>1,"Duplicate","Unique") -> Unique
A34: EMP-10033 | B34: kiara malhotra | C34: DEP-MKT | D34: Growth Marketing | E34: MKT-L4 | F34: L4 | G34: Director of Marketing | H34: Mumbai | I34: On-Site | J34: 2022-10-08 | K34: Voluntary Exit | L34: 2025-10-22 | M34: Compensation | N34: LinkedIn Sourcing | O34: 2152000 | P34: 4 | Q34: No | R34: 24 | S34: MGR-601 | T34: =IF(COUNTIF($A$2:A34,A34)>1,"Duplicate","Unique") -> Unique
A35: EMP-10034 | B35: Rohan Menon | C35: DEP-MKT | D35: Marketing - Growth | E35: MKT-L2 | F35: L2 | G35: Growth Specialist | H35: Pune | I35: Hybrid | J35: 2023-11-23 | K35: Voluntary Exit | L35: 2025-04-14 | M35: Career Growth | N35: Employee Referral | O35: 983000 | P35: 5 | Q35: Yes | R35: 29 | S35: MGR-601 | T35: =IF(COUNTIF($A$2:A35,A35)>1,"Duplicate","Unique") -> Unique
A36: EMP-10035 | B36: Rohan Patil | C36: DEP-SAL | D36: Enterprise Sales | E36: SAL-L3 | F36: L3 | G36: Regional Sales Manager | H36: Hyderabad | I36: On-Site | J36: 2024-08-20 | K36: Voluntary Exit | L36: 2025-02-06 | M36: Work-Life Balance | N36: External Agency | O36: 2097000 | P36: 3 | Q36: No | R36: 46 | S36: MGR-201 | T36: =IF(COUNTIF($A$2:A36,A36)>1,"Duplicate","Unique") -> Unique
A37: EMP-10036 | B37: Krishna Chitnis | C37: DEP-HR | D37: People & Talent | E37: -HR-L4 | F37: L4 | G37: Director of People | H37: Pune | I37: Hybrid | J37: 2024-04-12 | K37: Active | M37: N/A - Active | N37: LinkedIn Sourcing | O37: 2670000 | P37: 3 | Q37: No | R37: 28 | S37: MGR-501 | T37: =IF(COUNTIF($A$2:A37,A37)>1,"Duplicate","Unique") -> Unique
A38: EMP-10037 | B38: Riya Shah | C38: DEP-FIN | D38: Finance & Strategy | E38: FIN-L3 | F38: L3 | G38: Finance Manager | H38: Mumbai | I38: On-Site | J38: 2022-11-27 | K38: Involuntary Exit | L38: 2024-06-30 | M38: Performance / Restructuring | N38: LinkedIn Sourcing | O38: 2049000 | P38: 2 | Q38: No | R38: 16 | S38: MGR-401 | T38: =IF(COUNTIF($A$2:A38,A38)>1,"Duplicate","Unique") -> Unique
A39: EMP-10038 | B39: Ayaan Joshi | C39: DEP-OPS | D39: Customer Operations | E39: OPS-L1 | F39: L1 | G39: Operations Coordinator | H39: Pune | I39: Hybrid | J39: 2019-09-05 | K39: Active | M39: N/A - Active | N39: Employee Referral | O39: 731000 | P39: 4 | Q39: Yes | R39: 36 | S39: MGR-303 | T39: =IF(COUNTIF($A$2:A39,A39)>1,"Duplicate","Unique") -> Unique
A40: EMP-10039 | B40: Saanvi Menon | C40: DEP-SAL | D40: Enterprise Sales | E40: SAL-L1 | F40: L1 | G40: Sales Development Rep | H40: Pune | I40: Hybrid | J40: 2021-08-09 | K40: Voluntary Exit | L40: 2023-04-07 | M40: Work-Life Balance | N40: External Agency | O40: 804000 | P40: 3 | Q40: No | R40: 64 | S40: MGR-203 | T40: =IF(COUNTIF($A$2:A40,A40)>1,"Duplicate","Unique") -> Unique
A41: EMP-10040 | B41: Aditya Deshmukh | C41: DEP-FIN | D41: Finance & Strategy | E41: FIN-L5 | F41: L5 | G41: VP of Finance | H41: Pune | I41: Hybrid | J41: 2024-03-21 | K41: Active | M41: N/A - Active | N41: LinkedIn Sourcing | O41: 3691000 | P41: 3 | Q41: No | R41: 58 | S41: MGR-402 | T41: =IF(COUNTIF($A$2:A41,A41)>1,"Duplicate","Unique") -> Unique
A42: EMP-10041 | B42: Neha Bhatt | C42: DEP-SAL | D42: Enterprise Sales | E42: SAL-L1 | F42: L1 | G42: Sales Development Rep | H42: Bengaluru | I42: Hybrid | J42: 2024-02-03 | K42: Involuntary Exit | L42: 2024-09-14 | M42: Performance / Restructuring | N42: Company Career Portal | O42: 757000 | P42: 4 | Q42: No | R42: 21 | S42: MGR-201 | T42: =IF(COUNTIF($A$2:A42,A42)>1,"Duplicate","Unique") -> Unique
A43: EMP-10042 | B43: Pallavi Bhatt | C43: DEP-ENG | D43: Engineering & Prod | E43: ENG-L2 | F43: L2 | G43: Software Engineer II | H43: Hyderabad | I43: On-Site | J43: 2021-07-05 | K43: Active | M43: N/A - Active | N43: Campus Recruitment | O43: 1032000 | P43: 5 | Q43: Yes | R43: 31 | S43: MGR-102 | T43: =IF(COUNTIF($A$2:A43,A43)>1,"Duplicate","Unique") -> Unique
A44: EMP-10043 | B44: Aditya Chitnis | C44: DEP-FIN | D44: Finance & Strategy | E44: FIN-L2 | F44: L2 | G44: Senior FP&A Analyst | H44: Pune | I44: Hybrid | J44: 2021-11-08 | K44: Active | M44: N/A - Active | N44: LinkedIn Sourcing | O44: 1027000 | P44: 3 | Q44: No | R44: 33 | S44: MGR-401 | T44: =IF(COUNTIF($A$2:A44,A44)>1,"Duplicate","Unique") -> Unique
A45: EMP-10044 | B45: Siddharth Shah | C45: DEP-ENG | D45: Engineering & Product | E45: ENG-L2 | F45: L2 | G45: Software Engineer II | H45: Pune | I45: Hybrid | J45: 2022-04-28 | K45: Voluntary Exit | L45: 2022-09-01 | M45: Work-Life Balance | N45: Employee Referral | O45: 1250000 | P45: 3 | Q45: Yes | R45: 58 | S45: MGR-102 | T45: =IF(COUNTIF($A$2:A45,A45)>1,"Duplicate","Unique") -> Unique
A46: EMP-10045 | B46: Sneha kapoor | C46: DEP-OPS | D46: Customer Operations | E46: OPS-L1 | F46: L1 | G46: Operations Coordinator | H46: Bengaluru | I46: Hybrid | J46: 2023-12-26 | K46: Active | M46: N/A - Active | N46: Campus Recruitment | O46: 598000 | P46: 4 | Q46: Yes | R46: 24 | S46: MGR-303 | T46: =IF(COUNTIF($A$2:A46,A46)>1,"Duplicate","Unique") -> Unique
A47: EMP-10046 | B47: Nikhil Kulkarni | C47: DEP-ENG | D47: Engineering & Product | E47: ENG-L2 | F47: L2 | G47: Software Engineer II | H47: Bengaluru | I47: Hybrid | J47: 2025-04-07 | K47: Active | M47: N/A - Active | N47: Campus Recruitment | O47: 1080000 | P47: 3 | Q47: No | R47: 41 | S47: MGR-104 | T47: =IF(COUNTIF($A$2:A47,A47)>1,"Duplicate","Unique") -> Unique
A48: EMP-10047 | B48: Aadhya Nair | C48: DEP-SAL | D48: Enterprise Sales | E48: SAL-L2 | F48: L2 | G48: Account Executive | H48: Pune | I48: Hybrid | J48: 2025-11-07 | K48: Involuntary Exit | L48: 2025-12-22 | M48: Performance / Restructuring | N48: Campus Recruitment | O48: 989000 | P48: 3 | Q48: Yes | R48: 39 | S48: MGR-201 | T48: =IF(COUNTIF($A$2:A48,A48)>1,"Duplicate","Unique") -> Unique
A49: EMP-10048 | B49: Gaurav Malhotra | C49: DEP-ENG | D49: Engineering & Product | E49: ENG-L3 | F49: L3 | G49: Engineering Manager | H49: Bengaluru | I49: Hybrid | J49: 2021-01-04 | K49: Active | M49: N/A - Active | N49: External Agency | O49: 1546000 | P49: 2 | Q49: No | R49: 14 | S49: MGR-103 | T49: =IF(COUNTIF($A$2:A49,A49)>1,"Duplicate","Unique") -> Unique
A50: EMP-10049 | B50: Myra Kulkarni | C50: DEP-OPS | D50: Customer Operations | E50: OPS-L2 | F50: L2 | G50: Customer Success Specialist | H50: Mumbai | I50: On-Site | J50: 2024-10-14 | K50: Active | M50: N/A - Active | N50: External Agency | O50: 1243000 | P50: 3 | Q50: Yes | R50: 42 | S50: MGR-301 | T50: =IF(COUNTIF($A$2:A50,A50)>1,"Duplicate","Unique") -> Unique
A51: EMP-10050 | B51: Gaurav Joshi | C51: DEP-HR | D51: People & Talent | E51: -HR-L5 | F51: L5 | G51: VP of People | H51: Pune | I51: Hybrid | J51: 2024-10-07 | K51: Voluntary Exit | L51: 2025-08-18 | M51: Higher Education | N51: LinkedIn Sourcing | O51: 4676000 | P51: 3 | Q51: Yes | S51: MGR-502 | T51: =IF(COUNTIF($A$2:A51,A51)>1,"Duplicate","Unique") -> Unique
A52: EMP-10051 | B52: Pari Chitnis | C52: DEP-HR | D52: HR / People & Talent | E52: -HR-L2 | F52: L2 | G52: Talent Acquisition Partner | H52: Hyderabad | I52: On-Site | J52: 2020-02-22 | K52: Active | M52: N/A - Active | N52: External Agency | O52: 1162000 | P52: 4 | Q52: No | R52: 51 | S52: MGR-502 | T52: =IF(COUNTIF($A$2:A52,A52)>1,"Duplicate","Unique") -> Unique
A53: EMP-10052 | B53: ayaan rao | C53: DEP-SAL | D53: Enterprise Sales | E53: SAL-L3 | F53: L3 | G53: Regional Sales Manager | H53: Bengaluru | I53: Hybrid | J53: 2025-05-22 | K53: Active | M53: N/A - Active | N53: Employee Referral | O53: 1652000 | P53: 2 | Q53: Yes | S53: MGR-203 | T53: =IF(COUNTIF($A$2:A53,A53)>1,"Duplicate","Unique") -> Unique
A54: EMP-10053 | B54: Krishna iyer | C54: DEP-ENG | D54: Engineering & Product | E54: ENG-L4 | F54: L4 | G54: Director of Engineering | H54: Remote-India | I54: Remote | J54: 2023-11-13 | K54: Active | M54: N/A - Active | N54: Campus Recruitment | O54: 3274000 | P54: 3 | Q54: N | R54: 23 | S54: MGR-104 | T54: =IF(COUNTIF($A$2:A54,A54)>1,"Duplicate","Unique") -> Unique
A55: EMP-10054 | B55: Riya Malhotra | C55: DEP-OPS | D55: Customer Operations | E55: OPS-L3 | F55: L3 | G55: Operations Lead | H55: Hyderabad | I55: On-Site | J55: 2020-01-10 | K55: Voluntary Exit | L55: 2025-05-07 | M55: Career Growth | N55: External Agency | O55: 1672000 | P55: 3 | Q55: Yes | R55: 21 | S55: MGR-303 | T55: =IF(COUNTIF($A$2:A55,A55)>1,"Duplicate","Unique") -> Unique
A56: EMP-10055 | B56: Karan Reddy | C56: DEP-OPS | D56: Customer Operations | E56: OPS-L2 | F56: L2 | G56: Customer Success Specialist | H56: Mumbai | I56: On-Site | J56: 2020-04-17 | K56: Active | M56: N/A - Active | N56: LinkedIn Sourcing | O56: 1301000 | P56: 2 | Q56: Yes | R56: 29 | S56: MGR-303 | T56: =IF(COUNTIF($A$2:A56,A56)>1,"Duplicate","Unique") -> Unique
A57: EMP-10056 | B57: Ananya Patil | C57: DEP-ENG | D57: Engineering & Product | E57: ENG-L1 | F57: L1 | G57: Software Engineer I | H57: Hyderabad | I57: On-Site | J57: 2024-09-22 | K57: Active | M57: N/A - Active | N57: Employee Referral | O57: 651000 | P57: 4 | Q57: No | R57: 52 | S57: MGR-103 | T57: =IF(COUNTIF($A$2:A57,A57)>1,"Duplicate","Unique") -> Unique
A58: EMP-10057 | B58: Kiara Rao | C58: DEP-ENG | D58: Engineering & Product | E58: ENG-L1 | F58: L1 | G58: Software Engineer I | H58: Remote-India | I58: Remote | J58: 2022-04-05 | K58: Active | M58: N/A - Active | N58: LinkedIn Sourcing | O58: 623000 | P58: 4 | Q58: Yes | R58: 28 | S58: MGR-102 | T58: =IF(COUNTIF($A$2:A58,A58)>1,"Duplicate","Unique") -> Unique
A59: EMP-10058 | B59: Arjun Reddy | C59: DEP-ENG | D59: Engineering & Product | E59: ENG-L3 | F59: L3 | G59: Engineering Manager | H59: Pune | I59: Hybrid | J59: 2025-11-19 | K59: Active | M59: N/A - Active | N59: LinkedIn Sourcing | O59: 1872000 | P59: 2 | Q59: Yes | R59: 38 | S59: MGR-104 | T59: =IF(COUNTIF($A$2:A59,A59)>1,"Duplicate","Unique") -> Unique
A60: EMP-10059 | B60: Kiara Sharma | C60: DEP-SAL | D60: Enterprise Sales | E60: SAL-L1 | F60: L1 | G60: Sales Development Rep | H60: Pune | I60: Hybrid | J60: 2020-12-01 | K60: Active | M60: N/A - Active | N60: Employee Referral | O60: 808000 | P60: 2 | Q60: No | R60: 37 | S60: MGR-203 | T60: =IF(COUNTIF($A$2:A60,A60)>1,"Duplicate","Unique") -> Unique
A61: EMP-10060 | B61: Neha Nair | C61: DEP-OPS | D61: Customer Ops | E61: OPS-L4 | F61: L4 | G61: Director of Operations | H61: Bengaluru | I61: Hybrid | J61: 2025-11-11 | K61: Active | M61: N/A - Active | N61: LinkedIn Sourcing | O61: 2424000 | P61: 3 | Q61: YES | R61: 45 | S61: MGR-301 | T61: =IF(COUNTIF($A$2:A61,A61)>1,"Duplicate","Unique") -> Unique
A62: EMP-10061 | B62: Tanvi Sharma | C62: DEP-MKT | D62: Growth Marketing | E62: MKT-L1 | F62: L1 | G62: Marketing Associate | H62: Remote-India | I62: Remote | J62: 2025-11-17 | K62: Active | M62: N/A - Active | N62: Employee Referral | O62: 729000 | P62: 3 | Q62: No | R62: 41 | S62: MGR-602 | T62: =IF(COUNTIF($A$2:A62,A62)>1,"Duplicate","Unique") -> Unique
A63: EMP-10062 | B63: Karan shah | C63: DEP-OPS | D63: Customer Operations | E63: OPS-L2 | F63: L2 | G63: Customer Success Specialist | H63: Hyderabad | I63: On-Site | J63: 2023-09-14 | K63: Active | M63: N/A - Active | N63: LinkedIn Sourcing | O63: 1124000 | P63: 3 | Q63: No | R63: 36 | S63: MGR-303 | T63: =IF(COUNTIF($A$2:A63,A63)>1,"Duplicate","Unique") -> Unique
A64: EMP-10063 | B64: Pranav Reddy | C64: DEP-MKT | D64: Growth Marketing | E64: MKT-L1 | F64: L1 | G64: Marketing Associate | H64: Bengaluru | I64: Hybrid | J64: 2025-04-27 | K64: Active | M64: N/A - Active | N64: Company Career Portal | O64: 780000 | P64: 3 | Q64: No | R64: 18 | S64: MGR-602 | T64: =IF(COUNTIF($A$2:A64,A64)>1,"Duplicate","Unique") -> Unique
A65: EMP-10064 | B65: Kiara menon | C65: DEP-ENG | D65: Engineering & Product | E65: ENG-L2 | F65: L2 | G65: Software Engineer II | H65: Bengaluru | I65: Hybrid | J65: 2020-02-23 | K65: Involuntary Exit | L65: 2021-10-21 | M65: Performance / Restructuring | N65: Campus Recruitment | O65: 986000 | P65: 5 | Q65: Yes | R65: 45 | S65: MGR-104 | T65: =IF(COUNTIF($A$2:A65,A65)>1,"Duplicate","Unique") -> Unique
A66: EMP-10065 | B66: Ishaan Nair | C66: DEP-OPS | D66: Customer Operations | E66: OPS-L2 | F66: L2 | G66: Customer Success Specialist | H66: Bengaluru | I66: Hybrid | J66: 2024-12-05 | K66: Active | M66: N/A - Active | N66: External Agency | O66: 882000 | P66: 2 | Q66: No | R66: 6 | S66: MGR-302 | T66: =IF(COUNTIF($A$2:A66,A66)>1,"Duplicate","Unique") -> Unique
A67: EMP-10066 | B67: Yash Reddy | C67: DEP-MKT | D67: Marketing - Growth | E67: MKT-L3 | F67: L3 | G67: Product Marketing Manager | H67: Bengaluru | I67: Hybrid | J67: 2022-01-07 | K67: Active | M67: N/A - Active | N67: Employee Referral | O67: 1642000 | P67: 4 | Q67: No | S67: MGR-602 | T67: =IF(COUNTIF($A$2:A67,A67)>1,"Duplicate","Unique") -> Unique
A68: EMP-10067 | B68: Vivaan Mehta | C68: DEP-MKT | D68: Growth Marketing | E68: MKT-L1 | F68: L1 | G68: Marketing Associate | H68: pune | I68: Hybrid | J68: 2025-08-01 | K68: Active | M68: N/A - Active | N68: LinkedIn Sourcing | O68: 640000 | Q68: No | R68: 34 | S68: MGR-602 | T68: =IF(COUNTIF($A$2:A68,A68)>1,"Duplicate","Unique") -> Unique
A69: EMP-10068 | B69: Siddharth Bhatt | C69: DEP-SAL | D69: Enterprise Sales | E69: SAL-L1 | F69: L1 | G69: Sales Development Rep | H69: Bengaluru | I69: Hybrid | J69: 2024-12-18 | K69: Active | M69: N/A - Active | N69: Company Career Portal | O69: 819000 | P69: 5 | Q69: No | S69: MGR-203 | T69: =IF(COUNTIF($A$2:A69,A69)>1,"Duplicate","Unique") -> Unique
A70: EMP-10069 | B70: Ira Kapoor | C70: DEP-MKT | D70: Growth Marketing | E70: MKT-L2 | F70: L2 | G70: Growth Specialist | H70: Hyderabad | I70: On-Site | J70: 2024-01-13 | K70: Active | M70: N/A - Active | N70: Company Career Portal | O70: 1190000 | P70: 3 | Q70: Yes | R70: 23 | S70: MGR-602 | T70: =IF(COUNTIF($A$2:A70,A70)>1,"Duplicate","Unique") -> Unique
A71: EMP-10070 | B71: Ananya Reddy | C71: DEP-MKT | D71: Growth Marketing | E71: MKT-L2 | F71: L2 | G71: Growth Specialist | H71: Bengaluru | I71: Hybrid | J71: 2023-10-18 | K71: Active | M71: N/A - Active | N71: Campus Recruitment | O71: 1047000 | P71: 3 | Q71: Yes | R71: 34 | S71: MGR-601 | T71: =IF(COUNTIF($A$2:A71,A71)>1,"Duplicate","Unique") -> Unique
A72: EMP-10071 | B72: Vivaan Patil | C72: DEP-ENG | D72: Engineering & Product | E72: ENG-L2 | F72: L2 | G72: Software Engineer II | H72: Pune | I72: Hybrid | J72: 2023-03-28 | K72: Active | M72: N/A - Active | N72: External Agency | O72: 875000 | P72: 4 | Q72: No | R72: 60 | S72: MGR-104 | T72: =IF(COUNTIF($A$2:A72,A72)>1,"Duplicate","Unique") -> Unique
A73: EMP-10072 | B73: Saanvi Reddy | C73: DEP-HR | D73: People & Talent | E73: -HR-L2 | F73: L2 | G73: Talent Acquisition Partner | H73: Bengaluru | I73: Hybrid | J73: 2024-06-25 | K73: Active | M73: N/A - Active | N73: Employee Referral | O73: 989000 | P73: 3 | Q73: No | R73: 57 | S73: MGR-502 | T73: =IF(COUNTIF($A$2:A73,A73)>1,"Duplicate","Unique") -> Unique
A74: EMP-10073 | B74: Siddharth Menon | C74: DEP-FIN | D74: Finance & Strategy | E74: FIN-L1 | F74: L1 | G74: Financial Analyst | H74: Bengaluru | I74: Hybrid | J74: 2022-08-01 | K74: Active | M74: N/A - Active | N74: Employee Referral | O74: 566000 | P74: 3 | Q74: No | R74: 21 | S74: MGR-401 | T74: =IF(COUNTIF($A$2:A74,A74)>1,"Duplicate","Unique") -> Unique
A75: EMP-10074 | B75: Aadhya Patil | C75: DEP-MKT | D75: Growth Marketing | E75: MKT-L1 | F75: L1 | G75: Marketing Associate | H75: Pune | I75: Hybrid | J75: 2022-01-08 | K75: Voluntary Exit | L75: 2022-04-11 | M75: Relocation | N75: External Agency | O75: 556000 | P75: 3 | Q75: Yes | R75: 11 | S75: MGR-601 | T75: =IF(COUNTIF($A$2:A75,A75)>1,"Duplicate","Unique") -> Unique
A76: EMP-10075 | B76: Omkar Iyer | C76: DEP-MKT | D76: Growth Marketing | E76: MKT-L1 | F76: L1 | G76: Marketing Associate | H76: Mumbai | I76: On-Site | J76: 2021-12-09 | K76: Active | M76: N/A - Active | N76: LinkedIn Sourcing | O76: 600000 | P76: 3 | Q76: No | R76: 35 | S76: MGR-602 | T76: =IF(COUNTIF($A$2:A76,A76)>1,"Duplicate","Unique") -> Unique
